Workbook

Sheet Start
C2: Palmetto Stay — Portfolio Release v1.0
C4: SYNTHETIC DATA: Palmetto Stay is fictional. All company-specific budgets, actuals, operating records, staffing information, and management updates are synthetic and contain no confidential company information.
C7: Workbook purpose | D7: Review recorded actuals and the approved budget, analyze first-half performance, and evaluate the 2026 RF1 Base, Upside, and Downside outlooks.
C8: Case version | D8: v1.0
C9: Current build status | D9: Portfolio Release v1.0 — independently validated within the project scope; actuals through June 2026; RF1 dated July 8, 2026.
C10: Analysis cutoff | D10: 46211
C11: Worksheet | D11: Role | E11: Portfolio release status
C12: Start | D12: Purpose, navigation, conventions, and use instructions | E12: Complete
C13: Data | D13: Frozen recorded actuals and dated case information | E13: Validated
C14: Assumptions | D14: Frozen approved 2026 budget drivers | E14: Validated
C15: Budget | D15: Formula-driven approved 2026 operating budget | E15: Complete
C16: Forecast | D16: Actualized forecast and scenarios | E16: Complete
C17: Variance | D17: Actual-versus-budget analysis | E17: Complete
C18: Review | D18: Two-page management-facing review | E18: Complete
C19: Checks | D19: Terminal source, model, aggregation, and package controls | E19: Complete
C21: Model-use instructions | D21: Review the frozen source tables, trace actuals through Variance, trace the outlook through Forecast and Assumptions, and inspect formulas before using results.
C22: Required control step | D22: Review the Checks tab before relying on this workbook. This instruction is static and is not linked to a check result.
C23: Later-phase status | D23: Portfolio Release v1.0 is complete: Budget, Variance, Forecast, Review, and all 179 terminal Checks are validated within the project scope.
C24: Expense convention | D24: Expenses are positive values and are subtracted when calculating property operating contribution.
C25: Variance convention | D25: Revenue and contribution use Actual minus Budget; expense tables also use Actual cost minus Budget cost, while contribution impacts reverse expense changes.
C28: Color and format legend | D28: Meaning
C29: Approved source input | D29: Blue font with pale-yellow fill
C30: Recorded source fact | D30: Dark text with pale-blue fill
C31: Cross-sheet formula | D31: Green font
C32: Same-sheet formula or result | D32: Black font
C34: Property | D34: One independently operated, leased limited-service hotel with 100 rooms
C35: Scope | D35: Room revenue and modeled property operating costs only

Sheet Data
C2: Frozen source data
C3: Static imports from case version v1.0. Actual KPIs and variances are intentionally not calculated on this sheet.
C5: Source: data/financial_actuals.csv | Case version: v1.0 | Static recorded facts
C7: case_version | D7: period | E7: account_code | F7: account_name | G7: amount_usd
C8: v1.0 | D8: 45658 | E8: 4000 | F8: Room Revenue | G8: 223203.5
C9: v1.0 | D9: 45658 | E9: 5000 | F9: Housekeeping Payroll | G9: 18834.45
C10: v1.0 | D10: 45658 | E10: 5100 | F10: Guest Services | G10: 28458
C11: v1.0 | D11: 45658 | E11: 5200 | F11: Distribution and Payment | G11: 8928.14
C12: v1.0 | D12: 45658 | E12: 6000 | F12: Fixed Staff Payroll | G12: 28750
C13: v1.0 | D13: 45658 | E13: 6100 | F13: Rent | G13: 76000
C14: v1.0 | D14: 45658 | E14: 6200 | F14: Property Overhead | G14: 26800
C15: v1.0 | D15: 45658 | E15: 6300 | F15: Marketing | G15: 9000
C16: v1.0 | D16: 45689 | E16: 4000 | F16: Room Revenue | G16: 221271
C17: v1.0 | D17: 45689 | E17: 5000 | F17: Housekeeping Payroll | G17: 18110.4
C18: v1.0 | D18: 45689 | E18: 5100 | F18: Guest Services | G18: 28028
C19: v1.0 | D19: 45689 | E19: 5200 | F19: Distribution and Payment | G19: 8850.84
... C151: v1.0 | D151: 46174 | E151: 6300 | F151: Marketing | G151: 6000
C155: Source: data/operating_actuals.csv | Case version: v1.0 | Static recorded facts
C157: case_version | D157: period | E157: segment | F157: occupied_room_nights | G157: room_revenue
C158: v1.0 | D158: 45658 | E158: Retail/Leisure | F158: 1154 | G158: 167907
C159: v1.0 | D159: 45658 | E159: Negotiated Corporate | F159: 427 | G159: 55296.5
C160: v1.0 | D160: 45689 | E160: Retail/Leisure | F160: 1109 | G160: 165241
C161: v1.0 | D161: 45689 | E161: Negotiated Corporate | F161: 431 | G161: 56030
C162: v1.0 | D162: 45717 | E162: Retail/Leisure | F162: 1367 | G162: 211201.5
C163: v1.0 | D163: 45717 | E163: Negotiated Corporate | F163: 586 | G163: 78231
C164: v1.0 | D164: 45748 | E164: Retail/Leisure | F164: 1387 | G164: 220533
C165: v1.0 | D165: 45748 | E165: Negotiated Corporate | F165: 623 | G165: 85974
C166: v1.0 | D166: 45778 | E166: Retail/Leisure | F166: 1518 | G166: 257301
C167: v1.0 | D167: 45778 | E167: Negotiated Corporate | F167: 714 | G167: 101745
C168: v1.0 | D168: 45809 | E168: Retail/Leisure | F168: 1505 | G168: 264127.5
C169: v1.0 | D169: 45809 | E169: Negotiated Corporate | F169: 775 | G169: 111987.5
... C193: v1.0 | D193: 46174 | E193: Negotiated Corporate | F193: 951 | G193: 141223.5
C197: Source: data/labor_actuals.csv | Case version: v1.0 | Static recorded facts
C199: case_version | D199: period | E199: housekeeping_hours | F199: housekeeping_payroll | G199: fixed_staff_fte | H199: fixed_staff_payroll
C200: v1.0 | D200: 45658 | E200: 901.17 | F200: 18834.45 | G200: 5 | H200: 28750
C201: v1.0 | D201: 45689 | E201: 862.4 | F201: 18110.4 | G201: 5 | H201: 28800
C202: v1.0 | D202: 45717 | E202: 1074.15 | F202: 22610.86 | G202: 4.9 | H202: 28322
C203: v1.0 | D203: 45748 | E203: 1105.5 | F203: 23436.6 | G203: 5 | H203: 29000
C204: v1.0 | D204: 45778 | E204: 1182.96 | F204: 25137.9 | G204: 5 | H204: 29100
C205: v1.0 | D205: 45809 | E205: 1208.4 | F205: 25738.92 | G205: 5 | H205: 29200
C206: v1.0 | D206: 45839 | E206: 1286.5 | F206: 27595.43 | G206: 5.1 | H206: 29886
C207: v1.0 | D207: 45870 | E207: 1264.8 | F207: 27193.2 | G207: 5.1 | H207: 29988
C208: v1.0 | D208: 45901 | E208: 1134 | F208: 24437.7 | G208: 5 | H208: 29500
C209: v1.0 | D209: 45931 | E209: 1138.32 | F209: 24701.54 | G209: 5 | H209: 29600
C210: v1.0 | D210: 45962 | E210: 957 | F210: 20814.75 | G210: 5 | H210: 29700
C211: v1.0 | D211: 45992 | E211: 971.85 | F211: 21186.33 | G211: 5 | H211: 29800
... C217: v1.0 | D217: 46174 | E217: 1268.4 | F217: 29490.3 | G217: 5 | H217: 30250
C221: Source: data/case_updates.csv | Information cutoff: July 8, 2026 | Static case information
C223: update_id | D223: as_of_date | E223: effective_start | F223: effective_end | G223: category | H223: observation | I223: evidence_status | J223: forecast_relevance
C224: UPD-2026-001 | D224: 46127 | E224: 46082 | F224: 46173 | G224: Demand | H224: Weekly property records show retail/leisure occupied room nights below the approved planning pattern during March and April. | I224: Confirmed | J224: Use the dated results when reassessing second-half retail/leisure demand.
C225: UPD-2026-002 | D225: 46162 | E225: 46082 | F225: 46203 | G225: Customer Mix | H225: Negotiated corporate accounts generated additional transient room nights during the spring; no guaranteed room blocks are in place. | I225: Confirmed | J225: Separate customer mix from total demand when updating the outlook.
C226: UPD-2026-003 | D226: 46099 | E226: 46113 | F226: 46387 | G226: Labor Rate | H226: The loaded housekeeping wage increases to 23.25 per hour on April 1. | I226: Confirmed | J226: Apply the confirmed wage schedule from its effective date.
C227: UPD-2026-004 | D227: 46193 | E227: 46113 | F227: 46203 | G227: Labor Productivity | H227: Property logs record higher housekeeping hours during April and May; management expects the transition to continue easing after June. | I227: Management Estimate | J227: Retain the observed disruption and document any future normalization assumption.
C228: UPD-2026-005 | D228: 46197 | E228: 46174 | F228: 46295 | G228: Marketing Timing | H228: The marketing activity scheduled for June was not delivered and has been rescheduled for September. | I228: Confirmed | J228: Reflect service timing rather than payment timing in future assumptions.
C229: UPD-2026-006 | D229: 46203 | E229: 46143 | F229: 46173 | G229: Property Overhead | H229: A modest May property-overhead increase remains under vendor-detail review; available records do not establish a definitive cause. | I229: Unconfirmed | J229: Request invoice detail before changing ongoing overhead assumptions.
C230: UPD-2026-007 | D230: 46211 | E230: 46204 | F230: 46387 | G230: Demand Outlook | H230: Management's current view assumes partial second-half retail/leisure recovery, subject to summer pickup. | I230: Management Estimate | J230: Use only as a documented future assumption; recorded actuals remain unchanged.

Sheet Assumptions
C2: Approved 2026 budget assumptions
C3: The frozen approved plan is the single authoritative source for the Budget sheet.
C5: Source: data/approved_budget_assumptions.csv | Case version: v1.0 | Approved before 2026 actual results
C7: case_version | D7: period | E7: rooms_available | F7: total_occupied_room_nights | G7: corporate_share | H7: retail_adr | I7: corporate_adr | J7: housekeeping_hours_per_occupied_room | K7: housekeeping_loaded_wage_per_hour | L7: guest_service_cost_per_occupied_room | M7: distribution_fee_rate | N7: fixed_staff_fte | O7: fixed_staff_loaded_cost_per_fte | P7: rent | Q7: property_overhead | R7: marketing
C8: v1.0 | D8: 46023 | E8: 100 | F8: 1705 | G8: 0.3 | H8: 150 | I8: 132 | J8: 0.56 | K8: 22 | L8: 18.5 | M8: 0.04 | N8: 5 | O8: 6000 | P8: 78000 | Q8: 28000 | R8: 10000
C9: v1.0 | D9: 46054 | E9: 100 | F9: 1624 | G9: 0.31 | H9: 152 | I9: 133 | J9: 0.55 | K9: 22 | L9: 18.7 | M9: 0.04 | N9: 5 | O9: 6000 | P9: 78000 | Q9: 28100 | R9: 9000
C10: v1.0 | D10: 46082 | E10: 100 | F10: 2015 | G10: 0.32 | H10: 158 | I10: 137 | J10: 0.54 | K10: 22 | L10: 19 | M10: 0.04 | N10: 5 | O10: 6000 | P10: 78000 | Q10: 28500 | R10: 11000
C11: v1.0 | D11: 46113 | E11: 100 | F11: 2100 | G11: 0.34 | H11: 164 | I11: 140 | J11: 0.53 | K11: 22 | L11: 19.2 | M11: 0.04 | N11: 5 | O11: 6000 | P11: 78000 | Q11: 28600 | R11: 13000
C12: v1.0 | D12: 46143 | E12: 100 | F12: 2294 | G12: 0.35 | H12: 172 | I12: 145 | J12: 0.52 | K12: 22 | L12: 19.5 | M12: 0.04 | N12: 5 | O12: 6000 | P12: 78000 | Q12: 28900 | R12: 14000
C13: v1.0 | D13: 46174 | E13: 100 | F13: 2340 | G13: 0.36 | H13: 180 | I13: 148 | J13: 0.51 | K13: 22 | L13: 19.8 | M13: 0.04 | N13: 5 | O13: 6000 | P13: 78000 | Q13: 29200 | R13: 24000
C14: v1.0 | D14: 46204 | E14: 100 | F14: 2604 | G14: 0.38 | H14: 188 | I14: 153 | J14: 0.5 | K14: 22.75 | L14: 20 | M14: 0.04 | N14: 5 | O14: 6120 | P14: 78000 | Q14: 29800 | R14: 18000
C15: v1.0 | D15: 46235 | E15: 100 | F15: 2542 | G15: 0.39 | H15: 185 | I15: 151 | J15: 0.5 | K15: 22.75 | L15: 20 | M15: 0.04 | N15: 5 | O15: 6120 | P15: 78000 | Q15: 30000 | R15: 15000
C16: v1.0 | D16: 46266 | E16: 100 | F16: 2190 | G16: 0.4 | H16: 175 | I16: 146 | J16: 0.52 | K16: 22.75 | L16: 19.8 | M16: 0.04 | N16: 5 | O16: 6120 | P16: 78000 | Q16: 29400 | R16: 12000
C17: v1.0 | D17: 46296 | E17: 100 | F17: 2201 | G17: 0.38 | H17: 170 | I17: 144 | J17: 0.53 | K17: 22.75 | L17: 19.5 | M17: 0.04 | N17: 5 | O17: 6120 | P17: 78000 | Q17: 29100 | R17: 13000
C18: v1.0 | D18: 46327 | E18: 100 | F18: 1830 | G18: 0.34 | H18: 158 | I18: 138 | J18: 0.55 | K18: 22.75 | L18: 19 | M18: 0.04 | N18: 5 | O18: 6120 | P18: 78000 | Q18: 28700 | R18: 12000
C19: v1.0 | D19: 46357 | E19: 100 | F19: 1829 | G19: 0.32 | H19: 162 | I19: 140 | J19: 0.56 | K19: 22.75 | L19: 19.2 | M19: 0.04 | N19: 5 | O19: 6120 | P19: 78000 | Q19: 29000 | R19: 16000
C22: Input treatment | D22: Static approved source values; do not overwrite for forecast or scenarios.
C23: Date convention | D23: Monthly period keys use the first day of each month.
C24: Budget link | D24: Budget formulas match each monthly header to this table.
C25: Formatting | D25: Blue font and pale-yellow fill identify approved source inputs.
C28: 2026 RF1 assumptions
C29: A later analytical layer for July–December 2026. The approved budget assumptions above remain frozen and are not overwritten.
C31: Forecast controls
C32: Forecast version | D32: 2026 RF1 | F32: Case version | G32: v1.0 | I32: Information cutoff | J32: 46211 | L32: Actual through | M32: 46174 | O32: First forecast | P32: 46204 | Q32: Last forecast | R32: 46357
C34: Base | D34: Official working reforecast: partial retail recovery, continued corporate support, structural wage rate, staged productivity normalization, and deferred September marketing.
C35: Upside | D35: Bounded sensitivity: stronger demand and pricing with faster housekeeping productivity normalization.
C36: Downside | D36: Bounded sensitivity: persistent demand weakness, less corporate offset, rate pressure, and slower productivity normalization.
C37: Scenario ranges support decisions; they are not probability weighted and are not confidence intervals. RF1 accuracy cannot be evaluated until later actuals exist.
C39: Base case monthly assumptions
C40: Driver | D40: Basis type | E40: Source / update | F40: Jul-26 | G40: Aug-26 | H40: Sep-26 | I40: Oct-26 | J40: Nov-26 | K40: Dec-26
C41: Rooms available | D41: Approved budget | E41: Approved assumption pack | F41: 100 | G41: 100 | H41: 100 | I41: 100 | J41: 100 | K41: 100
C42: Occupied room nights | D42: Analyst judgment | E42: UPD-2026-001, 002, 007 | F42: 2552 | G42: 2491 | H42: 2146 | I42: 2168 | J42: 1812 | K42: 1811
C43: Corporate share | D43: Actual run rate | E43: UPD-2026-002 | F43: 0.41 | G43: 0.42 | H43: 0.43 | I43: 0.405 | J43: 0.36 | K43: 0.335
C44: Retail ADR | D44: Approved budget | E44: Approved assumption pack | F44: 188 | G44: 185 | H44: 175 | I44: 170 | J44: 158 | K44: 162
C45: Corporate ADR | D45: Actual run rate | E45: Recorded actuals and budget | F45: 153.5 | G45: 151.5 | H45: 146.5 | I45: 144.5 | J45: 138.5 | K45: 140.5
C46: Housekeeping hours per occupied room | D46: Analyst judgment | E46: UPD-2026-004 | F46: 0.55 | G46: 0.54 | H46: 0.53 | I46: 0.53 | J46: 0.55 | K46: 0.56
C47: Housekeeping loaded wage per hour | D47: Case update | E47: UPD-2026-003 | F47: 23.25 | G47: 23.25 | H47: 23.25 | I47: 23.25 | J47: 23.25 | K47: 23.25
C48: Guest-service cost per occupied room | D48: Approved budget | E48: Approved assumption pack | F48: 20 | G48: 20 | H48: 19.8 | I48: 19.5 | J48: 19 | K48: 19.2
C49: Distribution fee rate | D49: Approved budget | E49: Locked 4% policy | F49: 0.04 | G49: 0.04 | H49: 0.04 | I49: 0.04 | J49: 0.04 | K49: 0.04
C50: Fixed-staff FTE | D50: Approved budget | E50: Approved assumption pack | F50: 5 | G50: 5 | H50: 5 | I50: 5 | J50: 5 | K50: 5
C51: Fixed-staff loaded cost per FTE | D51: Approved budget | E51: Approved assumption pack | F51: 6120 | G51: 6120 | H51: 6120 | I51: 6120 | J51: 6120 | K51: 6120
C52: Rent | D52: Approved budget | E52: Approved assumption pack | F52: 78000 | G52: 78000 | H52: 78000 | I52: 78000 | J52: 78000 | K52: 78000
... C54: Marketing | D54: Case update | E54: UPD-2026-005 | F54: 18000 | G54: 15000 | H54: 30000 | I54: 13000 | J54: 12000 | K54: 16000
C56: Base assumption rationale
C57: Demand | D57: H1 weakness is retained, but monthly budget seasonality and the July 8 management estimate support a partial rather than immediate recovery. Corporate support offsets part of continued retail softness.
C58: Customer mix | D58: Spring actuals and UPD-2026-002 support elevated corporate share through year-end without treating negotiated activity as guaranteed.
C59: Pricing | D59: Retail ADR stays at the approved monthly path because realized H1 rates were near plan. Corporate ADR adds a modest $0.50 to the approved path based on recent realized rates.
C60: Wage | D60: The confirmed April 1 loaded wage of $23.25 remains structural through December in every scenario.
C61: Productivity | D61: The April–May disruption eases after June and reaches the approved monthly path by October in Base.
C62: Guest service | D62: No dated evidence supports a new unit-cost path, so the approved monthly assumptions remain in every scenario.
C63: Fixed staffing and rent | D63: The approved H2 staffing, loaded cost, and rent remain unchanged because no source supports a revision.
C64: Marketing | D64: The $18,000 June activity that was not delivered is added to September. Other H2 monthly amounts remain at budget.
C65: Property overhead | D65: The unconfirmed May item is not annualized. Approved H2 monthly overhead remains unchanged pending vendor detail.
C67: Upside scenario assumptions — changes from Base only
C68: Driver | D68: Basis type | E68: Source / update | F68: Jul-26 | G68: Aug-26 | H68: Sep-26 | I68: Oct-26 | J68: Nov-26 | K68: Dec-26
C69: Occupied room nights | D69: Analyst judgment | E69: UPD-2026-007 | F69: 2629 | G69: 2566 | H69: 2200 | I69: 2222 | J69: 1848 | K69: 1847
C70: Corporate share | D70: Analyst judgment | E70: UPD-2026-002 | F70: 0.415 | G70: 0.425 | H70: 0.435 | I70: 0.41 | J70: 0.365 | K70: 0.34
C71: Retail ADR | D71: Analyst judgment | E71: Budget plus 1% | F71: 189.88 | G71: 186.85 | H71: 176.75 | I71: 171.7 | J71: 159.58 | K71: 163.62
C72: Corporate ADR | D72: Analyst judgment | E72: Base plus 0.5% | F72: 154.27 | G72: 152.26 | H72: 147.23 | I72: 145.22 | J72: 139.19 | K72: 141.2
C73: Housekeeping hours per occupied room | D73: Analyst judgment | E73: UPD-2026-004 | F73: 0.53 | G73: 0.51 | H73: 0.52 | I73: 0.53 | J73: 0.55 | K73: 0.56
C75: Downside scenario assumptions — changes from Base only
C76: Driver | D76: Basis type | E76: Source / update | F76: Jul-26 | G76: Aug-26 | H76: Sep-26 | I76: Oct-26 | J76: Nov-26 | K76: Dec-26
C77: Occupied room nights | D77: Analyst judgment | E77: UPD-2026-001, 007 | F77: 2450 | G77: 2391 | H77: 2039 | I77: 2060 | J77: 1721 | K77: 1720
C78: Corporate share | D78: Analyst judgment | E78: UPD-2026-002 | F78: 0.395 | G78: 0.405 | H78: 0.415 | I78: 0.39 | J78: 0.345 | K78: 0.32
C79: Retail ADR | D79: Analyst judgment | E79: Base less 2% | F79: 184.24 | G79: 181.3 | H79: 171.5 | I79: 166.6 | J79: 154.84 | K79: 158.76
C80: Corporate ADR | D80: Analyst judgment | E80: Base less 1% | F80: 151.97 | G80: 149.99 | H80: 145.04 | I80: 143.06 | J80: 137.12 | K80: 139.1
C81: Housekeeping hours per occupied room | D81: Analyst judgment | E81: UPD-2026-004 | F81: 0.57 | G81: 0.56 | H81: 0.55 | I81: 0.54 | J81: 0.56 | K81: 0.57
C83: All drivers not listed in the scenario sections use Base. Scenario differences apply only to July–December 2026.

Sheet Budget
C2: Approved 2026 operating budget
C3: Formula-driven build from the frozen approved assumption pack. Expenses are shown as positive values.
C5: Metric | D5: 46023 | E5: 46054 | F5: 46082 | G5: 46113 | H5: 46143 | I5: 46174 | J5: 46204 | K5: 46235 | L5: 46266 | M5: 46296 | N5: 46327 | O5: 46357 | P5: FY2026
C6: FY column uses sums for additive lines and weighted or average calculations for rates and monthly levels.
C7: Operating drivers
C8: Rooms available | D8: =INDEX(Assumptions!$E$8:$E$19,MATCH(D$5,Assumptions!$D$8:$D$19,0)) -> 100 | E8: =INDEX(Assumptions!$E$8:$E$19,MATCH(E$5,Assumptions!$D$8:$D$19,0)) -> 100 | F8: =INDEX(Assumptions!$E$8:$E$19,MATCH(F$5,Assumptions!$D$8:$D$19,0)) -> 100 | G8: =INDEX(Assumptions!$E$8:$E$19,MATCH(G$5,Assumptions!$D$8:$D$19,0)) -> 100 | H8: =INDEX(Assumptions!$E$8:$E$19,MATCH(H$5,Assumptions!$D$8:$D$19,0)) -> 100 | I8: =INDEX(Assumptions!$E$8:$E$19,MATCH(I$5,Assumptions!$D$8:$D$19,0)) -> 100 | J8: =INDEX(Assumptions!$E$8:$E$19,MATCH(J$5,Assumptions!$D$8:$D$19,0)) -> 100 | K8: =INDEX(Assumptions!$E$8:$E$19,MATCH(K$5,Assumptions!$D$8:$D$19,0)) -> 100 | ... O8: =INDEX(Assumptions!$E$8:$E$19,MATCH(O$5,Assumptions!$D$8:$D$19,0)) -> 100 | P8: =AVERAGE(D8:O8) -> 100
C9: Calendar days | D9: =DATE(YEAR(D$5),MONTH(D$5)+1,1)-D$5 -> 31 | E9: =DATE(YEAR(E$5),MONTH(E$5)+1,1)-E$5 -> 28 | F9: =DATE(YEAR(F$5),MONTH(F$5)+1,1)-F$5 -> 31 | G9: =DATE(YEAR(G$5),MONTH(G$5)+1,1)-G$5 -> 30 | H9: =DATE(YEAR(H$5),MONTH(H$5)+1,1)-H$5 -> 31 | I9: =DATE(YEAR(I$5),MONTH(I$5)+1,1)-I$5 -> 30 | J9: =DATE(YEAR(J$5),MONTH(J$5)+1,1)-J$5 -> 31 | K9: =DATE(YEAR(K$5),MONTH(K$5)+1,1)-K$5 -> 31 | ... O9: =DATE(YEAR(O$5),MONTH(O$5)+1,1)-O$5 -> 31 | P9: =SUM(D9:O9) -> 365
C10: Available room nights | D10: =D8*D9 -> 3100 | E10: =E8*E9 -> 2800 | F10: =F8*F9 -> 3100 | G10: =G8*G9 -> 3000 | H10: =H8*H9 -> 3100 | I10: =I8*I9 -> 3000 | J10: =J8*J9 -> 3100 | K10: =K8*K9 -> 3100 | ... O10: =O8*O9 -> 3100 | P10: =SUM(D10:O10) -> 36500
C11: Total occupied room nights | D11: =INDEX(Assumptions!$F$8:$F$19,MATCH(D$5,Assumptions!$D$8:$D$19,0)) -> 1705 | E11: =INDEX(Assumptions!$F$8:$F$19,MATCH(E$5,Assumptions!$D$8:$D$19,0)) -> 1624 | F11: =INDEX(Assumptions!$F$8:$F$19,MATCH(F$5,Assumptions!$D$8:$D$19,0)) -> 2015 | G11: =INDEX(Assumptions!$F$8:$F$19,MATCH(G$5,Assumptions!$D$8:$D$19,0)) -> 2100 | H11: =INDEX(Assumptions!$F$8:$F$19,MATCH(H$5,Assumptions!$D$8:$D$19,0)) -> 2294 | I11: =INDEX(Assumptions!$F$8:$F$19,MATCH(I$5,Assumptions!$D$8:$D$19,0)) -> 2340 | J11: =INDEX(Assumptions!$F$8:$F$19,MATCH(J$5,Assumptions!$D$8:$D$19,0)) -> 2604 | K11: =INDEX(Assumptions!$F$8:$F$19,MATCH(K$5,Assumptions!$D$8:$D$19,0)) -> 2542 | ... O11: =INDEX(Assumptions!$F$8:$F$19,MATCH(O$5,Assumptions!$D$8:$D$19,0)) -> 1829 | P11: =SUM(D11:O11) -> 25274
C12: Occupancy | D12: =D11/D10 -> 0.55 | E12: =E11/E10 -> 0.58 | F12: =F11/F10 -> 0.65 | G12: =G11/G10 -> 0.7 | H12: =H11/H10 -> 0.74 | I12: =I11/I10 -> 0.78 | J12: =J11/J10 -> 0.84 | K12: =K11/K10 -> 0.82 | ... P12: =P11/P10 -> 0.69243836
C13: Corporate share | D13: =INDEX(Assumptions!$G$8:$G$19,MATCH(D$5,Assumptions!$D$8:$D$19,0)) -> 0.3 | E13: =INDEX(Assumptions!$G$8:$G$19,MATCH(E$5,Assumptions!$D$8:$D$19,0)) -> 0.31 | F13: =INDEX(Assumptions!$G$8:$G$19,MATCH(F$5,Assumptions!$D$8:$D$19,0)) -> 0.32 | G13: =INDEX(Assumptions!$G$8:$G$19,MATCH(G$5,Assumptions!$D$8:$D$19,0)) -> 0.34 | H13: =INDEX(Assumptions!$G$8:$G$19,MATCH(H$5,Assumptions!$D$8:$D$19,0)) -> 0.35 | I13: =INDEX(Assumptions!$G$8:$G$19,MATCH(I$5,Assumptions!$D$8:$D$19,0)) -> 0.36 | J13: =INDEX(Assumptions!$G$8:$G$19,MATCH(J$5,Assumptions!$D$8:$D$19,0)) -> 0.38 | K13: =INDEX(Assumptions!$G$8:$G$19,MATCH(K$5,Assumptions!$D$8:$D$19,0)) -> 0.39 | ... O13: =INDEX(Assumptions!$G$8:$G$19,MATCH(O$5,Assumptions!$D$8:$D$19,0)) -> 0.32 | P13: =P15/P11 -> 0.35292395
C14: Retail room nights | D14: =D11-D15 -> 1193.5 | E14: =E11-E15 -> 1120.56 | F14: =F11-F15 -> 1370.2 | G14: =G11-G15 -> 1386 | H14: =H11-H15 -> 1491.1 | I14: =I11-I15 -> 1497.6 | J14: =J11-J15 -> 1614.48 | K14: =K11-K15 -> 1550.62 | ... O14: =O11-O15 -> 1243.72 | P14: =SUM(D14:O14) -> 16354.2
C15: Corporate room nights | D15: =D11*D13 -> 511.5 | E15: =E11*E13 -> 503.44 | F15: =F11*F13 -> 644.8 | G15: =G11*G13 -> 714 | H15: =H11*H13 -> 802.9 | I15: =I11*I13 -> 842.4 | J15: =J11*J13 -> 989.52 | K15: =K11*K13 -> 991.38 | ... O15: =O11*O13 -> 585.28 | P15: =SUM(D15:O15) -> 8919.8
C16: Retail ADR | D16: =INDEX(Assumptions!$H$8:$H$19,MATCH(D$5,Assumptions!$D$8:$D$19,0)) -> 150 | E16: =INDEX(Assumptions!$H$8:$H$19,MATCH(E$5,Assumptions!$D$8:$D$19,0)) -> 152 | F16: =INDEX(Assumptions!$H$8:$H$19,MATCH(F$5,Assumptions!$D$8:$D$19,0)) -> 158 | G16: =INDEX(Assumptions!$H$8:$H$19,MATCH(G$5,Assumptions!$D$8:$D$19,0)) -> 164 | H16: =INDEX(Assumptions!$H$8:$H$19,MATCH(H$5,Assumptions!$D$8:$D$19,0)) -> 172 | I16: =INDEX(Assumptions!$H$8:$H$19,MATCH(I$5,Assumptions!$D$8:$D$19,0)) -> 180 | J16: =INDEX(Assumptions!$H$8:$H$19,MATCH(J$5,Assumptions!$D$8:$D$19,0)) -> 188 | K16: =INDEX(Assumptions!$H$8:$H$19,MATCH(K$5,Assumptions!$D$8:$D$19,0)) -> 185 | ... O16: =INDEX(Assumptions!$H$8:$H$19,MATCH(O$5,Assumptions!$D$8:$D$19,0)) -> 162 | P16: =P21/P14 -> 168.99758
C17: Corporate ADR | D17: =INDEX(Assumptions!$I$8:$I$19,MATCH(D$5,Assumptions!$D$8:$D$19,0)) -> 132 | E17: =INDEX(Assumptions!$I$8:$I$19,MATCH(E$5,Assumptions!$D$8:$D$19,0)) -> 133 | F17: =INDEX(Assumptions!$I$8:$I$19,MATCH(F$5,Assumptions!$D$8:$D$19,0)) -> 137 | G17: =INDEX(Assumptions!$I$8:$I$19,MATCH(G$5,Assumptions!$D$8:$D$19,0)) -> 140 | H17: =INDEX(Assumptions!$I$8:$I$19,MATCH(H$5,Assumptions!$D$8:$D$19,0)) -> 145 | I17: =INDEX(Assumptions!$I$8:$I$19,MATCH(I$5,Assumptions!$D$8:$D$19,0)) -> 148 | J17: =INDEX(Assumptions!$I$8:$I$19,MATCH(J$5,Assumptions!$D$8:$D$19,0)) -> 153 | K17: =INDEX(Assumptions!$I$8:$I$19,MATCH(K$5,Assumptions!$D$8:$D$19,0)) -> 151 | ... O17: =INDEX(Assumptions!$I$8:$I$19,MATCH(O$5,Assumptions!$D$8:$D$19,0)) -> 140 | P17: =P22/P15 -> 143.62444
C20: Revenue
C21: Retail room revenue | D21: =D14*D16 -> 179025 | E21: =E14*E16 -> 170325.12 | F21: =F14*F16 -> 216491.6 | G21: =G14*G16 -> 227304 | H21: =H14*H16 -> 256469.2 | I21: =I14*I16 -> 269568 | J21: =J14*J16 -> 303522.24 | K21: =K14*K16 -> 286864.7 | ... O21: =O14*O16 -> 201482.64 | P21: =SUM(D21:O21) -> 2763820.3
C22: Corporate room revenue | D22: =D15*D17 -> 67518 | E22: =E15*E17 -> 66957.52 | F22: =F15*F17 -> 88337.6 | G22: =G15*G17 -> 99960 | H22: =H15*H17 -> 116420.5 | I22: =I15*I17 -> 124675.2 | J22: =J15*J17 -> 151396.56 | K22: =K15*K17 -> 149698.38 | ... O22: =O15*O17 -> 81939.2 | P22: =SUM(D22:O22) -> 1281101.3
C23: Total room revenue | D23: =SUM(D21:D22) -> 246543 | E23: =SUM(E21:E22) -> 237282.64 | F23: =SUM(F21:F22) -> 304829.2 | G23: =SUM(G21:G22) -> 327264 | H23: =SUM(H21:H22) -> 372889.7 | I23: =SUM(I21:I22) -> 394243.2 | J23: =SUM(J21:J22) -> 454918.8 | K23: =SUM(K21:K22) -> 436563.08 | ... O23: =SUM(O21:O22) -> 283421.84 | P23: =SUM(D23:O23) -> 4044921.6
C24: Blended ADR | D24: =D23/D11 -> 144.6 | E24: =E23/E11 -> 146.11 | F24: =F23/F11 -> 151.28 | G24: =G23/G11 -> 155.84 | H24: =H23/H11 -> 162.55 | I24: =I23/I11 -> 168.48 | J24: =J23/J11 -> 174.7 | K24: =K23/K11 -> 171.74 | ... P24: =P23/P11 -> 160.04279
C25: RevPAR | D25: =D23/D10 -> 79.53 | E25: =E23/E10 -> 84.7438 | F25: =F23/F10 -> 98.332 | G25: =G23/G10 -> 109.088 | H25: =H23/H10 -> 120.287 | I25: =I23/I10 -> 131.4144 | J25: =J23/J10 -> 146.748 | K25: =K23/K10 -> 140.8268 | ... P25: =P23/P10 -> 110.81977
C28: Variable and operating costs
C29: Housekeeping hours per occupied room | D29: =INDEX(Assumptions!$J$8:$J$19,MATCH(D$5,Assumptions!$D$8:$D$19,0)) -> 0.56 | E29: =INDEX(Assumptions!$J$8:$J$19,MATCH(E$5,Assumptions!$D$8:$D$19,0)) -> 0.55 | F29: =INDEX(Assumptions!$J$8:$J$19,MATCH(F$5,Assumptions!$D$8:$D$19,0)) -> 0.54 | G29: =INDEX(Assumptions!$J$8:$J$19,MATCH(G$5,Assumptions!$D$8:$D$19,0)) -> 0.53 | H29: =INDEX(Assumptions!$J$8:$J$19,MATCH(H$5,Assumptions!$D$8:$D$19,0)) -> 0.52 | I29: =INDEX(Assumptions!$J$8:$J$19,MATCH(I$5,Assumptions!$D$8:$D$19,0)) -> 0.51 | J29: =INDEX(Assumptions!$J$8:$J$19,MATCH(J$5,Assumptions!$D$8:$D$19,0)) -> 0.5 | K29: =INDEX(Assumptions!$J$8:$J$19,MATCH(K$5,Assumptions!$D$8:$D$19,0)) -> 0.5 | ... O29: =INDEX(Assumptions!$J$8:$J$19,MATCH(O$5,Assumptions!$D$8:$D$19,0)) -> 0.56 | P29: =P31/P11 -> 0.52799122
C30: Loaded housekeeping wage per hour | D30: =INDEX(Assumptions!$K$8:$K$19,MATCH(D$5,Assumptions!$D$8:$D$19,0)) -> 22 | E30: =INDEX(Assumptions!$K$8:$K$19,MATCH(E$5,Assumptions!$D$8:$D$19,0)) -> 22 | F30: =INDEX(Assumptions!$K$8:$K$19,MATCH(F$5,Assumptions!$D$8:$D$19,0)) -> 22 | G30: =INDEX(Assumptions!$K$8:$K$19,MATCH(G$5,Assumptions!$D$8:$D$19,0)) -> 22 | H30: =INDEX(Assumptions!$K$8:$K$19,MATCH(H$5,Assumptions!$D$8:$D$19,0)) -> 22 | I30: =INDEX(Assumptions!$K$8:$K$19,MATCH(I$5,Assumptions!$D$8:$D$19,0)) -> 22 | J30: =INDEX(Assumptions!$K$8:$K$19,MATCH(J$5,Assumptions!$D$8:$D$19,0)) -> 22.75 | K30: =INDEX(Assumptions!$K$8:$K$19,MATCH(K$5,Assumptions!$D$8:$D$19,0)) -> 22.75 | ... O30: =INDEX(Assumptions!$K$8:$K$19,MATCH(O$5,Assumptions!$D$8:$D$19,0)) -> 22.75 | P30: =P32/P31 -> 22.388311
C31: Housekeeping hours | D31: =D11*D29 -> 954.8 | E31: =E11*E29 -> 893.2 | F31: =F11*F29 -> 1088.1 | G31: =G11*G29 -> 1113 | H31: =H11*H29 -> 1192.88 | I31: =I11*I29 -> 1193.4 | J31: =J11*J29 -> 1302 | K31: =K11*K29 -> 1271 | ... O31: =O11*O29 -> 1024.24 | P31: =SUM(D31:O31) -> 13344.45
C32: Housekeeping payroll | D32: =D31*D30 -> 21005.6 | E32: =E31*E30 -> 19650.4 | F32: =F31*F30 -> 23938.2 | G32: =G31*G30 -> 24486 | H32: =H31*H30 -> 26243.36 | I32: =I31*I30 -> 26254.8 | J32: =J31*J30 -> 29620.5 | K32: =K31*K30 -> 28915.25 | ... O32: =O31*O30 -> 23301.46 | P32: =SUM(D32:O32) -> 298759.7
C33: Guest-service cost per occupied room | D33: =INDEX(Assumptions!$L$8:$L$19,MATCH(D$5,Assumptions!$D$8:$D$19,0)) -> 18.5 | E33: =INDEX(Assumptions!$L$8:$L$19,MATCH(E$5,Assumptions!$D$8:$D$19,0)) -> 18.7 | F33: =INDEX(Assumptions!$L$8:$L$19,MATCH(F$5,Assumptions!$D$8:$D$19,0)) -> 19 | G33: =INDEX(Assumptions!$L$8:$L$19,MATCH(G$5,Assumptions!$D$8:$D$19,0)) -> 19.2 | H33: =INDEX(Assumptions!$L$8:$L$19,MATCH(H$5,Assumptions!$D$8:$D$19,0)) -> 19.5 | I33: =INDEX(Assumptions!$L$8:$L$19,MATCH(I$5,Assumptions!$D$8:$D$19,0)) -> 19.8 | J33: =INDEX(Assumptions!$L$8:$L$19,MATCH(J$5,Assumptions!$D$8:$D$19,0)) -> 20 | K33: =INDEX(Assumptions!$L$8:$L$19,MATCH(K$5,Assumptions!$D$8:$D$19,0)) -> 20 | ... O33: =INDEX(Assumptions!$L$8:$L$19,MATCH(O$5,Assumptions!$D$8:$D$19,0)) -> 19.2 | P33: =P34/P11 -> 19.414006
C34: Guest-service expense | D34: =D11*D33 -> 31542.5 | E34: =E11*E33 -> 30368.8 | F34: =F11*F33 -> 38285 | G34: =G11*G33 -> 40320 | H34: =H11*H33 -> 44733 | I34: =I11*I33 -> 46332 | J34: =J11*J33 -> 52080 | K34: =K11*K33 -> 50840 | ... O34: =O11*O33 -> 35116.8 | P34: =SUM(D34:O34) -> 490669.6
C35: Distribution fee rate | D35: =INDEX(Assumptions!$M$8:$M$19,MATCH(D$5,Assumptions!$D$8:$D$19,0)) -> 0.04 | E35: =INDEX(Assumptions!$M$8:$M$19,MATCH(E$5,Assumptions!$D$8:$D$19,0)) -> 0.04 | F35: =INDEX(Assumptions!$M$8:$M$19,MATCH(F$5,Assumptions!$D$8:$D$19,0)) -> 0.04 | G35: =INDEX(Assumptions!$M$8:$M$19,MATCH(G$5,Assumptions!$D$8:$D$19,0)) -> 0.04 | H35: =INDEX(Assumptions!$M$8:$M$19,MATCH(H$5,Assumptions!$D$8:$D$19,0)) -> 0.04 | I35: =INDEX(Assumptions!$M$8:$M$19,MATCH(I$5,Assumptions!$D$8:$D$19,0)) -> 0.04 | J35: =INDEX(Assumptions!$M$8:$M$19,MATCH(J$5,Assumptions!$D$8:$D$19,0)) -> 0.04 | K35: =INDEX(Assumptions!$M$8:$M$19,MATCH(K$5,Assumptions!$D$8:$D$19,0)) -> 0.04 | ... O35: =INDEX(Assumptions!$M$8:$M$19,MATCH(O$5,Assumptions!$D$8:$D$19,0)) -> 0.04 | P35: =P36/P23 -> 0.04
C36: Distribution and payment expense | D36: =D23*D35 -> 9861.72 | E36: =E23*E35 -> 9491.3056 | F36: =F23*F35 -> 12193.168 | G36: =G23*G35 -> 13090.56 | H36: =H23*H35 -> 14915.588 | I36: =I23*I35 -> 15769.728 | J36: =J23*J35 -> 18196.752 | K36: =K23*K35 -> 17462.523 | ... O36: =O23*O35 -> 11336.874 | P36: =SUM(D36:O36) -> 161796.86
C39: Fixed costs
C40: Fixed staff FTE | D40: =INDEX(Assumptions!$N$8:$N$19,MATCH(D$5,Assumptions!$D$8:$D$19,0)) -> 5 | E40: =INDEX(Assumptions!$N$8:$N$19,MATCH(E$5,Assumptions!$D$8:$D$19,0)) -> 5 | F40: =INDEX(Assumptions!$N$8:$N$19,MATCH(F$5,Assumptions!$D$8:$D$19,0)) -> 5 | G40: =INDEX(Assumptions!$N$8:$N$19,MATCH(G$5,Assumptions!$D$8:$D$19,0)) -> 5 | H40: =INDEX(Assumptions!$N$8:$N$19,MATCH(H$5,Assumptions!$D$8:$D$19,0)) -> 5 | I40: =INDEX(Assumptions!$N$8:$N$19,MATCH(I$5,Assumptions!$D$8:$D$19,0)) -> 5 | J40: =INDEX(Assumptions!$N$8:$N$19,MATCH(J$5,Assumptions!$D$8:$D$19,0)) -> 5 | K40: =INDEX(Assumptions!$N$8:$N$19,MATCH(K$5,Assumptions!$D$8:$D$19,0)) -> 5 | ... O40: =INDEX(Assumptions!$N$8:$N$19,MATCH(O$5,Assumptions!$D$8:$D$19,0)) -> 5 | P40: =AVERAGE(D40:O40) -> 5
C41: Fixed staff loaded cost per FTE | D41: =INDEX(Assumptions!$O$8:$O$19,MATCH(D$5,Assumptions!$D$8:$D$19,0)) -> 6000 | E41: =INDEX(Assumptions!$O$8:$O$19,MATCH(E$5,Assumptions!$D$8:$D$19,0)) -> 6000 | F41: =INDEX(Assumptions!$O$8:$O$19,MATCH(F$5,Assumptions!$D$8:$D$19,0)) -> 6000 | G41: =INDEX(Assumptions!$O$8:$O$19,MATCH(G$5,Assumptions!$D$8:$D$19,0)) -> 6000 | H41: =INDEX(Assumptions!$O$8:$O$19,MATCH(H$5,Assumptions!$D$8:$D$19,0)) -> 6000 | I41: =INDEX(Assumptions!$O$8:$O$19,MATCH(I$5,Assumptions!$D$8:$D$19,0)) -> 6000 | J41: =INDEX(Assumptions!$O$8:$O$19,MATCH(J$5,Assumptions!$D$8:$D$19,0)) -> 6120 | K41: =INDEX(Assumptions!$O$8:$O$19,MATCH(K$5,Assumptions!$D$8:$D$19,0)) -> 6120 | ... O41: =INDEX(Assumptions!$O$8:$O$19,MATCH(O$5,Assumptions!$D$8:$D$19,0)) -> 6120 | P41: =P42/SUM(D40:O40) -> 6060
C42: Fixed staff payroll | D42: =D40*D41 -> 30000 | E42: =E40*E41 -> 30000 | F42: =F40*F41 -> 30000 | G42: =G40*G41 -> 30000 | H42: =H40*H41 -> 30000 | I42: =I40*I41 -> 30000 | J42: =J40*J41 -> 30600 | K42: =K40*K41 -> 30600 | ... O42: =O40*O41 -> 30600 | P42: =SUM(D42:O42) -> 363600
C43: Rent | D43: =INDEX(Assumptions!$P$8:$P$19,MATCH(D$5,Assumptions!$D$8:$D$19,0)) -> 78000 | E43: =INDEX(Assumptions!$P$8:$P$19,MATCH(E$5,Assumptions!$D$8:$D$19,0)) -> 78000 | F43: =INDEX(Assumptions!$P$8:$P$19,MATCH(F$5,Assumptions!$D$8:$D$19,0)) -> 78000 | G43: =INDEX(Assumptions!$P$8:$P$19,MATCH(G$5,Assumptions!$D$8:$D$19,0)) -> 78000 | H43: =INDEX(Assumptions!$P$8:$P$19,MATCH(H$5,Assumptions!$D$8:$D$19,0)) -> 78000 | I43: =INDEX(Assumptions!$P$8:$P$19,MATCH(I$5,Assumptions!$D$8:$D$19,0)) -> 78000 | J43: =INDEX(Assumptions!$P$8:$P$19,MATCH(J$5,Assumptions!$D$8:$D$19,0)) -> 78000 | K43: =INDEX(Assumptions!$P$8:$P$19,MATCH(K$5,Assumptions!$D$8:$D$19,0)) -> 78000 | ... O43: =INDEX(Assumptions!$P$8:$P$19,MATCH(O$5,Assumptions!$D$8:$D$19,0)) -> 78000 | P43: =SUM(D43:O43) -> 936000
C44: Property overhead | D44: =INDEX(Assumptions!$Q$8:$Q$19,MATCH(D$5,Assumptions!$D$8:$D$19,0)) -> 28000 | E44: =INDEX(Assumptions!$Q$8:$Q$19,MATCH(E$5,Assumptions!$D$8:$D$19,0)) -> 28100 | F44: =INDEX(Assumptions!$Q$8:$Q$19,MATCH(F$5,Assumptions!$D$8:$D$19,0)) -> 28500 | G44: =INDEX(Assumptions!$Q$8:$Q$19,MATCH(G$5,Assumptions!$D$8:$D$19,0)) -> 28600 | H44: =INDEX(Assumptions!$Q$8:$Q$19,MATCH(H$5,Assumptions!$D$8:$D$19,0)) -> 28900 | I44: =INDEX(Assumptions!$Q$8:$Q$19,MATCH(I$5,Assumptions!$D$8:$D$19,0)) -> 29200 | J44: =INDEX(Assumptions!$Q$8:$Q$19,MATCH(J$5,Assumptions!$D$8:$D$19,0)) -> 29800 | K44: =INDEX(Assumptions!$Q$8:$Q$19,MATCH(K$5,Assumptions!$D$8:$D$19,0)) -> 30000 | ... O44: =INDEX(Assumptions!$Q$8:$Q$19,MATCH(O$5,Assumptions!$D$8:$D$19,0)) -> 29000 | P44: =SUM(D44:O44) -> 347300
C45: Marketing | D45: =INDEX(Assumptions!$R$8:$R$19,MATCH(D$5,Assumptions!$D$8:$D$19,0)) -> 10000 | E45: =INDEX(Assumptions!$R$8:$R$19,MATCH(E$5,Assumptions!$D$8:$D$19,0)) -> 9000 | F45: =INDEX(Assumptions!$R$8:$R$19,MATCH(F$5,Assumptions!$D$8:$D$19,0)) -> 11000 | G45: =INDEX(Assumptions!$R$8:$R$19,MATCH(G$5,Assumptions!$D$8:$D$19,0)) -> 13000 | H45: =INDEX(Assumptions!$R$8:$R$19,MATCH(H$5,Assumptions!$D$8:$D$19,0)) -> 14000 | I45: =INDEX(Assumptions!$R$8:$R$19,MATCH(I$5,Assumptions!$D$8:$D$19,0)) -> 24000 | J45: =INDEX(Assumptions!$R$8:$R$19,MATCH(J$5,Assumptions!$D$8:$D$19,0)) -> 18000 | K45: =INDEX(Assumptions!$R$8:$R$19,MATCH(K$5,Assumptions!$D$8:$D$19,0)) -> 15000 | ... O45: =INDEX(Assumptions!$R$8:$R$19,MATCH(O$5,Assumptions!$D$8:$D$19,0)) -> 16000 | P45: =SUM(D45:O45) -> 167000
C48: Profitability
C49: Total operating costs | D49: =SUM(D32,D34,D36,D42:D45) -> 208409.82 | E49: =SUM(E32,E34,E36,E42:E45) -> 204610.51 | F49: =SUM(F32,F34,F36,F42:F45) -> 221916.37 | G49: =SUM(G32,G34,G36,G42:G45) -> 227496.56 | H49: =SUM(H32,H34,H36,H42:H45) -> 236791.95 | I49: =SUM(I32,I34,I36,I42:I45) -> 249556.53 | J49: =SUM(J32,J34,J36,J42:J45) -> 256297.25 | K49: =SUM(K32,K34,K36,K42:K45) -> 250817.77 | ... O49: =SUM(O32,O34,O36,O42:O45) -> 223355.13 | P49: =SUM(D49:O49) -> 2765126.2
C50: Property operating contribution | D50: =D23-D49 -> 38133.18 | E50: =E23-E49 -> 32672.134 | F50: =F23-F49 -> 82912.832 | G50: =G23-G49 -> 99767.44 | H50: =H23-H49 -> 136097.75 | I50: =I23-I49 -> 144686.67 | J50: =J23-J49 -> 198621.55 | K50: =K23-K49 -> 185745.31 | ... O50: =O23-O49 -> 60066.706 | P50: =SUM(D50:O50) -> 1279795.4
C51: Contribution margin | D51: =D50/D23 -> 0.15467152 | E51: =E50/E23 -> 0.1376929 | F51: =F50/F23 -> 0.27199767 | G51: =G50/G23 -> 0.30485308 | H51: =H50/H23 -> 0.36498126 | I51: =I50/I23 -> 0.36699852 | J51: =J50/J23 -> 0.43660879 | K51: =K50/K23 -> 0.42547186 | ... P51: =P50/P23 -> 0.31639561

Sheet Forecast
C2: 2026 RF1 — Actuals Through June 2026
C3: January–June recorded actuals plus a July–December driver-based forecast. Base is the official working reforecast; Upside and Downside are bounded sensitivities.
C5: Forecast version | D5: 2026 RF1 | F5: Case version | G5: v1.0 | I5: Cutoff | J5: 46211 | L5: Actuals | M5: Jan–Jun 2026 | O5: Forecast | P5: Jul–Dec 2026 | R5: Official case | S5: Base
C7: Full-year scenario summary | L7: Principal H2 driver differences
C8: Metric | D8: Approved Budget | E8: Base RF1 | F8: Base vs Budget | G8: Upside | H8: Upside vs Base | I8: Downside | J8: Downside vs Base | L8: Driver | M8: Base | N8: Upside | O8: Δ vs Base | P8: Downside | Q8: Δ vs Base
C9: Occupied room nights | D9: =Budget!P11 -> 25274 | E9: =P32 -> 24518 | F9: =E9-D9 -> -756 | G9: =P80 -> 24850 | H9: =G9-E9 -> 332 | I9: =P128 -> 23919 | J9: =I9-E9 -> -599 | L9: H2 occupied room nights | M9: =SUM(J32:O32) -> 12980 | N9: =SUM(J80:O80) -> 13312 | O9: =N9-M9 -> 332 | P9: =SUM(J128:O128) -> 12381 | Q9: =P9-M9 -> -599
C10: Occupancy | D10: =Budget!P12 -> 0.69243836 | E10: =P33 -> 0.67172603 | F10: =E10-D10 -> -0.020712329 | G10: =P81 -> 0.68082192 | H10: =G10-E10 -> 0.0090958904 | I10: =P129 -> 0.65531507 | J10: =I10-E10 -> -0.016410959 | L10: H2 corporate share | M10: =SUM(J36:O36)/SUM(J32:O32) -> 0.39694646 | N10: =SUM(J84:O84)/SUM(J80:O80) -> 0.40205116 | O10: =N10-M10 -> 0.0051047008 | P10: =SUM(J132:O132)/SUM(J128:O128) -> 0.38202367 | Q10: =P10-M10 -> -0.014922791
C11: Corporate share | D11: =Budget!P13 -> 0.35292395 | E11: =P34 -> 0.39474529 | F11: =E11-D11 -> 0.041821336 | G11: =P82 -> 0.39750926 | H11: =G11-E11 -> 0.0027639664 | I11: =P130 -> 0.3869658 | J11: =I11-E11 -> -0.0077794879 | L11: H2 Retail ADR | M11: =SUM(J41:O41)/SUM(J35:O35) -> 174.00368 | N11: =SUM(J89:O89)/SUM(J83:O83) -> 175.78525 | O11: =N11-M11 -> 1.7815683 | P11: =SUM(J137:O137)/SUM(J131:O131) -> 170.5835 | Q11: =P11-M11 -> -3.4201862
C12: Total room revenue | D12: =Budget!P23 -> 4044921.6 | E12: =P43 -> 3903659.4 | F12: =E12-D12 -> -141262.21 | G12: =P91 -> 3974207.9 | H12: =G12-E12 -> 70548.523 | I12: =P139 -> 3777975 | J12: =I12-E12 -> -125684.34 | L12: H2 Corporate ADR | M12: =SUM(J42:O42)/SUM(J36:O36) -> 146.87664 | N12: =SUM(J90:O90)/SUM(J84:O84) -> 147.6271 | O12: =N12-M12 -> 0.75046341 | P12: =SUM(J138:O138)/SUM(J132:O132) -> 145.44959 | Q12: =P12-M12 -> -1.4270499
C13: Blended ADR | D13: =Budget!P24 -> 160.04279 | E13: =P44 -> 159.21606 | F13: =E13-D13 -> -0.82673363 | G13: =P92 -> 159.92788 | H13: =G13-E13 -> 0.71182256 | I13: =P140 -> 157.9487 | J13: =I13-E13 -> -1.2673572 | L13: H2 housekeeping hours / occupied room | M13: =SUM(J50:O50)/SUM(J32:O32) -> 0.54282897 | N13: =SUM(J98:O98)/SUM(J80:O80) -> 0.53143104 | O13: =N13-M13 -> -0.011397928 | P13: =SUM(J146:O146)/SUM(J128:O128) -> 0.55839351 | Q13: =P13-M13 -> 0.015564539
C14: RevPAR | D14: =Budget!P25 -> 110.81977 | E14: =P45 -> 106.94957 | F14: =E14-D14 -> -3.8701975 | G14: =P93 -> 108.88241 | H14: =G14-E14 -> 1.9328362 | I14: =P141 -> 103.50617 | J14: =I14-E14 -> -3.4434065
C15: Total operating costs | D15: =Budget!P49 -> 2765126.2 | E15: =P66 -> 2766112.2 | F15: =E15-D15 -> 986.0292 | G15: =P114 -> 2776133.9 | H15: =G15-E15 -> 10021.733 | I15: =P162 -> 2746264.6 | J15: =I15-E15 -> -19847.636
C16: Property operating contribution | D16: =Budget!P50 -> 1279795.4 | E16: =P67 -> 1137547.2 | F16: =E16-D16 -> -142248.24 | G16: =P115 -> 1198074 | H16: =G16-E16 -> 60526.789 | I16: =P163 -> 1031710.5 | J16: =I16-E16 -> -105836.7
C17: Contribution margin | D17: =Budget!P51 -> 0.31639561 | E17: =P68 -> 0.29140534 | F17: =E17-D17 -> -0.024990268 | G17: =P116 -> 0.30146233 | H17: =G17-E17 -> 0.010056991 | I17: =P164 -> 0.27308557 | J17: =I17-E17 -> -0.018319765
C19: Forecast accuracy: Phase 3 actual-versus-budget analysis is the available evidence about approved-plan performance. RF1 accuracy cannot be evaluated until later actual results exist.
C20: Scenario ranges are decision-support cases, not confidence intervals, and no probability weighting is used.
C22: Detailed scenarios — January–June Actual (A), July–December Forecast (F)
C24: Base — 2026 RF1
C25: Period type | D25: A | E25: A | F25: A | G25: A | H25: A | I25: A | J25: F | K25: F | L25: F | M25: F | N25: F | O25: F | P25: FY2026 | Q25: Approved Budget | R25: Variance | S25: Variance % / pp
C26: Month | D26: 46023 | E26: 46054 | F26: 46082 | G26: 46113 | H26: 46143 | I26: 46174 | J26: 46204 | K26: 46235 | L26: 46266 | M26: 46296 | N26: 46327 | O26: 46357 | P26: FY2026 | Q26: Approved Budget | R26: Variance | S26: Variance % / pp
C27: Actual costs remain recorded facts; forecast costs use visible assumptions.
C28: Operating drivers
C29: Rooms available | D29: =Budget!D8 -> 100 | E29: =Budget!E8 -> 100 | F29: =Budget!F8 -> 100 | G29: =Budget!G8 -> 100 | H29: =Budget!H8 -> 100 | I29: =Budget!I8 -> 100 | J29: =Assumptions!F41 -> 100 | K29: =Assumptions!G41 -> 100 | L29: =Assumptions!H41 -> 100 | M29: =Assumptions!I41 -> 100 | N29: =Assumptions!J41 -> 100 | O29: =Assumptions!K41 -> 100 | P29: =AVERAGE(D29:O29) -> 100 | Q29: =Budget!P8 -> 100 | R29: =P29-Q29 -> 0 | S29: =IF(Q29=0,"n.a.",R29/ABS(Q29)) -> 0
C30: Calendar days | D30: =DATE(YEAR(D$26),MONTH(D$26)+1,1)-D$26 -> 31 | E30: =DATE(YEAR(E$26),MONTH(E$26)+1,1)-E$26 -> 28 | F30: =DATE(YEAR(F$26),MONTH(F$26)+1,1)-F$26 -> 31 | G30: =DATE(YEAR(G$26),MONTH(G$26)+1,1)-G$26 -> 30 | H30: =DATE(YEAR(H$26),MONTH(H$26)+1,1)-H$26 -> 31 | I30: =DATE(YEAR(I$26),MONTH(I$26)+1,1)-I$26 -> 30 | J30: =DATE(YEAR(J$26),MONTH(J$26)+1,1)-J$26 -> 31 | K30: =DATE(YEAR(K$26),MONTH(K$26)+1,1)-K$26 -> 31 | ... O30: =DATE(YEAR(O$26),MONTH(O$26)+1,1)-O$26 -> 31 | P30: =SUM(D30:O30) -> 365 | Q30: =Budget!P9 -> 365 | R30: =P30-Q30 -> 0 | S30: =IF(Q30=0,"n.a.",R30/ABS(Q30)) -> 0
C31: Available room nights | D31: =D29*D30 -> 3100 | E31: =E29*E30 -> 2800 | F31: =F29*F30 -> 3100 | G31: =G29*G30 -> 3000 | H31: =H29*H30 -> 3100 | I31: =I29*I30 -> 3000 | J31: =J29*J30 -> 3100 | K31: =K29*K30 -> 3100 | ... O31: =O29*O30 -> 3100 | P31: =SUM(D31:O31) -> 36500 | Q31: =Budget!P10 -> 36500 | R31: =P31-Q31 -> 0 | S31: =IF(Q31=0,"n.a.",R31/ABS(Q31)) -> 0
C32: Occupied room nights | D32: =SUM(D35:D36) -> 1658 | E32: =SUM(E35:E36) -> 1604 | F32: =SUM(F35:F36) -> 1922 | G32: =SUM(G35:G36) -> 1950 | H32: =SUM(H35:H36) -> 2139 | I32: =SUM(I35:I36) -> 2265 | J32: =Assumptions!F42 -> 2552 | K32: =Assumptions!G42 -> 2491 | L32: =Assumptions!H42 -> 2146 | M32: =Assumptions!I42 -> 2168 | N32: =Assumptions!J42 -> 1812 | O32: =Assumptions!K42 -> 1811 | P32: =SUM(D32:O32) -> 24518 | Q32: =Budget!P11 -> 25274 | R32: =P32-Q32 -> -756 | S32: =IF(Q32=0,"n.a.",R32/ABS(Q32)) -> -0.029912163
C33: Occupancy | D33: =D32/D31 -> 0.53483871 | E33: =E32/E31 -> 0.57285714 | F33: =F32/F31 -> 0.62 | G33: =G32/G31 -> 0.65 | H33: =H32/H31 -> 0.69 | I33: =I32/I31 -> 0.755 | J33: =J32/J31 -> 0.82322581 | K33: =K32/K31 -> 0.80354839 | ... P33: =P32/P31 -> 0.67172603 | Q33: =Budget!P12 -> 0.69243836 | R33: =P33-Q33 -> -0.020712329 | S33: =R33 -> -0.020712329
C34: Corporate share | D34: =D36/D32 -> 0.31001206 | E34: =E36/E32 -> 0.3298005 | F34: =F36/F32 -> 0.3798127 | G34: =G36/G32 -> 0.43025641 | H34: =H36/H32 -> 0.45021038 | I34: =I36/I32 -> 0.41986755 | J34: =Assumptions!F43 -> 0.41 | K34: =Assumptions!G43 -> 0.42 | L34: =Assumptions!H43 -> 0.43 | M34: =Assumptions!I43 -> 0.405 | N34: =Assumptions!J43 -> 0.36 | O34: =Assumptions!K43 -> 0.335 | P34: =P36/P32 -> 0.39474529 | Q34: =Budget!P13 -> 0.35292395 | R34: =P34-Q34 -> 0.041821336 | S34: =R34 -> 0.041821336
C35: Retail room nights | D35: =SUMIFS(Data!$F$158:$F$193,Data!$D$158:$D$193,D$26,Data!$E$158:$E$193,"Retail/Leisure") -> 1144 | E35: =SUMIFS(Data!$F$158:$F$193,Data!$D$158:$D$193,E$26,Data!$E$158:$E$193,"Retail/Leisure") -> 1075 | F35: =SUMIFS(Data!$F$158:$F$193,Data!$D$158:$D$193,F$26,Data!$E$158:$E$193,"Retail/Leisure") -> 1192 | G35: =SUMIFS(Data!$F$158:$F$193,Data!$D$158:$D$193,G$26,Data!$E$158:$E$193,"Retail/Leisure") -> 1111 | H35: =SUMIFS(Data!$F$158:$F$193,Data!$D$158:$D$193,H$26,Data!$E$158:$E$193,"Retail/Leisure") -> 1176 | I35: =SUMIFS(Data!$F$158:$F$193,Data!$D$158:$D$193,I$26,Data!$E$158:$E$193,"Retail/Leisure") -> 1314 | J35: =J32-J36 -> 1505.68 | K35: =K32-K36 -> 1444.78 | L35: =L32-L36 -> 1223.22 | M35: =M32-M36 -> 1289.96 | N35: =N32-N36 -> 1159.68 | O35: =O32-O36 -> 1204.315 | P35: =SUM(D35:O35) -> 14839.635 | Q35: =Budget!P14 -> 16354.2 | R35: =P35-Q35 -> -1514.565 | S35: =IF(Q35=0,"n.a.",R35/ABS(Q35)) -> -0.092610155
C36: Corporate room nights | D36: =SUMIFS(Data!$F$158:$F$193,Data!$D$158:$D$193,D$26,Data!$E$158:$E$193,"Negotiated Corporate") -> 514 | E36: =SUMIFS(Data!$F$158:$F$193,Data!$D$158:$D$193,E$26,Data!$E$158:$E$193,"Negotiated Corporate") -> 529 | F36: =SUMIFS(Data!$F$158:$F$193,Data!$D$158:$D$193,F$26,Data!$E$158:$E$193,"Negotiated Corporate") -> 730 | G36: =SUMIFS(Data!$F$158:$F$193,Data!$D$158:$D$193,G$26,Data!$E$158:$E$193,"Negotiated Corporate") -> 839 | H36: =SUMIFS(Data!$F$158:$F$193,Data!$D$158:$D$193,H$26,Data!$E$158:$E$193,"Negotiated Corporate") -> 963 | I36: =SUMIFS(Data!$F$158:$F$193,Data!$D$158:$D$193,I$26,Data!$E$158:$E$193,"Negotiated Corporate") -> 951 | J36: =J32*J34 -> 1046.32 | K36: =K32*K34 -> 1046.22 | L36: =L32*L34 -> 922.78 | M36: =M32*M34 -> 878.04 | N36: =N32*N34 -> 652.32 | O36: =O32*O34 -> 606.685 | P36: =SUM(D36:O36) -> 9678.365 | Q36: =Budget!P15 -> 8919.8 | R36: =P36-Q36 -> 758.565 | S36: =IF(Q36=0,"n.a.",R36/ABS(Q36)) -> 0.085042826
C37: Retail ADR | D37: =D41/D35 -> 151 | E37: =E41/E35 -> 153 | F37: =F41/F35 -> 158.5 | G37: =G41/G35 -> 164 | H37: =H41/H35 -> 171 | I37: =I41/I35 -> 181 | J37: =Assumptions!F44 -> 188 | K37: =Assumptions!G44 -> 185 | L37: =Assumptions!H44 -> 175 | M37: =Assumptions!I44 -> 170 | N37: =Assumptions!J44 -> 158 | O37: =Assumptions!K44 -> 162 | P37: =P41/P35 -> 169.09596 | Q37: =Budget!P16 -> 168.99758 | R37: =P37-Q37 -> 0.098374178 | S37: =IF(Q37=0,"n.a.",R37/ABS(Q37)) -> 0.00058210405
C38: Corporate ADR | D38: =D42/D36 -> 132.5 | E38: =E42/E36 -> 133 | F38: =F42/F36 -> 137.5 | G38: =G42/G36 -> 140.5 | H38: =H42/H36 -> 145 | I38: =I42/I36 -> 148.5 | J38: =Assumptions!F45 -> 153.5 | K38: =Assumptions!G45 -> 151.5 | L38: =Assumptions!H45 -> 146.5 | M38: =Assumptions!I45 -> 144.5 | N38: =Assumptions!J45 -> 138.5 | O38: =Assumptions!K45 -> 140.5 | P38: =P42/P36 -> 144.06742 | Q38: =Budget!P17 -> 143.62444 | R38: =P38-Q38 -> 0.44297866 | S38: =IF(Q38=0,"n.a.",R38/ABS(Q38)) -> 0.0030842847
C40: Revenue
C41: Retail room revenue | D41: =SUMIFS(Data!$G$158:$G$193,Data!$D$158:$D$193,D$26,Data!$E$158:$E$193,"Retail/Leisure") -> 172744 | E41: =SUMIFS(Data!$G$158:$G$193,Data!$D$158:$D$193,E$26,Data!$E$158:$E$193,"Retail/Leisure") -> 164475 | F41: =SUMIFS(Data!$G$158:$G$193,Data!$D$158:$D$193,F$26,Data!$E$158:$E$193,"Retail/Leisure") -> 188932 | G41: =SUMIFS(Data!$G$158:$G$193,Data!$D$158:$D$193,G$26,Data!$E$158:$E$193,"Retail/Leisure") -> 182204 | H41: =SUMIFS(Data!$G$158:$G$193,Data!$D$158:$D$193,H$26,Data!$E$158:$E$193,"Retail/Leisure") -> 201096 | I41: =SUMIFS(Data!$G$158:$G$193,Data!$D$158:$D$193,I$26,Data!$E$158:$E$193,"Retail/Leisure") -> 237834 | J41: =J35*J37 -> 283067.84 | K41: =K35*K37 -> 267284.3 | L41: =L35*L37 -> 214063.5 | M41: =M35*M37 -> 219293.2 | N41: =N35*N37 -> 183229.44 | O41: =O35*O37 -> 195099.03 | P41: =SUM(D41:O41) -> 2509322.3 | Q41: =Budget!P21 -> 2763820.3 | R41: =P41-Q41 -> -254497.99 | S41: =IF(Q41=0,"n.a.",R41/ABS(Q41)) -> -0.09208196
C42: Corporate room revenue | D42: =SUMIFS(Data!$G$158:$G$193,Data!$D$158:$D$193,D$26,Data!$E$158:$E$193,"Negotiated Corporate") -> 68105 | E42: =SUMIFS(Data!$G$158:$G$193,Data!$D$158:$D$193,E$26,Data!$E$158:$E$193,"Negotiated Corporate") -> 70357 | F42: =SUMIFS(Data!$G$158:$G$193,Data!$D$158:$D$193,F$26,Data!$E$158:$E$193,"Negotiated Corporate") -> 100375 | G42: =SUMIFS(Data!$G$158:$G$193,Data!$D$158:$D$193,G$26,Data!$E$158:$E$193,"Negotiated Corporate") -> 117879.5 | H42: =SUMIFS(Data!$G$158:$G$193,Data!$D$158:$D$193,H$26,Data!$E$158:$E$193,"Negotiated Corporate") -> 139635 | I42: =SUMIFS(Data!$G$158:$G$193,Data!$D$158:$D$193,I$26,Data!$E$158:$E$193,"Negotiated Corporate") -> 141223.5 | J42: =J36*J38 -> 160610.12 | K42: =K36*K38 -> 158502.33 | L42: =L36*L38 -> 135187.27 | M42: =M36*M38 -> 126876.78 | N42: =N36*N38 -> 90346.32 | O42: =O36*O38 -> 85239.243 | P42: =SUM(D42:O42) -> 1394337.1 | Q42: =Budget!P22 -> 1281101.3 | R42: =P42-Q42 -> 113235.78 | S42: =IF(Q42=0,"n.a.",R42/ABS(Q42)) -> 0.088389407
C43: Total room revenue | D43: =SUM(D41:D42) -> 240849 | E43: =SUM(E41:E42) -> 234832 | F43: =SUM(F41:F42) -> 289307 | G43: =SUM(G41:G42) -> 300083.5 | H43: =SUM(H41:H42) -> 340731 | I43: =SUM(I41:I42) -> 379057.5 | J43: =SUM(J41:J42) -> 443677.96 | K43: =SUM(K41:K42) -> 425786.63 | ... O43: =SUM(O41:O42) -> 280338.27 | P43: =SUM(D43:O43) -> 3903659.4 | Q43: =Budget!P23 -> 4044921.6 | R43: =P43-Q43 -> -141262.21 | S43: =IF(Q43=0,"n.a.",R43/ABS(Q43)) -> -0.034923349
C44: Blended ADR | D44: =D43/D32 -> 145.26478 | E44: =E43/E32 -> 146.40399 | F44: =F43/F32 -> 150.52393 | G44: =G43/G32 -> 153.88897 | H44: =H43/H32 -> 159.29453 | I44: =I43/I32 -> 167.3543 | J44: =J43/J32 -> 173.855 | K44: =K43/K32 -> 170.93 | ... P44: =P43/P32 -> 159.21606 | Q44: =Budget!P24 -> 160.04279 | R44: =P44-Q44 -> -0.82673363 | S44: =IF(Q44=0,"n.a.",R44/ABS(Q44)) -> -0.0051657035
C45: RevPAR | D45: =D43/D31 -> 77.693226 | E45: =E43/E31 -> 83.868571 | F45: =F43/F31 -> 93.324839 | G45: =G43/G31 -> 100.02783 | H45: =H43/H31 -> 109.91323 | I45: =I43/I31 -> 126.3525 | J45: =J43/J31 -> 143.12192 | K45: =K43/K31 -> 137.35053 | ... P45: =P43/P31 -> 106.94957 | Q45: =Budget!P25 -> 110.81977 | R45: =P45-Q45 -> -3.8701975 | S45: =IF(Q45=0,"n.a.",R45/ABS(Q45)) -> -0.034923349
C47: Variable and operating costs
C48: Housekeeping hours per occupied room | D48: =D50/D32 -> 0.57 | E48: =E50/E32 -> 0.55 | F48: =F50/F32 -> 0.56 | G48: =G50/G32 -> 0.62 | H48: =H50/H32 -> 0.6 | I48: =I50/I32 -> 0.56 | J48: =Assumptions!F46 -> 0.55 | K48: =Assumptions!G46 -> 0.54 | L48: =Assumptions!H46 -> 0.53 | M48: =Assumptions!I46 -> 0.53 | N48: =Assumptions!J46 -> 0.55 | O48: =Assumptions!K46 -> 0.56 | P48: =P50/P32 -> 0.55919325 | Q48: =Budget!P29 -> 0.52799122 | R48: =P48-Q48 -> 0.03120203 | S48: =IF(Q48=0,"n.a.",R48/ABS(Q48)) -> 0.059095736
C49: Housekeeping wage per hour | D49: =D51/D50 -> 21.899996 | E49: =E51/E50 -> 22 | F49: =F51/F50 -> 22.099998 | G49: =G51/G50 -> 23.25 | H49: =H51/H50 -> 23.25 | I49: =I51/I50 -> 23.25 | J49: =Assumptions!F47 -> 23.25 | K49: =Assumptions!G47 -> 23.25 | L49: =Assumptions!H47 -> 23.25 | M49: =Assumptions!I47 -> 23.25 | N49: =Assumptions!J47 -> 23.25 | O49: =Assumptions!K47 -> 23.25 | P49: =P51/P50 -> 22.986231 | Q49: =Budget!P30 -> 22.388311 | R49: =P49-Q49 -> 0.59791936 | S49: =IF(Q49=0,"n.a.",R49/ABS(Q49)) -> 0.026706764
C50: Housekeeping hours | D50: =SUMIFS(Data!$E$200:$E$217,Data!$D$200:$D$217,D$26) -> 945.06 | E50: =SUMIFS(Data!$E$200:$E$217,Data!$D$200:$D$217,E$26) -> 882.2 | F50: =SUMIFS(Data!$E$200:$E$217,Data!$D$200:$D$217,F$26) -> 1076.32 | G50: =SUMIFS(Data!$E$200:$E$217,Data!$D$200:$D$217,G$26) -> 1209 | H50: =SUMIFS(Data!$E$200:$E$217,Data!$D$200:$D$217,H$26) -> 1283.4 | I50: =SUMIFS(Data!$E$200:$E$217,Data!$D$200:$D$217,I$26) -> 1268.4 | J50: =J32*J48 -> 1403.6 | K50: =K32*K48 -> 1345.14 | L50: =L32*L48 -> 1137.38 | M50: =M32*M48 -> 1149.04 | N50: =N32*N48 -> 996.6 | O50: =O32*O48 -> 1014.16 | P50: =SUM(D50:O50) -> 13710.3 | Q50: =Budget!P31 -> 13344.45 | R50: =P50-Q50 -> 365.85 | S50: =IF(Q50=0,"n.a.",R50/ABS(Q50)) -> 0.027415892
C51: Housekeeping payroll | D51: =SUMIFS(Data!$F$200:$F$217,Data!$D$200:$D$217,D$26) -> 20696.81 | E51: =SUMIFS(Data!$F$200:$F$217,Data!$D$200:$D$217,E$26) -> 19408.4 | F51: =SUMIFS(Data!$F$200:$F$217,Data!$D$200:$D$217,F$26) -> 23786.67 | G51: =SUMIFS(Data!$F$200:$F$217,Data!$D$200:$D$217,G$26) -> 28109.25 | H51: =SUMIFS(Data!$F$200:$F$217,Data!$D$200:$D$217,H$26) -> 29839.05 | I51: =SUMIFS(Data!$F$200:$F$217,Data!$D$200:$D$217,I$26) -> 29490.3 | J51: =J50*J49 -> 32633.7 | K51: =K50*K49 -> 31274.505 | L51: =L50*L49 -> 26444.085 | M51: =M50*M49 -> 26715.18 | N51: =N50*N49 -> 23170.95 | O51: =O50*O49 -> 23579.22 | P51: =SUM(D51:O51) -> 315148.12 | Q51: =Budget!P32 -> 298759.7 | R51: =P51-Q51 -> 16388.417 | S51: =IF(Q51=0,"n.a.",R51/ABS(Q51)) -> 0.054854846
C52: Guest-service cost per occupied room | D52: =D53/D32 -> 18.6 | E52: =E53/E32 -> 18.5 | F52: =F53/F32 -> 19.1 | G52: =G53/G32 -> 19.4 | H52: =H53/H32 -> 19.8 | I52: =I53/I32 -> 20.1 | J52: =Assumptions!F48 -> 20 | K52: =Assumptions!G48 -> 20 | L52: =Assumptions!H48 -> 19.8 | M52: =Assumptions!I48 -> 19.5 | N52: =Assumptions!J48 -> 19 | O52: =Assumptions!K48 -> 19.2 | P52: =P53/P32 -> 19.485998 | Q52: =Budget!P33 -> 19.414006 | R52: =P52-Q52 -> 0.071991553 | S52: =IF(Q52=0,"n.a.",R52/ABS(Q52)) -> 0.0037082275
C53: Guest-service expense | D53: =SUMIFS(Data!$G$8:$G$151,Data!$D$8:$D$151,D$26,Data!$F$8:$F$151,"Guest Services") -> 30838.8 | E53: =SUMIFS(Data!$G$8:$G$151,Data!$D$8:$D$151,E$26,Data!$F$8:$F$151,"Guest Services") -> 29674 | F53: =SUMIFS(Data!$G$8:$G$151,Data!$D$8:$D$151,F$26,Data!$F$8:$F$151,"Guest Services") -> 36710.2 | G53: =SUMIFS(Data!$G$8:$G$151,Data!$D$8:$D$151,G$26,Data!$F$8:$F$151,"Guest Services") -> 37830 | H53: =SUMIFS(Data!$G$8:$G$151,Data!$D$8:$D$151,H$26,Data!$F$8:$F$151,"Guest Services") -> 42352.2 | I53: =SUMIFS(Data!$G$8:$G$151,Data!$D$8:$D$151,I$26,Data!$F$8:$F$151,"Guest Services") -> 45526.5 | J53: =J32*J52 -> 51040 | K53: =K32*K52 -> 49820 | L53: =L32*L52 -> 42490.8 | M53: =M32*M52 -> 42276 | N53: =N32*N52 -> 34428 | O53: =O32*O52 -> 34771.2 | P53: =SUM(D53:O53) -> 477757.7 | Q53: =Budget!P34 -> 490669.6 | R53: =P53-Q53 -> -12911.9 | S53: =IF(Q53=0,"n.a.",R53/ABS(Q53)) -> -0.026314856
C54: Distribution fee rate | D54: =D55/D43 -> 0.04 | E54: =E55/E43 -> 0.04 | F54: =F55/F43 -> 0.04 | G54: =G55/G43 -> 0.04 | H54: =H55/H43 -> 0.04 | I54: =I55/I43 -> 0.04 | J54: =Assumptions!F49 -> 0.04 | K54: =Assumptions!G49 -> 0.04 | L54: =Assumptions!H49 -> 0.04 | M54: =Assumptions!I49 -> 0.04 | N54: =Assumptions!J49 -> 0.04 | O54: =Assumptions!K49 -> 0.04 | P54: =P55/P43 -> 0.04 | Q54: =Budget!P35 -> 0.04 | R54: =P54-Q54 -> 0 | S54: =R54 -> 0
C55: Distribution and payment expense | D55: =SUMIFS(Data!$G$8:$G$151,Data!$D$8:$D$151,D$26,Data!$F$8:$F$151,"Distribution and Payment") -> 9633.96 | E55: =SUMIFS(Data!$G$8:$G$151,Data!$D$8:$D$151,E$26,Data!$F$8:$F$151,"Distribution and Payment") -> 9393.28 | F55: =SUMIFS(Data!$G$8:$G$151,Data!$D$8:$D$151,F$26,Data!$F$8:$F$151,"Distribution and Payment") -> 11572.28 | G55: =SUMIFS(Data!$G$8:$G$151,Data!$D$8:$D$151,G$26,Data!$F$8:$F$151,"Distribution and Payment") -> 12003.34 | H55: =SUMIFS(Data!$G$8:$G$151,Data!$D$8:$D$151,H$26,Data!$F$8:$F$151,"Distribution and Payment") -> 13629.24 | I55: =SUMIFS(Data!$G$8:$G$151,Data!$D$8:$D$151,I$26,Data!$F$8:$F$151,"Distribution and Payment") -> 15162.3 | J55: =J43*J54 -> 17747.118 | K55: =K43*K54 -> 17031.465 | L55: =L43*L54 -> 13970.031 | M55: =M43*M54 -> 13846.799 | N55: =N43*N54 -> 10943.03 | O55: =O43*O54 -> 11213.531 | P55: =SUM(D55:O55) -> 156146.37 | Q55: =Budget!P36 -> 161796.86 | R55: =P55-Q55 -> -5650.4883 | S55: =IF(Q55=0,"n.a.",R55/ABS(Q55)) -> -0.034923349
C57: Fixed costs
C58: Fixed-staff FTE | D58: =SUMIFS(Data!$G$200:$G$217,Data!$D$200:$D$217,D$26) -> 5 | E58: =SUMIFS(Data!$G$200:$G$217,Data!$D$200:$D$217,E$26) -> 5 | F58: =SUMIFS(Data!$G$200:$G$217,Data!$D$200:$D$217,F$26) -> 5 | G58: =SUMIFS(Data!$G$200:$G$217,Data!$D$200:$D$217,G$26) -> 5 | H58: =SUMIFS(Data!$G$200:$G$217,Data!$D$200:$D$217,H$26) -> 5 | I58: =SUMIFS(Data!$G$200:$G$217,Data!$D$200:$D$217,I$26) -> 5 | J58: =Assumptions!F50 -> 5 | K58: =Assumptions!G50 -> 5 | L58: =Assumptions!H50 -> 5 | M58: =Assumptions!I50 -> 5 | N58: =Assumptions!J50 -> 5 | O58: =Assumptions!K50 -> 5 | P58: =AVERAGE(D58:O58) -> 5 | Q58: =Budget!P40 -> 5 | R58: =P58-Q58 -> 0 | S58: =IF(Q58=0,"n.a.",R58/ABS(Q58)) -> 0
C59: Fixed-staff cost per FTE | D59: =D60/D58 -> 5980 | E59: =E60/E58 -> 6005 | F59: =F60/F58 -> 6015 | G59: =G60/G58 -> 6040 | H59: =H60/H58 -> 6070 | I59: =I60/I58 -> 6050 | J59: =Assumptions!F51 -> 6120 | K59: =Assumptions!G51 -> 6120 | L59: =Assumptions!H51 -> 6120 | M59: =Assumptions!I51 -> 6120 | N59: =Assumptions!J51 -> 6120 | O59: =Assumptions!K51 -> 6120 | P59: =P60/SUM(D58:O58) -> 6073.3333 | Q59: =Budget!P41 -> 6060 | R59: =P59-Q59 -> 13.333333 | S59: =IF(Q59=0,"n.a.",R59/ABS(Q59)) -> 0.00220022
C60: Fixed-staff payroll | D60: =SUMIFS(Data!$H$200:$H$217,Data!$D$200:$D$217,D$26) -> 29900 | E60: =SUMIFS(Data!$H$200:$H$217,Data!$D$200:$D$217,E$26) -> 30025 | F60: =SUMIFS(Data!$H$200:$H$217,Data!$D$200:$D$217,F$26) -> 30075 | G60: =SUMIFS(Data!$H$200:$H$217,Data!$D$200:$D$217,G$26) -> 30200 | H60: =SUMIFS(Data!$H$200:$H$217,Data!$D$200:$D$217,H$26) -> 30350 | I60: =SUMIFS(Data!$H$200:$H$217,Data!$D$200:$D$217,I$26) -> 30250 | J60: =J58*J59 -> 30600 | K60: =K58*K59 -> 30600 | L60: =L58*L59 -> 30600 | M60: =M58*M59 -> 30600 | N60: =N58*N59 -> 30600 | O60: =O58*O59 -> 30600 | P60: =SUM(D60:O60) -> 364400 | Q60: =Budget!P42 -> 363600 | R60: =P60-Q60 -> 800 | S60: =IF(Q60=0,"n.a.",R60/ABS(Q60)) -> 0.00220022
C61: Rent | D61: =SUMIFS(Data!$G$8:$G$151,Data!$D$8:$D$151,D$26,Data!$F$8:$F$151,"Rent") -> 78000 | E61: =SUMIFS(Data!$G$8:$G$151,Data!$D$8:$D$151,E$26,Data!$F$8:$F$151,"Rent") -> 78000 | F61: =SUMIFS(Data!$G$8:$G$151,Data!$D$8:$D$151,F$26,Data!$F$8:$F$151,"Rent") -> 78000 | G61: =SUMIFS(Data!$G$8:$G$151,Data!$D$8:$D$151,G$26,Data!$F$8:$F$151,"Rent") -> 78000 | H61: =SUMIFS(Data!$G$8:$G$151,Data!$D$8:$D$151,H$26,Data!$F$8:$F$151,"Rent") -> 78000 | I61: =SUMIFS(Data!$G$8:$G$151,Data!$D$8:$D$151,I$26,Data!$F$8:$F$151,"Rent") -> 78000 | J61: =Assumptions!F52 -> 78000 | K61: =Assumptions!G52 -> 78000 | L61: =Assumptions!H52 -> 78000 | M61: =Assumptions!I52 -> 78000 | N61: =Assumptions!J52 -> 78000 | O61: =Assumptions!K52 -> 78000 | P61: =SUM(D61:O61) -> 936000 | Q61: =Budget!P43 -> 936000 | R61: =P61-Q61 -> 0 | S61: =IF(Q61=0,"n.a.",R61/ABS(Q61)) -> 0
C62: Property overhead | D62: =SUMIFS(Data!$G$8:$G$151,Data!$D$8:$D$151,D$26,Data!$F$8:$F$151,"Property Overhead") -> 28050 | E62: =SUMIFS(Data!$G$8:$G$151,Data!$D$8:$D$151,E$26,Data!$F$8:$F$151,"Property Overhead") -> 27920 | F62: =SUMIFS(Data!$G$8:$G$151,Data!$D$8:$D$151,F$26,Data!$F$8:$F$151,"Property Overhead") -> 28620 | G62: =SUMIFS(Data!$G$8:$G$151,Data!$D$8:$D$151,G$26,Data!$F$8:$F$151,"Property Overhead") -> 28710 | H62: =SUMIFS(Data!$G$8:$G$151,Data!$D$8:$D$151,H$26,Data!$F$8:$F$151,"Property Overhead") -> 30350 | I62: =SUMIFS(Data!$G$8:$G$151,Data!$D$8:$D$151,I$26,Data!$F$8:$F$151,"Property Overhead") -> 29410 | J62: =Assumptions!F53 -> 29800 | K62: =Assumptions!G53 -> 30000 | L62: =Assumptions!H53 -> 29400 | M62: =Assumptions!I53 -> 29100 | N62: =Assumptions!J53 -> 28700 | O62: =Assumptions!K53 -> 29000 | P62: =SUM(D62:O62) -> 349060 | Q62: =Budget!P44 -> 347300 | R62: =P62-Q62 -> 1760 | S62: =IF(Q62=0,"n.a.",R62/ABS(Q62)) -> 0.0050676648
C63: Marketing | D63: =SUMIFS(Data!$G$8:$G$151,Data!$D$8:$D$151,D$26,Data!$F$8:$F$151,"Marketing") -> 10200 | E63: =SUMIFS(Data!$G$8:$G$151,Data!$D$8:$D$151,E$26,Data!$F$8:$F$151,"Marketing") -> 8800 | F63: =SUMIFS(Data!$G$8:$G$151,Data!$D$8:$D$151,F$26,Data!$F$8:$F$151,"Marketing") -> 11300 | G63: =SUMIFS(Data!$G$8:$G$151,Data!$D$8:$D$151,G$26,Data!$F$8:$F$151,"Marketing") -> 13100 | H63: =SUMIFS(Data!$G$8:$G$151,Data!$D$8:$D$151,H$26,Data!$F$8:$F$151,"Marketing") -> 14200 | I63: =SUMIFS(Data!$G$8:$G$151,Data!$D$8:$D$151,I$26,Data!$F$8:$F$151,"Marketing") -> 6000 | J63: =Assumptions!F54 -> 18000 | K63: =Assumptions!G54 -> 15000 | L63: =Assumptions!H54 -> 30000 | M63: =Assumptions!I54 -> 13000 | N63: =Assumptions!J54 -> 12000 | O63: =Assumptions!K54 -> 16000 | P63: =SUM(D63:O63) -> 167600 | Q63: =Budget!P45 -> 167000 | R63: =P63-Q63 -> 600 | S63: =IF(Q63=0,"n.a.",R63/ABS(Q63)) -> 0.0035928144
C65: Profitability
C66: Total operating costs | D66: =SUM(D51,D53,D55,D60:D63) -> 207319.57 | E66: =SUM(E51,E53,E55,E60:E63) -> 203220.68 | F66: =SUM(F51,F53,F55,F60:F63) -> 220064.15 | G66: =SUM(G51,G53,G55,G60:G63) -> 227952.59 | H66: =SUM(H51,H53,H55,H60:H63) -> 238720.49 | I66: =SUM(I51,I53,I55,I60:I63) -> 233839.1 | J66: =SUM(J51,J53,J55,J60:J63) -> 257820.82 | K66: =SUM(K51,K53,K55,K60:K63) -> 251725.97 | ... O66: =SUM(O51,O53,O55,O60:O63) -> 223163.95 | P66: =SUM(D66:O66) -> 2766112.2 | Q66: =Budget!P49 -> 2765126.2 | R66: =P66-Q66 -> 986.0292 | S66: =IF(Q66=0,"n.a.",R66/ABS(Q66)) -> 0.00035659465
C67: Property operating contribution | D67: =D43-D66 -> 33529.43 | E67: =E43-E66 -> 31611.32 | F67: =F43-F66 -> 69242.85 | G67: =G43-G66 -> 72130.91 | H67: =H43-H66 -> 102010.51 | I67: =I43-I66 -> 145218.4 | J67: =J43-J66 -> 185857.14 | K67: =K43-K66 -> 174060.66 | ... O67: =O43-O66 -> 57174.322 | P67: =SUM(D67:O67) -> 1137547.2 | Q67: =Budget!P50 -> 1279795.4 | R67: =P67-Q67 -> -142248.24 | S67: =IF(Q67=0,"n.a.",R67/ABS(Q67)) -> -0.1111492
C68: Contribution margin | D68: =D67/D43 -> 0.13921349 | E68: =E67/E43 -> 0.13461249 | F68: =F67/F43 -> 0.23934039 | G68: =G67/G43 -> 0.24036946 | H68: =H67/H43 -> 0.29938723 | I68: =I67/I43 -> 0.38310388 | J68: =J67/J43 -> 0.418901 | K68: =K67/K43 -> 0.40879785 | ... P68: =P67/P43 -> 0.29140534 | Q68: =Budget!P51 -> 0.31639561 | R68: =P68-Q68 -> -0.024990268 | S68: =R68 -> -0.024990268
C72: Upside — 2026 RF1
C73: Period type | D73: A | E73: A | F73: A | G73: A | H73: A | I73: A | J73: F | K73: F | L73: F | M73: F | N73: F | O73: F | P73: FY2026 | Q73: Approved Budget | R73: Variance | S73: Variance % / pp
C74: Month | D74: 46023 | E74: 46054 | F74: 46082 | G74: 46113 | H74: 46143 | I74: 46174 | J74: 46204 | K74: 46235 | L74: 46266 | M74: 46296 | N74: 46327 | O74: 46357 | P74: FY2026 | Q74: Approved Budget | R74: Variance | S74: Variance % / pp
C75: Actual costs remain recorded facts; forecast costs use visible assumptions.
C76: Operating drivers
C77: Rooms available | D77: =D29 -> 100 | E77: =E29 -> 100 | F77: =F29 -> 100 | G77: =G29 -> 100 | H77: =H29 -> 100 | I77: =I29 -> 100 | J77: =Assumptions!F41 -> 100 | K77: =Assumptions!G41 -> 100 | L77: =Assumptions!H41 -> 100 | M77: =Assumptions!I41 -> 100 | N77: =Assumptions!J41 -> 100 | O77: =Assumptions!K41 -> 100 | P77: =AVERAGE(D77:O77) -> 100 | Q77: =Budget!P8 -> 100 | R77: =P77-Q77 -> 0 | S77: =IF(Q77=0,"n.a.",R77/ABS(Q77)) -> 0
C78: Calendar days | D78: =D30 -> 31 | E78: =E30 -> 28 | F78: =F30 -> 31 | G78: =G30 -> 30 | H78: =H30 -> 31 | I78: =I30 -> 30 | J78: =DATE(YEAR(J$74),MONTH(J$74)+1,1)-J$74 -> 31 | K78: =DATE(YEAR(K$74),MONTH(K$74)+1,1)-K$74 -> 31 | L78: =DATE(YEAR(L$74),MONTH(L$74)+1,1)-L$74 -> 30 | M78: =DATE(YEAR(M$74),MONTH(M$74)+1,1)-M$74 -> 31 | N78: =DATE(YEAR(N$74),MONTH(N$74)+1,1)-N$74 -> 30 | O78: =DATE(YEAR(O$74),MONTH(O$74)+1,1)-O$74 -> 31 | P78: =SUM(D78:O78) -> 365 | Q78: =Budget!P9 -> 365 | R78: =P78-Q78 -> 0 | S78: =IF(Q78=0,"n.a.",R78/ABS(Q78)) -> 0
C79: Available room nights | D79: =D31 -> 3100 | E79: =E31 -> 2800 | F79: =F31 -> 3100 | G79: =G31 -> 3000 | H79: =H31 -> 3100 | I79: =I31 -> 3000 | J79: =J77*J78 -> 3100 | K79: =K77*K78 -> 3100 | L79: =L77*L78 -> 3000 | M79: =M77*M78 -> 3100 | N79: =N77*N78 -> 3000 | O79: =O77*O78 -> 3100 | P79: =SUM(D79:O79) -> 36500 | Q79: =Budget!P10 -> 36500 | R79: =P79-Q79 -> 0 | S79: =IF(Q79=0,"n.a.",R79/ABS(Q79)) -> 0
C80: Occupied room nights | D80: =D32 -> 1658 | E80: =E32 -> 1604 | F80: =F32 -> 1922 | G80: =G32 -> 1950 | H80: =H32 -> 2139 | I80: =I32 -> 2265 | J80: =Assumptions!F69 -> 2629 | K80: =Assumptions!G69 -> 2566 | L80: =Assumptions!H69 -> 2200 | M80: =Assumptions!I69 -> 2222 | N80: =Assumptions!J69 -> 1848 | O80: =Assumptions!K69 -> 1847 | P80: =SUM(D80:O80) -> 24850 | Q80: =Budget!P11 -> 25274 | R80: =P80-Q80 -> -424 | S80: =IF(Q80=0,"n.a.",R80/ABS(Q80)) -> -0.016776134
C81: Occupancy | D81: =D33 -> 0.53483871 | E81: =E33 -> 0.57285714 | F81: =F33 -> 0.62 | G81: =G33 -> 0.65 | H81: =H33 -> 0.69 | I81: =I33 -> 0.755 | J81: =J80/J79 -> 0.84806452 | K81: =K80/K79 -> 0.82774194 | L81: =L80/L79 -> 0.73333333 | M81: =M80/M79 -> 0.71677419 | N81: =N80/N79 -> 0.616 | O81: =O80/O79 -> 0.59580645 | P81: =P80/P79 -> 0.68082192 | Q81: =Budget!P12 -> 0.69243836 | R81: =P81-Q81 -> -0.011616438 | S81: =R81 -> -0.011616438
C82: Corporate share | D82: =D34 -> 0.31001206 | E82: =E34 -> 0.3298005 | F82: =F34 -> 0.3798127 | G82: =G34 -> 0.43025641 | H82: =H34 -> 0.45021038 | I82: =I34 -> 0.41986755 | J82: =Assumptions!F70 -> 0.415 | K82: =Assumptions!G70 -> 0.425 | L82: =Assumptions!H70 -> 0.435 | M82: =Assumptions!I70 -> 0.41 | N82: =Assumptions!J70 -> 0.365 | O82: =Assumptions!K70 -> 0.34 | P82: =P84/P80 -> 0.39750926 | Q82: =Budget!P13 -> 0.35292395 | R82: =P82-Q82 -> 0.044585302 | S82: =R82 -> 0.044585302
C83: Retail room nights | D83: =D35 -> 1144 | E83: =E35 -> 1075 | F83: =F35 -> 1192 | G83: =G35 -> 1111 | H83: =H35 -> 1176 | I83: =I35 -> 1314 | J83: =J80-J84 -> 1537.965 | K83: =K80-K84 -> 1475.45 | L83: =L80-L84 -> 1243 | M83: =M80-M84 -> 1310.98 | N83: =N80-N84 -> 1173.48 | O83: =O80-O84 -> 1219.02 | P83: =SUM(D83:O83) -> 14971.895 | Q83: =Budget!P14 -> 16354.2 | R83: =P83-Q83 -> -1382.305 | S83: =IF(Q83=0,"n.a.",R83/ABS(Q83)) -> -0.084522936
C84: Corporate room nights | D84: =D36 -> 514 | E84: =E36 -> 529 | F84: =F36 -> 730 | G84: =G36 -> 839 | H84: =H36 -> 963 | I84: =I36 -> 951 | J84: =J80*J82 -> 1091.035 | K84: =K80*K82 -> 1090.55 | L84: =L80*L82 -> 957 | M84: =M80*M82 -> 911.02 | N84: =N80*N82 -> 674.52 | O84: =O80*O82 -> 627.98 | P84: =SUM(D84:O84) -> 9878.105 | Q84: =Budget!P15 -> 8919.8 | R84: =P84-Q84 -> 958.305 | S84: =IF(Q84=0,"n.a.",R84/ABS(Q84)) -> 0.1074357
C85: Retail ADR | D85: =D37 -> 151 | E85: =E37 -> 153 | F85: =F37 -> 158.5 | G85: =G37 -> 164 | H85: =H37 -> 171 | I85: =I37 -> 181 | J85: =Assumptions!F71 -> 189.88 | K85: =Assumptions!G71 -> 186.85 | L85: =Assumptions!H71 -> 176.75 | M85: =Assumptions!I71 -> 171.7 | N85: =Assumptions!J71 -> 159.58 | O85: =Assumptions!K71 -> 163.62 | P85: =P89/P83 -> 170.08649 | Q85: =Budget!P16 -> 168.99758 | R85: =P85-Q85 -> 1.0889096 | S85: =IF(Q85=0,"n.a.",R85/ABS(Q85)) -> 0.006443344
C86: Corporate ADR | D86: =D38 -> 132.5 | E86: =E38 -> 133 | F86: =F38 -> 137.5 | G86: =G38 -> 140.5 | H86: =H38 -> 145 | I86: =I38 -> 148.5 | J86: =Assumptions!F72 -> 154.27 | K86: =Assumptions!G72 -> 152.26 | L86: =Assumptions!H72 -> 147.23 | M86: =Assumptions!I72 -> 145.22 | N86: =Assumptions!J72 -> 139.19 | O86: =Assumptions!K72 -> 141.2 | P86: =P90/P84 -> 144.53083 | Q86: =Budget!P17 -> 143.62444 | R86: =P86-Q86 -> 0.90639477 | S86: =IF(Q86=0,"n.a.",R86/ABS(Q86)) -> 0.0063108672
C88: Revenue
C89: Retail room revenue | D89: =D41 -> 172744 | E89: =E41 -> 164475 | F89: =F41 -> 188932 | G89: =G41 -> 182204 | H89: =H41 -> 201096 | I89: =I41 -> 237834 | J89: =J83*J85 -> 292028.79 | K89: =K83*K85 -> 275687.83 | L89: =L83*L85 -> 219700.25 | M89: =M83*M85 -> 225095.27 | N89: =N83*N85 -> 187263.94 | O89: =O83*O85 -> 199456.05 | P89: =SUM(D89:O89) -> 2546517.1 | Q89: =Budget!P21 -> 2763820.3 | R89: =P89-Q89 -> -217303.17 | S89: =IF(Q89=0,"n.a.",R89/ABS(Q89)) -> -0.078624202
C90: Corporate room revenue | D90: =D42 -> 68105 | E90: =E42 -> 70357 | F90: =F42 -> 100375 | G90: =G42 -> 117879.5 | H90: =H42 -> 139635 | I90: =I42 -> 141223.5 | J90: =J84*J86 -> 168313.97 | K90: =K84*K86 -> 166047.14 | L90: =L84*L86 -> 140899.11 | M90: =M84*M86 -> 132298.32 | N90: =N84*N86 -> 93886.439 | O90: =O84*O86 -> 88670.776 | P90: =SUM(D90:O90) -> 1427690.8 | Q90: =Budget!P22 -> 1281101.3 | R90: =P90-Q90 -> 146589.48 | S90: =IF(Q90=0,"n.a.",R90/ABS(Q90)) -> 0.11442458
C91: Total room revenue | D91: =D43 -> 240849 | E91: =E43 -> 234832 | F91: =F43 -> 289307 | G91: =G43 -> 300083.5 | H91: =H43 -> 340731 | I91: =I43 -> 379057.5 | J91: =SUM(J89:J90) -> 460342.76 | K91: =SUM(K89:K90) -> 441734.98 | L91: =SUM(L89:L90) -> 360599.36 | M91: =SUM(M89:M90) -> 357393.59 | N91: =SUM(N89:N90) -> 281150.38 | O91: =SUM(O89:O90) -> 288126.83 | P91: =SUM(D91:O91) -> 3974207.9 | Q91: =Budget!P23 -> 4044921.6 | R91: =P91-Q91 -> -70713.685 | S91: =IF(Q91=0,"n.a.",R91/ABS(Q91)) -> -0.01748209
C92: Blended ADR | D92: =D44 -> 145.26478 | E92: =E44 -> 146.40399 | F92: =F44 -> 150.52393 | G92: =G44 -> 153.88897 | H92: =H44 -> 159.29453 | I92: =I44 -> 167.3543 | J92: =J91/J80 -> 175.10185 | K92: =K91/K80 -> 172.14925 | L92: =L91/L80 -> 163.9088 | M92: =M91/M80 -> 160.8432 | N92: =N91/N80 -> 152.13765 | O92: =O91/O80 -> 155.9972 | P92: =P91/P80 -> 159.92788 | Q92: =Budget!P24 -> 160.04279 | R92: =P92-Q92 -> -0.11491107 | S92: =IF(Q92=0,"n.a.",R92/ABS(Q92)) -> -0.00071800216
C93: RevPAR | D93: =D45 -> 77.693226 | E93: =E45 -> 83.868571 | F93: =F45 -> 93.324839 | G93: =G45 -> 100.02783 | H93: =H45 -> 109.91323 | I93: =I45 -> 126.3525 | J93: =J91/J79 -> 148.49767 | K93: =K91/K79 -> 142.49515 | L93: =L91/L79 -> 120.19979 | M93: =M91/M79 -> 115.28825 | N93: =N91/N79 -> 93.716792 | O93: =O91/O79 -> 92.944138 | P93: =P91/P79 -> 108.88241 | Q93: =Budget!P25 -> 110.81977 | R93: =P93-Q93 -> -1.9373612 | S93: =IF(Q93=0,"n.a.",R93/ABS(Q93)) -> -0.01748209
C95: Variable and operating costs
C96: Housekeeping hours per occupied room | D96: =D48 -> 0.57 | E96: =E48 -> 0.55 | F96: =F48 -> 0.56 | G96: =G48 -> 0.62 | H96: =H48 -> 0.6 | I96: =I48 -> 0.56 | J96: =Assumptions!F73 -> 0.53 | K96: =Assumptions!G73 -> 0.51 | L96: =Assumptions!H73 -> 0.52 | M96: =Assumptions!I73 -> 0.53 | N96: =Assumptions!J73 -> 0.55 | O96: =Assumptions!K73 -> 0.56 | P96: =P98/P80 -> 0.55286881 | Q96: =Budget!P29 -> 0.52799122 | R96: =P96-Q96 -> 0.024877597 | S96: =IF(Q96=0,"n.a.",R96/ABS(Q96)) -> 0.047117444
C97: Housekeeping wage per hour | D97: =D49 -> 21.899996 | E97: =E49 -> 22 | F97: =F49 -> 22.099998 | G97: =G49 -> 23.25 | H97: =H49 -> 23.25 | I97: =I49 -> 23.25 | J97: =Assumptions!F47 -> 23.25 | K97: =Assumptions!G47 -> 23.25 | L97: =Assumptions!H47 -> 23.25 | M97: =Assumptions!I47 -> 23.25 | N97: =Assumptions!J47 -> 23.25 | O97: =Assumptions!K47 -> 23.25 | P97: =P99/P98 -> 22.986778 | Q97: =Budget!P30 -> 22.388311 | R97: =P97-Q97 -> 0.59846633 | S97: =IF(Q97=0,"n.a.",R97/ABS(Q97)) -> 0.026731196
C98: Housekeeping hours | D98: =D50 -> 945.06 | E98: =E50 -> 882.2 | F98: =F50 -> 1076.32 | G98: =G50 -> 1209 | H98: =H50 -> 1283.4 | I98: =I50 -> 1268.4 | J98: =J80*J96 -> 1393.37 | K98: =K80*K96 -> 1308.66 | L98: =L80*L96 -> 1144 | M98: =M80*M96 -> 1177.66 | N98: =N80*N96 -> 1016.4 | O98: =O80*O96 -> 1034.32 | P98: =SUM(D98:O98) -> 13738.79 | Q98: =Budget!P31 -> 13344.45 | R98: =P98-Q98 -> 394.34 | S98: =IF(Q98=0,"n.a.",R98/ABS(Q98)) -> 0.029550862
C99: Housekeeping payroll | D99: =D51 -> 20696.81 | E99: =E51 -> 19408.4 | F99: =F51 -> 23786.67 | G99: =G51 -> 28109.25 | H99: =H51 -> 29839.05 | I99: =I51 -> 29490.3 | J99: =J98*J97 -> 32395.853 | K99: =K98*K97 -> 30426.345 | L99: =L98*L97 -> 26598 | M99: =M98*M97 -> 27380.595 | N99: =N98*N97 -> 23631.3 | O99: =O98*O97 -> 24047.94 | P99: =SUM(D99:O99) -> 315810.51 | Q99: =Budget!P32 -> 298759.7 | R99: =P99-Q99 -> 17050.81 | S99: =IF(Q99=0,"n.a.",R99/ABS(Q99)) -> 0.057071987
C100: Guest-service cost per occupied room | D100: =D52 -> 18.6 | E100: =E52 -> 18.5 | F100: =F52 -> 19.1 | G100: =G52 -> 19.4 | H100: =H52 -> 19.8 | I100: =I52 -> 20.1 | J100: =Assumptions!F48 -> 20 | K100: =Assumptions!G48 -> 20 | L100: =Assumptions!H48 -> 19.8 | M100: =Assumptions!I48 -> 19.5 | N100: =Assumptions!J48 -> 19 | O100: =Assumptions!K48 -> 19.2 | P100: =P101/P80 -> 19.488736 | Q100: =Budget!P33 -> 19.414006 | R100: =P100-Q100 -> 0.07472993 | S100: =IF(Q100=0,"n.a.",R100/ABS(Q100)) -> 0.0038492791
C101: Guest-service expense | D101: =D53 -> 30838.8 | E101: =E53 -> 29674 | F101: =F53 -> 36710.2 | G101: =G53 -> 37830 | H101: =H53 -> 42352.2 | I101: =I53 -> 45526.5 | J101: =J80*J100 -> 52580 | K101: =K80*K100 -> 51320 | L101: =L80*L100 -> 43560 | M101: =M80*M100 -> 43329 | N101: =N80*N100 -> 35112 | O101: =O80*O100 -> 35462.4 | P101: =SUM(D101:O101) -> 484295.1 | Q101: =Budget!P34 -> 490669.6 | R101: =P101-Q101 -> -6374.5 | S101: =IF(Q101=0,"n.a.",R101/ABS(Q101)) -> -0.01299143
C102: Distribution fee rate | D102: =D54 -> 0.04 | E102: =E54 -> 0.04 | F102: =F54 -> 0.04 | G102: =G54 -> 0.04 | H102: =H54 -> 0.04 | I102: =I54 -> 0.04 | J102: =Assumptions!F49 -> 0.04 | K102: =Assumptions!G49 -> 0.04 | L102: =Assumptions!H49 -> 0.04 | M102: =Assumptions!I49 -> 0.04 | N102: =Assumptions!J49 -> 0.04 | O102: =Assumptions!K49 -> 0.04 | P102: =P103/P91 -> 0.04 | Q102: =Budget!P35 -> 0.04 | R102: =P102-Q102 -> 0 | S102: =R102 -> 0
C103: Distribution and payment expense | D103: =D55 -> 9633.96 | E103: =E55 -> 9393.28 | F103: =F55 -> 11572.28 | G103: =G55 -> 12003.34 | H103: =H55 -> 13629.24 | I103: =I55 -> 15162.3 | J103: =J91*J102 -> 18413.711 | K103: =K91*K102 -> 17669.399 | L103: =L91*L102 -> 14423.974 | M103: =M91*M102 -> 14295.744 | N103: =N91*N102 -> 11246.015 | O103: =O91*O102 -> 11525.073 | P103: =SUM(D103:O103) -> 158968.32 | Q103: =Budget!P36 -> 161796.86 | R103: =P103-Q103 -> -2828.5474 | S103: =IF(Q103=0,"n.a.",R103/ABS(Q103)) -> -0.01748209
C105: Fixed costs
C106: Fixed-staff FTE | D106: =D58 -> 5 | E106: =E58 -> 5 | F106: =F58 -> 5 | G106: =G58 -> 5 | H106: =H58 -> 5 | I106: =I58 -> 5 | J106: =Assumptions!F50 -> 5 | K106: =Assumptions!G50 -> 5 | L106: =Assumptions!H50 -> 5 | M106: =Assumptions!I50 -> 5 | N106: =Assumptions!J50 -> 5 | O106: =Assumptions!K50 -> 5 | P106: =AVERAGE(D106:O106) -> 5 | Q106: =Budget!P40 -> 5 | R106: =P106-Q106 -> 0 | S106: =IF(Q106=0,"n.a.",R106/ABS(Q106)) -> 0
C107: Fixed-staff cost per FTE | D107: =D59 -> 5980 | E107: =E59 -> 6005 | F107: =F59 -> 6015 | G107: =G59 -> 6040 | H107: =H59 -> 6070 | I107: =I59 -> 6050 | J107: =Assumptions!F51 -> 6120 | K107: =Assumptions!G51 -> 6120 | L107: =Assumptions!H51 -> 6120 | M107: =Assumptions!I51 -> 6120 | N107: =Assumptions!J51 -> 6120 | O107: =Assumptions!K51 -> 6120 | P107: =P108/SUM(D106:O106) -> 6073.3333 | Q107: =Budget!P41 -> 6060 | R107: =P107-Q107 -> 13.333333 | S107: =IF(Q107=0,"n.a.",R107/ABS(Q107)) -> 0.00220022
C108: Fixed-staff payroll | D108: =D60 -> 29900 | E108: =E60 -> 30025 | F108: =F60 -> 30075 | G108: =G60 -> 30200 | H108: =H60 -> 30350 | I108: =I60 -> 30250 | J108: =J106*J107 -> 30600 | K108: =K106*K107 -> 30600 | L108: =L106*L107 -> 30600 | M108: =M106*M107 -> 30600 | N108: =N106*N107 -> 30600 | O108: =O106*O107 -> 30600 | P108: =SUM(D108:O108) -> 364400 | Q108: =Budget!P42 -> 363600 | R108: =P108-Q108 -> 800 | S108: =IF(Q108=0,"n.a.",R108/ABS(Q108)) -> 0.00220022
C109: Rent | D109: =D61 -> 78000 | E109: =E61 -> 78000 | F109: =F61 -> 78000 | G109: =G61 -> 78000 | H109: =H61 -> 78000 | I109: =I61 -> 78000 | J109: =Assumptions!F52 -> 78000 | K109: =Assumptions!G52 -> 78000 | L109: =Assumptions!H52 -> 78000 | M109: =Assumptions!I52 -> 78000 | N109: =Assumptions!J52 -> 78000 | O109: =Assumptions!K52 -> 78000 | P109: =SUM(D109:O109) -> 936000 | Q109: =Budget!P43 -> 936000 | R109: =P109-Q109 -> 0 | S109: =IF(Q109=0,"n.a.",R109/ABS(Q109)) -> 0
C110: Property overhead | D110: =D62 -> 28050 | E110: =E62 -> 27920 | F110: =F62 -> 28620 | G110: =G62 -> 28710 | H110: =H62 -> 30350 | I110: =I62 -> 29410 | J110: =Assumptions!F53 -> 29800 | K110: =Assumptions!G53 -> 30000 | L110: =Assumptions!H53 -> 29400 | M110: =Assumptions!I53 -> 29100 | N110: =Assumptions!J53 -> 28700 | O110: =Assumptions!K53 -> 29000 | P110: =SUM(D110:O110) -> 349060 | Q110: =Budget!P44 -> 347300 | R110: =P110-Q110 -> 1760 | S110: =IF(Q110=0,"n.a.",R110/ABS(Q110)) -> 0.0050676648
C111: Marketing | D111: =D63 -> 10200 | E111: =E63 -> 8800 | F111: =F63 -> 11300 | G111: =G63 -> 13100 | H111: =H63 -> 14200 | I111: =I63 -> 6000 | J111: =Assumptions!F54 -> 18000 | K111: =Assumptions!G54 -> 15000 | L111: =Assumptions!H54 -> 30000 | M111: =Assumptions!I54 -> 13000 | N111: =Assumptions!J54 -> 12000 | O111: =Assumptions!K54 -> 16000 | P111: =SUM(D111:O111) -> 167600 | Q111: =Budget!P45 -> 167000 | R111: =P111-Q111 -> 600 | S111: =IF(Q111=0,"n.a.",R111/ABS(Q111)) -> 0.0035928144
C113: Profitability
C114: Total operating costs | D114: =D66 -> 207319.57 | E114: =E66 -> 203220.68 | F114: =F66 -> 220064.15 | G114: =G66 -> 227952.59 | H114: =H66 -> 238720.49 | I114: =I66 -> 233839.1 | J114: =SUM(J99,J101,J103,J108:J111) -> 259789.56 | K114: =SUM(K99,K101,K103,K108:K111) -> 253015.74 | L114: =SUM(L99,L101,L103,L108:L111) -> 252581.97 | M114: =SUM(M99,M101,M103,M108:M111) -> 235705.34 | N114: =SUM(N99,N101,N103,N108:N111) -> 219289.32 | O114: =SUM(O99,O101,O103,O108:O111) -> 224635.41 | P114: =SUM(D114:O114) -> 2776133.9 | Q114: =Budget!P49 -> 2765126.2 | R114: =P114-Q114 -> 11007.763 | S114: =IF(Q114=0,"n.a.",R114/ABS(Q114)) -> 0.003980926
C115: Property operating contribution | D115: =D67 -> 33529.43 | E115: =E67 -> 31611.32 | F115: =F67 -> 69242.85 | G115: =G67 -> 72130.91 | H115: =H67 -> 102010.51 | I115: =I67 -> 145218.4 | J115: =J91-J114 -> 200553.2 | K115: =K91-K114 -> 188719.23 | L115: =L91-L114 -> 108017.39 | M115: =M91-M114 -> 121688.25 | N115: =N91-N114 -> 61861.062 | O115: =O91-O114 -> 63491.415 | P115: =SUM(D115:O115) -> 1198074 | Q115: =Budget!P50 -> 1279795.4 | R115: =P115-Q115 -> -81721.447 | S115: =IF(Q115=0,"n.a.",R115/ABS(Q115)) -> -0.063855087
C116: Contribution margin | D116: =D68 -> 0.13921349 | E116: =E68 -> 0.13461249 | F116: =F68 -> 0.23934039 | G116: =G68 -> 0.24036946 | H116: =H68 -> 0.29938723 | I116: =I68 -> 0.38310388 | J116: =J115/J91 -> 0.43566059 | K116: =K115/K91 -> 0.42722275 | L116: =L115/L91 -> 0.29954958 | M116: =M115/M91 -> 0.34048806 | N116: =N115/N91 -> 0.22002838 | O116: =O115/O91 -> 0.22035926 | P116: =P115/P91 -> 0.30146233 | Q116: =Budget!P51 -> 0.31639561 | R116: =P116-Q116 -> -0.014933277 | S116: =R116 -> -0.014933277
C120: Downside — 2026 RF1
...

Sheet Variance
C2: Actual performance and variance attribution
C3: January–June 2026 actuals compared with the matched approved budget and January–June 2025 actuals.
C5: Analysis scope and conventions
C6: Actual period | D6: January–June 2026 recorded actuals
C7: Budget comparison | D7: January–June 2026 approved budget
C8: Prior-year comparison | D8: January–June 2025 recorded actuals
C9: Information cutoff | D9: 46211
C10: Case version | D10: v1.0
C11: Synthetic-data disclosure | D11: Palmetto Stay is fictional. All company-specific actuals, budgets, operating records, staffing information, and case updates are synthetic.
C12: Source references | D12: Data: financial_actuals.csv, operating_actuals.csv, labor_actuals.csv, and case_updates.csv. Budget: approved Budget sheet built from approved_budget_assumptions.csv.
C13: Revenue and contribution | D13: Actual minus Budget. Positive is favorable.
C14: Expense analysis | D14: Actual cost minus Budget cost. Positive is a cost increase and unfavorable.
C15: Contribution bridge expenses | D15: Budget cost minus Actual cost. Positive is favorable to contribution.
C16: Sequential bridges | D16: Revenue uses volume, mix, then rate. Housekeeping uses volume, efficiency, then wage rate. Monthly effects sum to YTD.
C17: Materiality guidance | D17: Review items with absolute YTD variance of at least $10,000, at least 5.0% on a meaningful base, or a known or unresolved qualitative event. A flag is not proof of causation.
C18: Interaction-effect disclosure | D18: Sequential attribution assigns interaction effects according to the stated order. It is a consistent analytical convention, not the only possible causal allocation.
C21: YTD operating scorecard
C22: Revenue and contribution variance: positive is favorable. Expense variance: positive is a cost increase and unfavorable. Occupancy, corporate share, and contribution margin changes are percentage points.
C23: Metric | D23: 2026 Actual | E23: 2026 Budget | F23: Variance / pp | G23: Variance % | H23: 2025 Actual | I23: YoY change / pp | J23: YoY change %
C24: Operating KPIs
C25: Available room nights | D25: =J94 -> 18100 | E25: =J61 -> 18100 | F25: =D25-E25 -> 0 | G25: =IF(E25=0,"n.a.",F25/ABS(E25)) -> 0 | H25: =100*(31+28+31+30+31+30) -> 18100 | I25: =D25-H25 -> 0 | J25: =IF(H25=0,"n.a.",I25/ABS(H25)) -> 0
C26: Occupied room nights | D26: =J95 -> 11538 | E26: =J62 -> 12078 | F26: =D26-E26 -> -540 | G26: =IF(E26=0,"n.a.",F26/ABS(E26)) -> -0.044709389 | H26: =H28+H29 -> 11596 | I26: =D26-H26 -> -58 | J26: =IF(H26=0,"n.a.",I26/ABS(H26)) -> -0.0050017247
C27: Occupancy | D27: =J96 -> 0.63745856 | E27: =J63 -> 0.66729282 | F27: =(D27-E27)*100 -> -2.9834254 | G27: n.a. | H27: =H26/H25 -> 0.64066298 | I27: =(D27-H27)*100 -> -0.32044199 | J27: n.a.
C28: Retail room nights | D28: =J97 -> 7012 | E28: =J64 -> 8058.96 | F28: =D28-E28 -> -1046.96 | G28: =IF(E28=0,"n.a.",F28/ABS(E28)) -> -0.12991254 | H28: =SUM(Data!$F$158,Data!$F$160,Data!$F$162,Data!$F$164,Data!$F$166,Data!$F$168) -> 8040 | I28: =D28-H28 -> -1028 | J28: =IF(H28=0,"n.a.",I28/ABS(H28)) -> -0.1278607
C29: Corporate room nights | D29: =J98 -> 4526 | E29: =J65 -> 4019.04 | F29: =D29-E29 -> 506.96 | G29: =IF(E29=0,"n.a.",F29/ABS(E29)) -> 0.12613958 | H29: =SUM(Data!$F$159,Data!$F$161,Data!$F$163,Data!$F$165,Data!$F$167,Data!$F$169) -> 3556 | I29: =D29-H29 -> 970 | J29: =IF(H29=0,"n.a.",I29/ABS(H29)) -> 0.2727784
C30: Corporate share | D30: =J99 -> 0.39226902 | E30: =J66 -> 0.33275708 | F30: =(D30-E30)*100 -> 5.9511945 | G30: n.a. | H30: =H29/H26 -> 0.30665747 | I30: =(D30-H30)*100 -> 8.5611556 | J30: n.a.
C31: Retail ADR | D31: =J100 -> 163.61737 | E31: =J67 -> 163.69146 | F31: =D31-E31 -> -0.074088725 | G31: =IF(E31=0,"n.a.",F31/ABS(E31)) -> -0.00045261204 | H31: =H36/H28 -> 159.98893 | I31: =D31-H31 -> 3.6284399 | J31: =IF(H31=0,"n.a.",I31/ABS(H31)) -> 0.022679318
C32: Corporate ADR | D32: =J101 -> 140.86942 | E32: =J68 -> 140.29938 | F32: =D32-E32 -> 0.57004117 | G32: =IF(E32=0,"n.a.",F32/ABS(E32)) -> 0.0040630341 | H32: =H37/H29 -> 137.5883 | I32: =D32-H32 -> 3.2811197 | J32: =IF(H32=0,"n.a.",I32/ABS(H32)) -> 0.023847374
C33: Blended ADR | D33: =J102 -> 154.69405 | E33: =J69 -> 155.90758 | F33: =D33-E33 -> -1.2135246 | G33: =IF(E33=0,"n.a.",F33/ABS(E33)) -> -0.0077836154 | H33: =H38/H26 -> 153.11961 | I33: =D33-H33 -> 1.5744442 | J33: =IF(H33=0,"n.a.",I33/ABS(H33)) -> 0.010282447
C34: RevPAR | D34: =J103 -> 98.61105 | E34: =J70 -> 104.03601 | F34: =D34-E34 -> -5.424958 | G34: =IF(E34=0,"n.a.",F34/ABS(E34)) -> -0.052145004 | H34: =H38/H25 -> 98.098066 | I34: =D34-H34 -> 0.51298343 | J34: =IF(H34=0,"n.a.",I34/ABS(H34)) -> 0.0052292919
C35: Financial performance
C36: Retail room revenue | D36: =J104 -> 1147285 | E36: =J71 -> 1319182.9 | F36: =D36-E36 -> -171897.92 | G36: =IF(E36=0,"n.a.",F36/ABS(E36)) -> -0.13030636 | H36: =SUM(Data!$G$158,Data!$G$160,Data!$G$162,Data!$G$164,Data!$G$166,Data!$G$168) -> 1286311 | I36: =D36-H36 -> -139026 | J36: =IF(H36=0,"n.a.",I36/ABS(H36)) -> -0.10808117
C37: Corporate room revenue | D37: =J105 -> 637575 | E37: =J72 -> 563868.82 | F37: =D37-E37 -> 73706.18 | G37: =IF(E37=0,"n.a.",F37/ABS(E37)) -> 0.13071512 | H37: =SUM(Data!$G$159,Data!$G$161,Data!$G$163,Data!$G$165,Data!$G$167,Data!$G$169) -> 489264 | I37: =D37-H37 -> 148311 | J37: =IF(H37=0,"n.a.",I37/ABS(H37)) -> 0.30313083
C38: Total room revenue | D38: =J106 -> 1784860 | E38: =J73 -> 1883051.7 | F38: =D38-E38 -> -98191.74 | G38: =IF(E38=0,"n.a.",F38/ABS(E38)) -> -0.052145004 | H38: =H36+H37 -> 1775575 | I38: =D38-H38 -> 9285 | J38: =IF(H38=0,"n.a.",I38/ABS(H38)) -> 0.0052292919
C39: Housekeeping payroll | D39: =J110 -> 151330.48 | E39: =J77 -> 141578.36 | F39: =D39-E39 -> 9752.12 | G39: =IF(E39=0,"n.a.",F39/ABS(E39)) -> 0.068881431 | H39: =SUM(Data!$F$200,Data!$F$201,Data!$F$202,Data!$F$203,Data!$F$204,Data!$F$205) -> 133869.13 | I39: =D39-H39 -> 17461.35 | J39: =IF(H39=0,"n.a.",I39/ABS(H39)) -> 0.13043597
C40: Guest-service expense | D40: =J112 -> 222931.7 | E40: =J79 -> 231581.3 | F40: =D40-E40 -> -8649.6 | G40: =IF(E40=0,"n.a.",F40/ABS(E40)) -> -0.037350166 | H40: =SUM(Data!$G$10,Data!$G$18,Data!$G$26,Data!$G$34,Data!$G$42,Data!$G$50) -> 215540 | I40: =D40-H40 -> 7391.7 | J40: =IF(H40=0,"n.a.",I40/ABS(H40)) -> 0.034293867
C41: Distribution and payment expense | D41: =J114 -> 71394.4 | E41: =J81 -> 75322.07 | F41: =D41-E41 -> -3927.6696 | G41: =IF(E41=0,"n.a.",F41/ABS(E41)) -> -0.052145004 | H41: =SUM(Data!$G$11,Data!$G$19,Data!$G$27,Data!$G$35,Data!$G$43,Data!$G$51) -> 71023 | I41: =D41-H41 -> 371.4 | J41: =IF(H41=0,"n.a.",I41/ABS(H41)) -> 0.0052292919
C42: Fixed-staff payroll | D42: =J117 -> 180800 | E42: =J84 -> 180000 | F42: =D42-E42 -> 800 | G42: =IF(E42=0,"n.a.",F42/ABS(E42)) -> 0.0044444444 | H42: =SUM(Data!$H$200,Data!$H$201,Data!$H$202,Data!$H$203,Data!$H$204,Data!$H$205) -> 173172 | I42: =D42-H42 -> 7628 | J42: =IF(H42=0,"n.a.",I42/ABS(H42)) -> 0.044048691
C43: Rent | D43: =J118 -> 468000 | E43: =J85 -> 468000 | F43: =D43-E43 -> 0 | G43: =IF(E43=0,"n.a.",F43/ABS(E43)) -> 0 | H43: =SUM(Data!$G$13,Data!$G$21,Data!$G$29,Data!$G$37,Data!$G$45,Data!$G$53) -> 456000 | I43: =D43-H43 -> 12000 | J43: =IF(H43=0,"n.a.",I43/ABS(H43)) -> 0.026315789
C44: Property overhead | D44: =J119 -> 173060 | E44: =J86 -> 171300 | F44: =D44-E44 -> 1760 | G44: =IF(E44=0,"n.a.",F44/ABS(E44)) -> 0.010274372 | H44: =SUM(Data!$G$14,Data!$G$22,Data!$G$30,Data!$G$38,Data!$G$46,Data!$G$54) -> 163600 | I44: =D44-H44 -> 9460 | J44: =IF(H44=0,"n.a.",I44/ABS(H44)) -> 0.057823961
C45: Marketing | D45: =J120 -> 63600 | E45: =J87 -> 81000 | F45: =D45-E45 -> -17400 | G45: =IF(E45=0,"n.a.",F45/ABS(E45)) -> -0.21481481 | H45: =SUM(Data!$G$15,Data!$G$23,Data!$G$31,Data!$G$39,Data!$G$47,Data!$G$55) -> 70500 | I45: =D45-H45 -> -6900 | J45: =IF(H45=0,"n.a.",I45/ABS(H45)) -> -0.09787234
C46: Total operating costs | D46: =J121 -> 1331116.6 | E46: =J88 -> 1348781.7 | F46: =D46-E46 -> -17665.15 | G46: =IF(E46=0,"n.a.",F46/ABS(E46)) -> -0.013097115 | H46: =SUM(H39,H40,H41,H42,H43,H44,H45) -> 1283704.1 | I46: =D46-H46 -> 47412.45 | J46: =IF(H46=0,"n.a.",I46/ABS(H46)) -> 0.036934095
C47: Property operating contribution | D47: =J122 -> 453743.42 | E47: =J89 -> 534270.01 | F47: =D47-E47 -> -80526.59 | G47: =IF(E47=0,"n.a.",F47/ABS(E47)) -> -0.15072265 | H47: =H38-H46 -> 491870.87 | I47: =D47-H47 -> -38127.45 | J47: =IF(H47=0,"n.a.",I47/ABS(H47)) -> -0.077515162
C48: Contribution margin | D48: =J123 -> 0.25421793 | E48: =J90 -> 0.28372561 | F48: =(D48-E48)*100 -> -2.9507681 | G48: n.a. | H48: =H47/H38 -> 0.27702061 | I48: =(D48-H48)*100 -> -2.2802677 | J48: n.a.
C49: Labor and unit metrics
C50: Housekeeping hours | D50: =J107 -> 6664.38 | E50: =J74 -> 6435.38 | F50: =D50-E50 -> 229 | G50: =IF(E50=0,"n.a.",F50/ABS(E50)) -> 0.035584534 | H50: =SUM(Data!$E$200,Data!$E$201,Data!$E$202,Data!$E$203,Data!$E$204,Data!$E$205) -> 6334.58 | I50: =D50-H50 -> 329.8 | J50: =IF(H50=0,"n.a.",I50/ABS(H50)) -> 0.052063436
C51: Housekeeping hours per occupied room | D51: =J108 -> 0.5776027 | E51: =J75 -> 0.53281835 | F51: =D51-E51 -> 0.044784357 | G51: =IF(E51=0,"n.a.",F51/ABS(E51)) -> 0.084051829 | H51: =H50/H26 -> 0.54627285 | I51: =D51-H51 -> 0.031329851 | J51: =IF(H51=0,"n.a.",I51/ABS(H51)) -> 0.05735202
C52: Effective housekeeping wage per hour | D52: =J109 -> 22.707361 | E52: =J76 -> 22 | F52: =D52-E52 -> 0.70736062 | G52: =IF(E52=0,"n.a.",F52/ABS(E52)) -> 0.032152756 | H52: =H39/H50 -> 21.133071 | I52: =D52-H52 -> 1.5742895 | J52: =IF(H52=0,"n.a.",I52/ABS(H52)) -> 0.074494116
C53: Guest-service cost per occupied room | D53: =J111 -> 19.32152 | E53: =J78 -> 19.173812 | F53: =D53-E53 -> 0.1477083 | G53: =IF(E53=0,"n.a.",F53/ABS(E53)) -> 0.0077036484 | H53: =H40/H26 -> 18.587444 | I53: =D53-H53 -> 0.73407625 | J53: =IF(H53=0,"n.a.",I53/ABS(H53)) -> 0.039493125
C54: Average fixed-staff FTE | D54: =J115 -> 5 | E54: =J82 -> 5 | F54: =D54-E54 -> 0 | G54: =IF(E54=0,"n.a.",F54/ABS(E54)) -> 0 | H54: =SUM(Data!$G$200,Data!$G$201,Data!$G$202,Data!$G$203,Data!$G$204,Data!$G$205)/6 -> 4.9833333 | I54: =D54-H54 -> 0.016666667 | J54: =IF(H54=0,"n.a.",I54/ABS(H54)) -> 0.0033444816
C55: Fixed-staff cost per FTE-month | D55: =J116 -> 6026.6667 | E55: =J83 -> 6000 | F55: =D55-E55 -> 26.666667 | G55: =IF(E55=0,"n.a.",F55/ABS(E55)) -> 0.0044444444 | H55: =H42/(H54*6) -> 5791.7057 | I55: =D55-H55 -> 234.96098 | J55: =IF(H55=0,"n.a.",I55/ABS(H55)) -> 0.040568529
C57: Monthly actual-versus-budget detail
C58: Six monthly columns plus YTD. Expense variances use Actual cost minus Budget cost; positive is unfavorable. Occupancy, corporate share, distribution rate, and contribution margin variances are shown in percentage points.
C59: Metric | D59: 46023 | E59: 46054 | F59: 46082 | G59: 46113 | H59: 46143 | I59: 46174 | J59: YTD
C60: Approved budget
C61: Available room nights | D61: =Budget!D10 -> 3100 | E61: =Budget!E10 -> 2800 | F61: =Budget!F10 -> 3100 | G61: =Budget!G10 -> 3000 | H61: =Budget!H10 -> 3100 | I61: =Budget!I10 -> 3000 | J61: =SUM(D61:I61) -> 18100
C62: Occupied room nights | D62: =Budget!D11 -> 1705 | E62: =Budget!E11 -> 1624 | F62: =Budget!F11 -> 2015 | G62: =Budget!G11 -> 2100 | H62: =Budget!H11 -> 2294 | I62: =Budget!I11 -> 2340 | J62: =SUM(D62:I62) -> 12078
C63: Occupancy | D63: =Budget!D12 -> 0.55 | E63: =Budget!E12 -> 0.58 | F63: =Budget!F12 -> 0.65 | G63: =Budget!G12 -> 0.7 | H63: =Budget!H12 -> 0.74 | I63: =Budget!I12 -> 0.78 | J63: =J62/J61 -> 0.66729282
C64: Retail room nights | D64: =Budget!D14 -> 1193.5 | E64: =Budget!E14 -> 1120.56 | F64: =Budget!F14 -> 1370.2 | G64: =Budget!G14 -> 1386 | H64: =Budget!H14 -> 1491.1 | I64: =Budget!I14 -> 1497.6 | J64: =SUM(D64:I64) -> 8058.96
C65: Corporate room nights | D65: =Budget!D15 -> 511.5 | E65: =Budget!E15 -> 503.44 | F65: =Budget!F15 -> 644.8 | G65: =Budget!G15 -> 714 | H65: =Budget!H15 -> 802.9 | I65: =Budget!I15 -> 842.4 | J65: =SUM(D65:I65) -> 4019.04
C66: Corporate share | D66: =Budget!D13 -> 0.3 | E66: =Budget!E13 -> 0.31 | F66: =Budget!F13 -> 0.32 | G66: =Budget!G13 -> 0.34 | H66: =Budget!H13 -> 0.35 | I66: =Budget!I13 -> 0.36 | J66: =J65/J62 -> 0.33275708
C67: Retail ADR | D67: =Budget!D16 -> 150 | E67: =Budget!E16 -> 152 | F67: =Budget!F16 -> 158 | G67: =Budget!G16 -> 164 | H67: =Budget!H16 -> 172 | I67: =Budget!I16 -> 180 | J67: =J71/J64 -> 163.69146
C68: Corporate ADR | D68: =Budget!D17 -> 132 | E68: =Budget!E17 -> 133 | F68: =Budget!F17 -> 137 | G68: =Budget!G17 -> 140 | H68: =Budget!H17 -> 145 | I68: =Budget!I17 -> 148 | J68: =J72/J65 -> 140.29938
C69: Blended ADR | D69: =Budget!D24 -> 144.6 | E69: =Budget!E24 -> 146.11 | F69: =Budget!F24 -> 151.28 | G69: =Budget!G24 -> 155.84 | H69: =Budget!H24 -> 162.55 | I69: =Budget!I24 -> 168.48 | J69: =J73/J62 -> 155.90758
C70: RevPAR | D70: =Budget!D25 -> 79.53 | E70: =Budget!E25 -> 84.7438 | F70: =Budget!F25 -> 98.332 | G70: =Budget!G25 -> 109.088 | H70: =Budget!H25 -> 120.287 | I70: =Budget!I25 -> 131.4144 | J70: =J73/J61 -> 104.03601
C71: Retail room revenue | D71: =Budget!D21 -> 179025 | E71: =Budget!E21 -> 170325.12 | F71: =Budget!F21 -> 216491.6 | G71: =Budget!G21 -> 227304 | H71: =Budget!H21 -> 256469.2 | I71: =Budget!I21 -> 269568 | J71: =SUM(D71:I71) -> 1319182.9
C72: Corporate room revenue | D72: =Budget!D22 -> 67518 | E72: =Budget!E22 -> 66957.52 | F72: =Budget!F22 -> 88337.6 | G72: =Budget!G22 -> 99960 | H72: =Budget!H22 -> 116420.5 | I72: =Budget!I22 -> 124675.2 | J72: =SUM(D72:I72) -> 563868.82
C73: Total room revenue | D73: =Budget!D23 -> 246543 | E73: =Budget!E23 -> 237282.64 | F73: =Budget!F23 -> 304829.2 | G73: =Budget!G23 -> 327264 | H73: =Budget!H23 -> 372889.7 | I73: =Budget!I23 -> 394243.2 | J73: =SUM(D73:I73) -> 1883051.7
C74: Housekeeping hours | D74: =Budget!D31 -> 954.8 | E74: =Budget!E31 -> 893.2 | F74: =Budget!F31 -> 1088.1 | G74: =Budget!G31 -> 1113 | H74: =Budget!H31 -> 1192.88 | I74: =Budget!I31 -> 1193.4 | J74: =SUM(D74:I74) -> 6435.38
C75: Housekeeping hours per occupied room | D75: =Budget!D29 -> 0.56 | E75: =Budget!E29 -> 0.55 | F75: =Budget!F29 -> 0.54 | G75: =Budget!G29 -> 0.53 | H75: =Budget!H29 -> 0.52 | I75: =Budget!I29 -> 0.51 | J75: =J74/J62 -> 0.53281835
C76: Effective housekeeping wage per hour | D76: =Budget!D30 -> 22 | E76: =Budget!E30 -> 22 | F76: =Budget!F30 -> 22 | G76: =Budget!G30 -> 22 | H76: =Budget!H30 -> 22 | I76: =Budget!I30 -> 22 | J76: =J77/J74 -> 22
C77: Housekeeping payroll | D77: =Budget!D32 -> 21005.6 | E77: =Budget!E32 -> 19650.4 | F77: =Budget!F32 -> 23938.2 | G77: =Budget!G32 -> 24486 | H77: =Budget!H32 -> 26243.36 | I77: =Budget!I32 -> 26254.8 | J77: =SUM(D77:I77) -> 141578.36
C78: Guest-service cost per occupied room | D78: =Budget!D33 -> 18.5 | E78: =Budget!E33 -> 18.7 | F78: =Budget!F33 -> 19 | G78: =Budget!G33 -> 19.2 | H78: =Budget!H33 -> 19.5 | I78: =Budget!I33 -> 19.8 | J78: =J79/J62 -> 19.173812
C79: Guest-service expense | D79: =Budget!D34 -> 31542.5 | E79: =Budget!E34 -> 30368.8 | F79: =Budget!F34 -> 38285 | G79: =Budget!G34 -> 40320 | H79: =Budget!H34 -> 44733 | I79: =Budget!I34 -> 46332 | J79: =SUM(D79:I79) -> 231581.3
C80: Distribution fee rate | D80: =Budget!D35 -> 0.04 | E80: =Budget!E35 -> 0.04 | F80: =Budget!F35 -> 0.04 | G80: =Budget!G35 -> 0.04 | H80: =Budget!H35 -> 0.04 | I80: =Budget!I35 -> 0.04 | J80: =J81/J73 -> 0.04
C81: Distribution and payment expense | D81: =Budget!D36 -> 9861.72 | E81: =Budget!E36 -> 9491.3056 | F81: =Budget!F36 -> 12193.168 | G81: =Budget!G36 -> 13090.56 | H81: =Budget!H36 -> 14915.588 | I81: =Budget!I36 -> 15769.728 | J81: =SUM(D81:I81) -> 75322.07
C82: Average fixed-staff FTE | D82: =Budget!D40 -> 5 | E82: =Budget!E40 -> 5 | F82: =Budget!F40 -> 5 | G82: =Budget!G40 -> 5 | H82: =Budget!H40 -> 5 | I82: =Budget!I40 -> 5 | J82: =SUM(D82:I82)/6 -> 5
C83: Fixed-staff cost per FTE-month | D83: =Budget!D41 -> 6000 | E83: =Budget!E41 -> 6000 | F83: =Budget!F41 -> 6000 | G83: =Budget!G41 -> 6000 | H83: =Budget!H41 -> 6000 | I83: =Budget!I41 -> 6000 | J83: =J84/SUM(D82:I82) -> 6000
C84: Fixed-staff payroll | D84: =Budget!D42 -> 30000 | E84: =Budget!E42 -> 30000 | F84: =Budget!F42 -> 30000 | G84: =Budget!G42 -> 30000 | H84: =Budget!H42 -> 30000 | I84: =Budget!I42 -> 30000 | J84: =SUM(D84:I84) -> 180000
C85: Rent | D85: =Budget!D43 -> 78000 | E85: =Budget!E43 -> 78000 | F85: =Budget!F43 -> 78000 | G85: =Budget!G43 -> 78000 | H85: =Budget!H43 -> 78000 | I85: =Budget!I43 -> 78000 | J85: =SUM(D85:I85) -> 468000
C86: Property overhead | D86: =Budget!D44 -> 28000 | E86: =Budget!E44 -> 28100 | F86: =Budget!F44 -> 28500 | G86: =Budget!G44 -> 28600 | H86: =Budget!H44 -> 28900 | I86: =Budget!I44 -> 29200 | J86: =SUM(D86:I86) -> 171300
C87: Marketing | D87: =Budget!D45 -> 10000 | E87: =Budget!E45 -> 9000 | F87: =Budget!F45 -> 11000 | G87: =Budget!G45 -> 13000 | H87: =Budget!H45 -> 14000 | I87: =Budget!I45 -> 24000 | J87: =SUM(D87:I87) -> 81000
C88: Total operating costs | D88: =Budget!D49 -> 208409.82 | E88: =Budget!E49 -> 204610.51 | F88: =Budget!F49 -> 221916.37 | G88: =Budget!G49 -> 227496.56 | H88: =Budget!H49 -> 236791.95 | I88: =Budget!I49 -> 249556.53 | J88: =SUM(D88:I88) -> 1348781.7
C89: Property operating contribution | D89: =Budget!D50 -> 38133.18 | E89: =Budget!E50 -> 32672.134 | F89: =Budget!F50 -> 82912.832 | G89: =Budget!G50 -> 99767.44 | H89: =Budget!H50 -> 136097.75 | I89: =Budget!I50 -> 144686.67 | J89: =SUM(D89:I89) -> 534270.01
C90: Contribution margin | D90: =Budget!D51 -> 0.15467152 | E90: =Budget!E51 -> 0.1376929 | F90: =Budget!F51 -> 0.27199767 | G90: =Budget!G51 -> 0.30485308 | H90: =Budget!H51 -> 0.36498126 | I90: =Budget!I51 -> 0.36699852 | J90: =J89/J73 -> 0.28372561
C92: Metric | D92: 46023 | E92: 46054 | F92: 46082 | G92: 46113 | H92: 46143 | I92: 46174 | J92: YTD
C93: Recorded actual
C94: Available room nights | D94: =100*DAY(DATE(YEAR(D$92),MONTH(D$92)+1,0)) -> 3100 | E94: =100*DAY(DATE(YEAR(E$92),MONTH(E$92)+1,0)) -> 2800 | F94: =100*DAY(DATE(YEAR(F$92),MONTH(F$92)+1,0)) -> 3100 | G94: =100*DAY(DATE(YEAR(G$92),MONTH(G$92)+1,0)) -> 3000 | H94: =100*DAY(DATE(YEAR(H$92),MONTH(H$92)+1,0)) -> 3100 | I94: =100*DAY(DATE(YEAR(I$92),MONTH(I$92)+1,0)) -> 3000 | J94: =SUM(D94:I94) -> 18100
C95: Occupied room nights | D95: =D97+D98 -> 1658 | E95: =E97+E98 -> 1604 | F95: =F97+F98 -> 1922 | G95: =G97+G98 -> 1950 | H95: =H97+H98 -> 2139 | I95: =I97+I98 -> 2265 | J95: =SUM(D95:I95) -> 11538
C96: Occupancy | D96: =D95/D94 -> 0.53483871 | E96: =E95/E94 -> 0.57285714 | F96: =F95/F94 -> 0.62 | G96: =G95/G94 -> 0.65 | H96: =H95/H94 -> 0.69 | I96: =I95/I94 -> 0.755 | J96: =J95/J94 -> 0.63745856
C97: Retail room nights | D97: =SUMIFS(Data!$F$158:$F$193,Data!$D$158:$D$193,D$92,Data!$E$158:$E$193,"Retail/Leisure") -> 1144 | E97: =SUMIFS(Data!$F$158:$F$193,Data!$D$158:$D$193,E$92,Data!$E$158:$E$193,"Retail/Leisure") -> 1075 | F97: =SUMIFS(Data!$F$158:$F$193,Data!$D$158:$D$193,F$92,Data!$E$158:$E$193,"Retail/Leisure") -> 1192 | G97: =SUMIFS(Data!$F$158:$F$193,Data!$D$158:$D$193,G$92,Data!$E$158:$E$193,"Retail/Leisure") -> 1111 | H97: =SUMIFS(Data!$F$158:$F$193,Data!$D$158:$D$193,H$92,Data!$E$158:$E$193,"Retail/Leisure") -> 1176 | I97: =SUMIFS(Data!$F$158:$F$193,Data!$D$158:$D$193,I$92,Data!$E$158:$E$193,"Retail/Leisure") -> 1314 | J97: =SUM(D97:I97) -> 7012
C98: Corporate room nights | D98: =SUMIFS(Data!$F$158:$F$193,Data!$D$158:$D$193,D$92,Data!$E$158:$E$193,"Negotiated Corporate") -> 514 | E98: =SUMIFS(Data!$F$158:$F$193,Data!$D$158:$D$193,E$92,Data!$E$158:$E$193,"Negotiated Corporate") -> 529 | F98: =SUMIFS(Data!$F$158:$F$193,Data!$D$158:$D$193,F$92,Data!$E$158:$E$193,"Negotiated Corporate") -> 730 | G98: =SUMIFS(Data!$F$158:$F$193,Data!$D$158:$D$193,G$92,Data!$E$158:$E$193,"Negotiated Corporate") -> 839 | H98: =SUMIFS(Data!$F$158:$F$193,Data!$D$158:$D$193,H$92,Data!$E$158:$E$193,"Negotiated Corporate") -> 963 | I98: =SUMIFS(Data!$F$158:$F$193,Data!$D$158:$D$193,I$92,Data!$E$158:$E$193,"Negotiated Corporate") -> 951 | J98: =SUM(D98:I98) -> 4526
C99: Corporate share | D99: =D98/D95 -> 0.31001206 | E99: =E98/E95 -> 0.3298005 | F99: =F98/F95 -> 0.3798127 | G99: =G98/G95 -> 0.43025641 | H99: =H98/H95 -> 0.45021038 | I99: =I98/I95 -> 0.41986755 | J99: =J98/J95 -> 0.39226902
C100: Retail ADR | D100: =D104/D97 -> 151 | E100: =E104/E97 -> 153 | F100: =F104/F97 -> 158.5 | G100: =G104/G97 -> 164 | H100: =H104/H97 -> 171 | I100: =I104/I97 -> 181 | J100: =J104/J97 -> 163.61737
C101: Corporate ADR | D101: =D105/D98 -> 132.5 | E101: =E105/E98 -> 133 | F101: =F105/F98 -> 137.5 | G101: =G105/G98 -> 140.5 | H101: =H105/H98 -> 145 | I101: =I105/I98 -> 148.5 | J101: =J105/J98 -> 140.86942
C102: Blended ADR | D102: =D106/D95 -> 145.26478 | E102: =E106/E95 -> 146.40399 | F102: =F106/F95 -> 150.52393 | G102: =G106/G95 -> 153.88897 | H102: =H106/H95 -> 159.29453 | I102: =I106/I95 -> 167.3543 | J102: =J106/J95 -> 154.69405
C103: RevPAR | D103: =D106/D94 -> 77.693226 | E103: =E106/E94 -> 83.868571 | F103: =F106/F94 -> 93.324839 | G103: =G106/G94 -> 100.02783 | H103: =H106/H94 -> 109.91323 | I103: =I106/I94 -> 126.3525 | J103: =J106/J94 -> 98.61105
C104: Retail room revenue | D104: =SUMIFS(Data!$G$158:$G$193,Data!$D$158:$D$193,D$92,Data!$E$158:$E$193,"Retail/Leisure") -> 172744 | E104: =SUMIFS(Data!$G$158:$G$193,Data!$D$158:$D$193,E$92,Data!$E$158:$E$193,"Retail/Leisure") -> 164475 | F104: =SUMIFS(Data!$G$158:$G$193,Data!$D$158:$D$193,F$92,Data!$E$158:$E$193,"Retail/Leisure") -> 188932 | G104: =SUMIFS(Data!$G$158:$G$193,Data!$D$158:$D$193,G$92,Data!$E$158:$E$193,"Retail/Leisure") -> 182204 | H104: =SUMIFS(Data!$G$158:$G$193,Data!$D$158:$D$193,H$92,Data!$E$158:$E$193,"Retail/Leisure") -> 201096 | I104: =SUMIFS(Data!$G$158:$G$193,Data!$D$158:$D$193,I$92,Data!$E$158:$E$193,"Retail/Leisure") -> 237834 | J104: =SUM(D104:I104) -> 1147285
C105: Corporate room revenue | D105: =SUMIFS(Data!$G$158:$G$193,Data!$D$158:$D$193,D$92,Data!$E$158:$E$193,"Negotiated Corporate") -> 68105 | E105: =SUMIFS(Data!$G$158:$G$193,Data!$D$158:$D$193,E$92,Data!$E$158:$E$193,"Negotiated Corporate") -> 70357 | F105: =SUMIFS(Data!$G$158:$G$193,Data!$D$158:$D$193,F$92,Data!$E$158:$E$193,"Negotiated Corporate") -> 100375 | G105: =SUMIFS(Data!$G$158:$G$193,Data!$D$158:$D$193,G$92,Data!$E$158:$E$193,"Negotiated Corporate") -> 117879.5 | H105: =SUMIFS(Data!$G$158:$G$193,Data!$D$158:$D$193,H$92,Data!$E$158:$E$193,"Negotiated Corporate") -> 139635 | I105: =SUMIFS(Data!$G$158:$G$193,Data!$D$158:$D$193,I$92,Data!$E$158:$E$193,"Negotiated Corporate") -> 141223.5 | J105: =SUM(D105:I105) -> 637575
C106: Total room revenue | D106: =D104+D105 -> 240849 | E106: =E104+E105 -> 234832 | F106: =F104+F105 -> 289307 | G106: =G104+G105 -> 300083.5 | H106: =H104+H105 -> 340731 | I106: =I104+I105 -> 379057.5 | J106: =SUM(D106:I106) -> 1784860
...

Sheet Review
T1: Driver | U1: Contribution impact | W1: Month | X1: Budget | Y1: Actual Jan–Jun / Base RF1 Jul–Dec | AB1: Case | AC1: Property operating contribution
B2: PALMETTO STAY | MANAGEMENT REVIEW | C2: PALMETTO STAY | MANAGEMENT REVIEW | D2: PALMETTO STAY | MANAGEMENT REVIEW | E2: PALMETTO STAY | MANAGEMENT REVIEW | F2: PALMETTO STAY | MANAGEMENT REVIEW | G2: PALMETTO STAY | MANAGEMENT REVIEW | H2: PALMETTO STAY | MANAGEMENT REVIEW | I2: PALMETTO STAY | MANAGEMENT REVIEW | J2: PALMETTO STAY | MANAGEMENT REVIEW | K2: PALMETTO STAY | MANAGEMENT REVIEW | L2: PALMETTO STAY | MANAGEMENT REVIEW | M2: PALMETTO STAY | MANAGEMENT REVIEW | N2: PALMETTO STAY | MANAGEMENT REVIEW | T2: Revenue volume | U2: =Variance!D241 -> -84994.69 | W2: Jan | X2: =Budget!D12*100 -> 55 | Y2: =Variance!D96*100 -> 53.483871 | AB2: Budget | AC2: =Forecast!D16 -> 1279795.4
B3: PALMETTO STAY | MANAGEMENT REVIEW | C3: PALMETTO STAY | MANAGEMENT REVIEW | D3: PALMETTO STAY | MANAGEMENT REVIEW | E3: PALMETTO STAY | MANAGEMENT REVIEW | F3: PALMETTO STAY | MANAGEMENT REVIEW | G3: PALMETTO STAY | MANAGEMENT REVIEW | H3: PALMETTO STAY | MANAGEMENT REVIEW | I3: PALMETTO STAY | MANAGEMENT REVIEW | J3: PALMETTO STAY | MANAGEMENT REVIEW | K3: PALMETTO STAY | MANAGEMENT REVIEW | L3: PALMETTO STAY | MANAGEMENT REVIEW | M3: PALMETTO STAY | MANAGEMENT REVIEW | N3: PALMETTO STAY | MANAGEMENT REVIEW | T3: Customer mix | U3: =Variance!D242 -> -17667.05 | W3: Feb | X3: =Budget!E12*100 -> 58 | Y3: =Variance!E96*100 -> 57.285714 | AB3: Base | AC3: =Forecast!E16 -> 1137547.2
B4: H1 2026 actual performance vs approved budget | Information cutoff: July 8, 2026 | Synthetic case v1.0 | C4: H1 2026 actual performance vs approved budget | Information cutoff: July 8, 2026 | Synthetic case v1.0 | D4: H1 2026 actual performance vs approved budget | Information cutoff: July 8, 2026 | Synthetic case v1.0 | E4: H1 2026 actual performance vs approved budget | Information cutoff: July 8, 2026 | Synthetic case v1.0 | F4: H1 2026 actual performance vs approved budget | Information cutoff: July 8, 2026 | Synthetic case v1.0 | G4: H1 2026 actual performance vs approved budget | Information cutoff: July 8, 2026 | Synthetic case v1.0 | H4: H1 2026 actual performance vs approved budget | Information cutoff: July 8, 2026 | Synthetic case v1.0 | I4: H1 2026 actual performance vs approved budget | Information cutoff: July 8, 2026 | Synthetic case v1.0 | J4: H1 2026 actual performance vs approved budget | Information cutoff: July 8, 2026 | Synthetic case v1.0 | K4: H1 2026 actual performance vs approved budget | Information cutoff: July 8, 2026 | Synthetic case v1.0 | L4: H1 2026 actual performance vs approved budget | Information cutoff: July 8, 2026 | Synthetic case v1.0 | M4: H1 2026 actual performance vs approved budget | Information cutoff: July 8, 2026 | Synthetic case v1.0 | N4: H1 2026 actual performance vs approved budget | Information cutoff: July 8, 2026 | Synthetic case v1.0 | T4: Rate | U4: =Variance!D243 -> 4470 | W4: Mar | X4: =Budget!F12*100 -> 65 | Y4: =Variance!F96*100 -> 62 | AB4: Upside | AC4: =Forecast!G16 -> 1198074
T5: Housekeeping | U5: =SUM(Variance!D244:D246) -> -9752.12 | W5: Apr | X5: =Budget!G12*100 -> 70 | Y5: =Variance!G96*100 -> 65 | AB5: Downside | AC5: =Forecast!I16 -> 1031710.5
B6: H1 PERFORMANCE AT A GLANCE | C6: H1 PERFORMANCE AT A GLANCE | D6: H1 PERFORMANCE AT A GLANCE | E6: H1 PERFORMANCE AT A GLANCE | F6: H1 PERFORMANCE AT A GLANCE | G6: H1 PERFORMANCE AT A GLANCE | H6: H1 PERFORMANCE AT A GLANCE | I6: H1 PERFORMANCE AT A GLANCE | J6: H1 PERFORMANCE AT A GLANCE | K6: H1 PERFORMANCE AT A GLANCE | L6: H1 PERFORMANCE AT A GLANCE | M6: H1 PERFORMANCE AT A GLANCE | N6: H1 PERFORMANCE AT A GLANCE | T6: Guest services | U6: =SUM(Variance!D247:D248) -> 8649.6 | W6: May | X6: =Budget!H12*100 -> 74 | Y6: =Variance!H96*100 -> 69
T7: Distribution | U7: =Variance!D249 -> 3927.6696 | W7: Jun (A) | X7: =Budget!I12*100 -> 78 | Y7: =Variance!I96*100 -> 75.5
B8: Metric | C8: Actual | D8: Budget | E8: Variance | T8: Fixed staff | U8: =SUM(Variance!D250:D251) -> -800 | W8: Jul (F) | X8: =Budget!J12*100 -> 84 | Y8: =Forecast!J33*100 -> 82.322581
B9: Occupancy | C9: =Variance!D27 -> 0.63745856 | D9: =Variance!E27 -> 0.66729282 | E9: =Variance!F27 -> -2.9834254 | T9: Overhead | U9: =Variance!D253 -> -1760 | W9: Aug | X9: =Budget!K12*100 -> 82 | Y9: =Forecast!K33*100 -> 80.354839
B10: Room revenue | C10: =Variance!D38 -> 1784860 | D10: =Variance!E38 -> 1883051.7 | E10: =Variance!F38 -> -98191.74 | T10: Marketing | U10: =Variance!D254 -> 17400 | W10: Sep | X10: =Budget!L12*100 -> 73 | Y10: =Forecast!L33*100 -> 71.533333
B11: Property contribution | C11: =Variance!D47 -> 453743.42 | D11: =Variance!E47 -> 534270.01 | E11: =Variance!F47 -> -80526.59 | W11: Oct | X11: =Budget!M12*100 -> 71 | Y11: =Forecast!M33*100 -> 69.935484
B12: Contribution margin | C12: =Variance!D48 -> 0.25421793 | D12: =Variance!E48 -> 0.28372561 | E12: =Variance!F48 -> -2.9507681 | W12: Nov | X12: =Budget!N12*100 -> 61 | Y12: =Forecast!N33*100 -> 60.4
W13: Dec | X13: =Budget!O12*100 -> 59 | Y13: =Forecast!O33*100 -> 58.419355
B15: MANAGEMENT READOUT | C15: MANAGEMENT READOUT | D15: MANAGEMENT READOUT | E15: MANAGEMENT READOUT | F15: MANAGEMENT READOUT | G15: H1 CONTRIBUTION IMPACT BY DRIVER ($000s) | H15: H1 CONTRIBUTION IMPACT BY DRIVER ($000s) | I15: H1 CONTRIBUTION IMPACT BY DRIVER ($000s) | J15: H1 CONTRIBUTION IMPACT BY DRIVER ($000s) | K15: H1 CONTRIBUTION IMPACT BY DRIVER ($000s) | L15: H1 CONTRIBUTION IMPACT BY DRIVER ($000s) | M15: H1 CONTRIBUTION IMPACT BY DRIVER ($000s) | N15: H1 CONTRIBUTION IMPACT BY DRIVER ($000s)
B16: Demand, not rate, is the primary first-half issue. Lower occupied room nights drove most of the revenue miss, while a richer corporate mix also diluted the benefit of modestly favorable realized rates. | C16: Demand, not rate, is the primary first-half issue. Lower occupied room nights drove most of the revenue miss, while a richer corporate mix also diluted the benefit of modestly favorable realized rates. | D16: Demand, not rate, is the primary first-half issue. Lower occupied room nights drove most of the revenue miss, while a richer corporate mix also diluted the benefit of modestly favorable realized rates. | E16: Demand, not rate, is the primary first-half issue. Lower occupied room nights drove most of the revenue miss, while a richer corporate mix also diluted the benefit of modestly favorable realized rates. | F16: Demand, not rate, is the primary first-half issue. Lower occupied room nights drove most of the revenue miss, while a richer corporate mix also diluted the benefit of modestly favorable realized rates.
B17: Demand, not rate, is the primary first-half issue. Lower occupied room nights drove most of the revenue miss, while a richer corporate mix also diluted the benefit of modestly favorable realized rates. | C17: Demand, not rate, is the primary first-half issue. Lower occupied room nights drove most of the revenue miss, while a richer corporate mix also diluted the benefit of modestly favorable realized rates. | D17: Demand, not rate, is the primary first-half issue. Lower occupied room nights drove most of the revenue miss, while a richer corporate mix also diluted the benefit of modestly favorable realized rates. | E17: Demand, not rate, is the primary first-half issue. Lower occupied room nights drove most of the revenue miss, while a richer corporate mix also diluted the benefit of modestly favorable realized rates. | F17: Demand, not rate, is the primary first-half issue. Lower occupied room nights drove most of the revenue miss, while a richer corporate mix also diluted the benefit of modestly favorable realized rates.
B18: Demand, not rate, is the primary first-half issue. Lower occupied room nights drove most of the revenue miss, while a richer corporate mix also diluted the benefit of modestly favorable realized rates. | C18: Demand, not rate, is the primary first-half issue. Lower occupied room nights drove most of the revenue miss, while a richer corporate mix also diluted the benefit of modestly favorable realized rates. | D18: Demand, not rate, is the primary first-half issue. Lower occupied room nights drove most of the revenue miss, while a richer corporate mix also diluted the benefit of modestly favorable realized rates. | E18: Demand, not rate, is the primary first-half issue. Lower occupied room nights drove most of the revenue miss, while a richer corporate mix also diluted the benefit of modestly favorable realized rates. | F18: Demand, not rate, is the primary first-half issue. Lower occupied room nights drove most of the revenue miss, while a richer corporate mix also diluted the benefit of modestly favorable realized rates.
B19: Property operating contribution finished below plan. Lower revenue was the dominant pressure; housekeeping productivity and wage effects added cost headwinds despite favorable volume flexing. | C19: Property operating contribution finished below plan. Lower revenue was the dominant pressure; housekeeping productivity and wage effects added cost headwinds despite favorable volume flexing. | D19: Property operating contribution finished below plan. Lower revenue was the dominant pressure; housekeeping productivity and wage effects added cost headwinds despite favorable volume flexing. | E19: Property operating contribution finished below plan. Lower revenue was the dominant pressure; housekeeping productivity and wage effects added cost headwinds despite favorable volume flexing. | F19: Property operating contribution finished below plan. Lower revenue was the dominant pressure; housekeeping productivity and wage effects added cost headwinds despite favorable volume flexing.
B20: Property operating contribution finished below plan. Lower revenue was the dominant pressure; housekeeping productivity and wage effects added cost headwinds despite favorable volume flexing. | C20: Property operating contribution finished below plan. Lower revenue was the dominant pressure; housekeeping productivity and wage effects added cost headwinds despite favorable volume flexing. | D20: Property operating contribution finished below plan. Lower revenue was the dominant pressure; housekeeping productivity and wage effects added cost headwinds despite favorable volume flexing. | E20: Property operating contribution finished below plan. Lower revenue was the dominant pressure; housekeeping productivity and wage effects added cost headwinds despite favorable volume flexing. | F20: Property operating contribution finished below plan. Lower revenue was the dominant pressure; housekeeping productivity and wage effects added cost headwinds despite favorable volume flexing.
B21: Property operating contribution finished below plan. Lower revenue was the dominant pressure; housekeeping productivity and wage effects added cost headwinds despite favorable volume flexing. | C21: Property operating contribution finished below plan. Lower revenue was the dominant pressure; housekeeping productivity and wage effects added cost headwinds despite favorable volume flexing. | D21: Property operating contribution finished below plan. Lower revenue was the dominant pressure; housekeeping productivity and wage effects added cost headwinds despite favorable volume flexing. | E21: Property operating contribution finished below plan. Lower revenue was the dominant pressure; housekeeping productivity and wage effects added cost headwinds despite favorable volume flexing. | F21: Property operating contribution finished below plan. Lower revenue was the dominant pressure; housekeeping productivity and wage effects added cost headwinds despite favorable volume flexing.
B22: The marketing underspend is timing, not a structural saving. The deferred June activity is included once in September in every RF1 scenario, preserving service timing without double counting. | C22: The marketing underspend is timing, not a structural saving. The deferred June activity is included once in September in every RF1 scenario, preserving service timing without double counting. | D22: The marketing underspend is timing, not a structural saving. The deferred June activity is included once in September in every RF1 scenario, preserving service timing without double counting. | E22: The marketing underspend is timing, not a structural saving. The deferred June activity is included once in September in every RF1 scenario, preserving service timing without double counting. | F22: The marketing underspend is timing, not a structural saving. The deferred June activity is included once in September in every RF1 scenario, preserving service timing without double counting.
B23: The marketing underspend is timing, not a structural saving. The deferred June activity is included once in September in every RF1 scenario, preserving service timing without double counting. | C23: The marketing underspend is timing, not a structural saving. The deferred June activity is included once in September in every RF1 scenario, preserving service timing without double counting. | D23: The marketing underspend is timing, not a structural saving. The deferred June activity is included once in September in every RF1 scenario, preserving service timing without double counting. | E23: The marketing underspend is timing, not a structural saving. The deferred June activity is included once in September in every RF1 scenario, preserving service timing without double counting. | F23: The marketing underspend is timing, not a structural saving. The deferred June activity is included once in September in every RF1 scenario, preserving service timing without double counting.
B24: The marketing underspend is timing, not a structural saving. The deferred June activity is included once in September in every RF1 scenario, preserving service timing without double counting. | C24: The marketing underspend is timing, not a structural saving. The deferred June activity is included once in September in every RF1 scenario, preserving service timing without double counting. | D24: The marketing underspend is timing, not a structural saving. The deferred June activity is included once in September in every RF1 scenario, preserving service timing without double counting. | E24: The marketing underspend is timing, not a structural saving. The deferred June activity is included once in September in every RF1 scenario, preserving service timing without double counting. | F24: The marketing underspend is timing, not a structural saving. The deferred June activity is included once in September in every RF1 scenario, preserving service timing without double counting.
B25: The Base outlook assumes partial demand recovery and gradual housekeeping normalization. The unconfirmed May overhead item is not annualized; it remains a follow-up rather than a recurring forecast assumption. | C25: The Base outlook assumes partial demand recovery and gradual housekeeping normalization. The unconfirmed May overhead item is not annualized; it remains a follow-up rather than a recurring forecast assumption. | D25: The Base outlook assumes partial demand recovery and gradual housekeeping normalization. The unconfirmed May overhead item is not annualized; it remains a follow-up rather than a recurring forecast assumption. | E25: The Base outlook assumes partial demand recovery and gradual housekeeping normalization. The unconfirmed May overhead item is not annualized; it remains a follow-up rather than a recurring forecast assumption. | F25: The Base outlook assumes partial demand recovery and gradual housekeeping normalization. The unconfirmed May overhead item is not annualized; it remains a follow-up rather than a recurring forecast assumption.
B26: The Base outlook assumes partial demand recovery and gradual housekeeping normalization. The unconfirmed May overhead item is not annualized; it remains a follow-up rather than a recurring forecast assumption. | C26: The Base outlook assumes partial demand recovery and gradual housekeeping normalization. The unconfirmed May overhead item is not annualized; it remains a follow-up rather than a recurring forecast assumption. | D26: The Base outlook assumes partial demand recovery and gradual housekeeping normalization. The unconfirmed May overhead item is not annualized; it remains a follow-up rather than a recurring forecast assumption. | E26: The Base outlook assumes partial demand recovery and gradual housekeeping normalization. The unconfirmed May overhead item is not annualized; it remains a follow-up rather than a recurring forecast assumption. | F26: The Base outlook assumes partial demand recovery and gradual housekeeping normalization. The unconfirmed May overhead item is not annualized; it remains a follow-up rather than a recurring forecast assumption.
B27: The Base outlook assumes partial demand recovery and gradual housekeeping normalization. The unconfirmed May overhead item is not annualized; it remains a follow-up rather than a recurring forecast assumption. | C27: The Base outlook assumes partial demand recovery and gradual housekeeping normalization. The unconfirmed May overhead item is not annualized; it remains a follow-up rather than a recurring forecast assumption. | D27: The Base outlook assumes partial demand recovery and gradual housekeeping normalization. The unconfirmed May overhead item is not annualized; it remains a follow-up rather than a recurring forecast assumption. | E27: The Base outlook assumes partial demand recovery and gradual housekeeping normalization. The unconfirmed May overhead item is not annualized; it remains a follow-up rather than a recurring forecast assumption. | F27: The Base outlook assumes partial demand recovery and gradual housekeeping normalization. The unconfirmed May overhead item is not annualized; it remains a follow-up rather than a recurring forecast assumption.
... B30: Driver | C30: Actual | D30: Budget | E30: Variance | F30: Read-through
B31: Occupied room nights | C31: =Variance!D26 -> 11538 | D31: =Variance!E26 -> 12078 | E31: =Variance!F26 -> -540 | F31: Demand shortfall
B32: Corporate share | C32: =Variance!D30 -> 0.39226902 | D32: =Variance!E30 -> 0.33275708 | E32: =Variance!F30 -> 5.9511945 | F32: Mix shifted corporate
B33: Blended ADR | C33: =Variance!D33 -> 154.69405 | D33: =Variance!E33 -> 155.90758 | E33: =Variance!F33 -> -1.2135246 | F33: Near plan
B34: HK hours / occupied room | C34: =Variance!D51 -> 0.5776027 | D34: =Variance!E51 -> 0.53281835 | E34: =Variance!F51 -> 0.044784357 | F34: Efficiency pressure | G34: BRIDGE RECONCILIATION | Positive impact is favorable | H34: BRIDGE RECONCILIATION | Positive impact is favorable | I34: BRIDGE RECONCILIATION | Positive impact is favorable | J34: BRIDGE RECONCILIATION | Positive impact is favorable | K34: BRIDGE RECONCILIATION | Positive impact is favorable | L34: BRIDGE RECONCILIATION | Positive impact is favorable | M34: BRIDGE RECONCILIATION | Positive impact is favorable | N34: BRIDGE RECONCILIATION | Positive impact is favorable
B35: HK effective wage / hour | C35: =Variance!D52 -> 22.707361 | D35: =Variance!E52 -> 22 | E35: =Variance!F52 -> 0.70736062 | F35: Structural wage step-up | G35: Bridge component | L35: Impact | N35: Direction
B36: Guest-service cost / room | C36: =Variance!D53 -> 19.32152 | D36: =Variance!E53 -> 19.173812 | E36: =Variance!F53 -> 0.1477083 | F36: Slight unit-cost pressure | G36: YTD budget contribution | L36: =Variance!D240 -> 534270.01 | N36: Starting point
G37: Revenue — volume | L37: =Variance!D241 -> -84994.69 | N37: =Variance!E241 -> Unfavorable
G38: Revenue — customer mix | L38: =Variance!D242 -> -17667.05 | N38: =Variance!E242 -> Unfavorable
G39: Revenue — rate | L39: =Variance!D243 -> 4470 | N39: =Variance!E243 -> Favorable
G40: Housekeeping — volume | L40: =Variance!D244 -> 6289.58 | N40: =Variance!E244 -> Favorable
G41: Housekeeping — efficiency | L41: =Variance!D245 -> -11327.58 | N41: =Variance!E245 -> Unfavorable
G42: Housekeeping — wage rate | L42: =Variance!D246 -> -4714.12 | N42: =Variance!E246 -> Unfavorable
G43: Guest services — net | L43: =SUM(Variance!D247:D248) -> 8649.6 | N43: =IF(L43>0,"Favorable",IF(L43<0,"Unfavorable","Neutral")) -> Favorable
G44: Distribution fee | L44: =Variance!D249 -> 3927.6696 | N44: =Variance!E249 -> Favorable
G45: Fixed staff — net | L45: =SUM(Variance!D250:D251) -> -800 | N45: =IF(L45>0,"Favorable",IF(L45<0,"Unfavorable","Neutral")) -> Unfavorable
G46: Rent and overhead | L46: =SUM(Variance!D252:D253) -> -1760 | N46: =IF(L46>0,"Favorable",IF(L46<0,"Unfavorable","Neutral")) -> Unfavorable
G47: Marketing timing | L47: =Variance!D254 -> 17400 | N47: =Variance!E254 -> Favorable
G48: Recorded YTD contribution | L48: =Variance!D256 -> 453743.42 | N48: Ending point
B50: 2026 RF1 OUTLOOK & ACTIONS | C50: 2026 RF1 OUTLOOK & ACTIONS | D50: 2026 RF1 OUTLOOK & ACTIONS | E50: 2026 RF1 OUTLOOK & ACTIONS | F50: 2026 RF1 OUTLOOK & ACTIONS | G50: 2026 RF1 OUTLOOK & ACTIONS | H50: 2026 RF1 OUTLOOK & ACTIONS | I50: 2026 RF1 OUTLOOK & ACTIONS | J50: 2026 RF1 OUTLOOK & ACTIONS | K50: 2026 RF1 OUTLOOK & ACTIONS | L50: 2026 RF1 OUTLOOK & ACTIONS | M50: 2026 RF1 OUTLOOK & ACTIONS | N50: 2026 RF1 OUTLOOK & ACTIONS
B51: 2026 RF1 OUTLOOK & ACTIONS | C51: 2026 RF1 OUTLOOK & ACTIONS | D51: 2026 RF1 OUTLOOK & ACTIONS | E51: 2026 RF1 OUTLOOK & ACTIONS | F51: 2026 RF1 OUTLOOK & ACTIONS | G51: 2026 RF1 OUTLOOK & ACTIONS | H51: 2026 RF1 OUTLOOK & ACTIONS | I51: 2026 RF1 OUTLOOK & ACTIONS | J51: 2026 RF1 OUTLOOK & ACTIONS | K51: 2026 RF1 OUTLOOK & ACTIONS | L51: 2026 RF1 OUTLOOK & ACTIONS | M51: 2026 RF1 OUTLOOK & ACTIONS | N51: 2026 RF1 OUTLOOK & ACTIONS
B52: Palmetto Stay | Actuals: January–June | Forecast: July–December | Base is the working outlook; scenarios are unweighted decision-support cases | C52: Palmetto Stay | Actuals: January–June | Forecast: July–December | Base is the working outlook; scenarios are unweighted decision-support cases | D52: Palmetto Stay | Actuals: January–June | Forecast: July–December | Base is the working outlook; scenarios are unweighted decision-support cases | E52: Palmetto Stay | Actuals: January–June | Forecast: July–December | Base is the working outlook; scenarios are unweighted decision-support cases | F52: Palmetto Stay | Actuals: January–June | Forecast: July–December | Base is the working outlook; scenarios are unweighted decision-support cases | G52: Palmetto Stay | Actuals: January–June | Forecast: July–December | Base is the working outlook; scenarios are unweighted decision-support cases | H52: Palmetto Stay | Actuals: January–June | Forecast: July–December | Base is the working outlook; scenarios are unweighted decision-support cases | I52: Palmetto Stay | Actuals: January–June | Forecast: July–December | Base is the working outlook; scenarios are unweighted decision-support cases | J52: Palmetto Stay | Actuals: January–June | Forecast: July–December | Base is the working outlook; scenarios are unweighted decision-support cases | K52: Palmetto Stay | Actuals: January–June | Forecast: July–December | Base is the working outlook; scenarios are unweighted decision-support cases | L52: Palmetto Stay | Actuals: January–June | Forecast: July–December | Base is the working outlook; scenarios are unweighted decision-support cases | M52: Palmetto Stay | Actuals: January–June | Forecast: July–December | Base is the working outlook; scenarios are unweighted decision-support cases | N52: Palmetto Stay | Actuals: January–June | Forecast: July–December | Base is the working outlook; scenarios are unweighted decision-support cases
B54: FULL-YEAR BASE OUTLOOK | C54: FULL-YEAR BASE OUTLOOK | D54: FULL-YEAR BASE OUTLOOK | E54: FULL-YEAR BASE OUTLOOK | F54: FULL-YEAR BASE OUTLOOK | G54: FULL-YEAR BASE OUTLOOK | H54: SCENARIO RANGE | Full-year 2026 | I54: SCENARIO RANGE | Full-year 2026 | J54: SCENARIO RANGE | Full-year 2026 | K54: SCENARIO RANGE | Full-year 2026 | L54: SCENARIO RANGE | Full-year 2026 | M54: SCENARIO RANGE | Full-year 2026 | N54: SCENARIO RANGE | Full-year 2026
B55: Metric | C55: Budget | D55: Base RF1 | E55: Base vs budget | F55: Management view | H55: Case | I55: Occupancy | J55: Revenue | L55: Contribution | N55: Margin
B56: Occupancy | C56: =Forecast!D10 -> 0.69243836 | D56: =Forecast!E10 -> 0.67172603 | E56: =Forecast!F10*100 -> -2.0712329 | F56: Partial recovery | H56: Budget | I56: =Forecast!D10 -> 0.69243836 | J56: =Forecast!D12 -> 4044921.6 | L56: =Forecast!D16 -> 1279795.4 | N56: =Forecast!D17 -> 0.31639561
B57: Room revenue | C57: =Forecast!D12 -> 4044921.6 | D57: =Forecast!E12 -> 3903659.4 | E57: =Forecast!F12 -> -141262.21 | F57: H1 gap persists | H57: Base | I57: =Forecast!E10 -> 0.67172603 | J57: =Forecast!E12 -> 3903659.4 | L57: =Forecast!E16 -> 1137547.2 | N57: =Forecast!E17 -> 0.29140534
B58: Property contribution | C58: =Forecast!D16 -> 1279795.4 | D58: =Forecast!E16 -> 1137547.2 | E58: =Forecast!F16 -> -142248.24 | F58: Below approved plan | H58: Upside | I58: =Forecast!G10 -> 0.68082192 | J58: =Forecast!G12 -> 3974207.9 | L58: =Forecast!G16 -> 1198074 | N58: =Forecast!G17 -> 0.30146233
B59: Contribution margin | C59: =Forecast!D17 -> 0.31639561 | D59: =Forecast!E17 -> 0.29140534 | E59: =Forecast!F17*100 -> -2.4990268 | F59: Margin remains compressed | H59: Downside | I59: =Forecast!I10 -> 0.65531507 | J59: =Forecast!I12 -> 3777975 | L59: =Forecast!I16 -> 1031710.5 | N59: =Forecast!I17 -> 0.27308557
B61: MONTHLY OCCUPANCY | Actual / forecast boundary is June–July | C61: MONTHLY OCCUPANCY | Actual / forecast boundary is June–July | D61: MONTHLY OCCUPANCY | Actual / forecast boundary is June–July | E61: MONTHLY OCCUPANCY | Actual / forecast boundary is June–July | F61: MONTHLY OCCUPANCY | Actual / forecast boundary is June–July | G61: MONTHLY OCCUPANCY | Actual / forecast boundary is June–July | H61: FULL-YEAR CONTRIBUTION COMPARISON ($M) | I61: FULL-YEAR CONTRIBUTION COMPARISON ($M) | J61: FULL-YEAR CONTRIBUTION COMPARISON ($M) | K61: FULL-YEAR CONTRIBUTION COMPARISON ($M) | L61: FULL-YEAR CONTRIBUTION COMPARISON ($M) | M61: FULL-YEAR CONTRIBUTION COMPARISON ($M) | N61: FULL-YEAR CONTRIBUTION COMPARISON ($M)
B78: OUTLOOK & MANAGEMENT IMPLICATIONS | C78: OUTLOOK & MANAGEMENT IMPLICATIONS | D78: OUTLOOK & MANAGEMENT IMPLICATIONS | E78: OUTLOOK & MANAGEMENT IMPLICATIONS | F78: OUTLOOK & MANAGEMENT IMPLICATIONS | G78: OUTLOOK & MANAGEMENT IMPLICATIONS | H78: OUTLOOK & MANAGEMENT IMPLICATIONS | I78: RISKS & OPPORTUNITIES | J78: RISKS & OPPORTUNITIES | K78: RISKS & OPPORTUNITIES | L78: RISKS & OPPORTUNITIES | M78: RISKS & OPPORTUNITIES | N78: RISKS & OPPORTUNITIES
B79: Base recovers from the first-half low point but does not regain the approved full-year plan. Even Upside remains below approved contribution, so the immediate goal is disciplined recovery rather than plan catch-up by assumption. | C79: Base recovers from the first-half low point but does not regain the approved full-year plan. Even Upside remains below approved contribution, so the immediate goal is disciplined recovery rather than plan catch-up by assumption. | D79: Base recovers from the first-half low point but does not regain the approved full-year plan. Even Upside remains below approved contribution, so the immediate goal is disciplined recovery rather than plan catch-up by assumption. | E79: Base recovers from the first-half low point but does not regain the approved full-year plan. Even Upside remains below approved contribution, so the immediate goal is disciplined recovery rather than plan catch-up by assumption. | F79: Base recovers from the first-half low point but does not regain the approved full-year plan. Even Upside remains below approved contribution, so the immediate goal is disciplined recovery rather than plan catch-up by assumption. | G79: Base recovers from the first-half low point but does not regain the approved full-year plan. Even Upside remains below approved contribution, so the immediate goal is disciplined recovery rather than plan catch-up by assumption. | H79: Base recovers from the first-half low point but does not regain the approved full-year plan. Even Upside remains below approved contribution, so the immediate goal is disciplined recovery rather than plan catch-up by assumption. | I79: Risk — Retail/leisure recovery remains the largest uncertainty. A slower H2 pickup would pressure both room revenue and flow-through. | J79: Risk — Retail/leisure recovery remains the largest uncertainty. A slower H2 pickup would pressure both room revenue and flow-through. | K79: Risk — Retail/leisure recovery remains the largest uncertainty. A slower H2 pickup would pressure both room revenue and flow-through. | L79: Risk — Retail/leisure recovery remains the largest uncertainty. A slower H2 pickup would pressure both room revenue and flow-through. | M79: Risk — Retail/leisure recovery remains the largest uncertainty. A slower H2 pickup would pressure both room revenue and flow-through. | N79: Risk — Retail/leisure recovery remains the largest uncertainty. A slower H2 pickup would pressure both room revenue and flow-through.
B80: Base recovers from the first-half low point but does not regain the approved full-year plan. Even Upside remains below approved contribution, so the immediate goal is disciplined recovery rather than plan catch-up by assumption. | C80: Base recovers from the first-half low point but does not regain the approved full-year plan. Even Upside remains below approved contribution, so the immediate goal is disciplined recovery rather than plan catch-up by assumption. | D80: Base recovers from the first-half low point but does not regain the approved full-year plan. Even Upside remains below approved contribution, so the immediate goal is disciplined recovery rather than plan catch-up by assumption. | E80: Base recovers from the first-half low point but does not regain the approved full-year plan. Even Upside remains below approved contribution, so the immediate goal is disciplined recovery rather than plan catch-up by assumption. | F80: Base recovers from the first-half low point but does not regain the approved full-year plan. Even Upside remains below approved contribution, so the immediate goal is disciplined recovery rather than plan catch-up by assumption. | G80: Base recovers from the first-half low point but does not regain the approved full-year plan. Even Upside remains below approved contribution, so the immediate goal is disciplined recovery rather than plan catch-up by assumption. | H80: Base recovers from the first-half low point but does not regain the approved full-year plan. Even Upside remains below approved contribution, so the immediate goal is disciplined recovery rather than plan catch-up by assumption. | I80: Risk — Retail/leisure recovery remains the largest uncertainty. A slower H2 pickup would pressure both room revenue and flow-through. | J80: Risk — Retail/leisure recovery remains the largest uncertainty. A slower H2 pickup would pressure both room revenue and flow-through. | K80: Risk — Retail/leisure recovery remains the largest uncertainty. A slower H2 pickup would pressure both room revenue and flow-through. | L80: Risk — Retail/leisure recovery remains the largest uncertainty. A slower H2 pickup would pressure both room revenue and flow-through. | M80: Risk — Retail/leisure recovery remains the largest uncertainty. A slower H2 pickup would pressure both room revenue and flow-through. | N80: Risk — Retail/leisure recovery remains the largest uncertainty. A slower H2 pickup would pressure both room revenue and flow-through.
B81: Base recovers from the first-half low point but does not regain the approved full-year plan. Even Upside remains below approved contribution, so the immediate goal is disciplined recovery rather than plan catch-up by assumption. | C81: Base recovers from the first-half low point but does not regain the approved full-year plan. Even Upside remains below approved contribution, so the immediate goal is disciplined recovery rather than plan catch-up by assumption. | D81: Base recovers from the first-half low point but does not regain the approved full-year plan. Even Upside remains below approved contribution, so the immediate goal is disciplined recovery rather than plan catch-up by assumption. | E81: Base recovers from the first-half low point but does not regain the approved full-year plan. Even Upside remains below approved contribution, so the immediate goal is disciplined recovery rather than plan catch-up by assumption. | F81: Base recovers from the first-half low point but does not regain the approved full-year plan. Even Upside remains below approved contribution, so the immediate goal is disciplined recovery rather than plan catch-up by assumption. | G81: Base recovers from the first-half low point but does not regain the approved full-year plan. Even Upside remains below approved contribution, so the immediate goal is disciplined recovery rather than plan catch-up by assumption. | H81: Base recovers from the first-half low point but does not regain the approved full-year plan. Even Upside remains below approved contribution, so the immediate goal is disciplined recovery rather than plan catch-up by assumption. | I81: Risk — Retail/leisure recovery remains the largest uncertainty. A slower H2 pickup would pressure both room revenue and flow-through. | J81: Risk — Retail/leisure recovery remains the largest uncertainty. A slower H2 pickup would pressure both room revenue and flow-through. | K81: Risk — Retail/leisure recovery remains the largest uncertainty. A slower H2 pickup would pressure both room revenue and flow-through. | L81: Risk — Retail/leisure recovery remains the largest uncertainty. A slower H2 pickup would pressure both room revenue and flow-through. | M81: Risk — Retail/leisure recovery remains the largest uncertainty. A slower H2 pickup would pressure both room revenue and flow-through. | N81: Risk — Retail/leisure recovery remains the largest uncertainty. A slower H2 pickup would pressure both room revenue and flow-through.
B82: The range is asymmetric: persistent demand weakness and slower housekeeping normalization create more downside than the incremental benefit available in Upside. Scenario differences remain limited to visible operating drivers. | C82: The range is asymmetric: persistent demand weakness and slower housekeeping normalization create more downside than the incremental benefit available in Upside. Scenario differences remain limited to visible operating drivers. | D82: The range is asymmetric: persistent demand weakness and slower housekeeping normalization create more downside than the incremental benefit available in Upside. Scenario differences remain limited to visible operating drivers. | E82: The range is asymmetric: persistent demand weakness and slower housekeeping normalization create more downside than the incremental benefit available in Upside. Scenario differences remain limited to visible operating drivers. | F82: The range is asymmetric: persistent demand weakness and slower housekeeping normalization create more downside than the incremental benefit available in Upside. Scenario differences remain limited to visible operating drivers. | G82: The range is asymmetric: persistent demand weakness and slower housekeeping normalization create more downside than the incremental benefit available in Upside. Scenario differences remain limited to visible operating drivers. | H82: The range is asymmetric: persistent demand weakness and slower housekeeping normalization create more downside than the incremental benefit available in Upside. Scenario differences remain limited to visible operating drivers. | I82: Risk — Housekeeping productivity may normalize more slowly while the higher wage remains structural, increasing variable labor cost. | J82: Risk — Housekeeping productivity may normalize more slowly while the higher wage remains structural, increasing variable labor cost. | K82: Risk — Housekeeping productivity may normalize more slowly while the higher wage remains structural, increasing variable labor cost. | L82: Risk — Housekeeping productivity may normalize more slowly while the higher wage remains structural, increasing variable labor cost. | M82: Risk — Housekeeping productivity may normalize more slowly while the higher wage remains structural, increasing variable labor cost. | N82: Risk — Housekeeping productivity may normalize more slowly while the higher wage remains structural, increasing variable labor cost.
B83: The range is asymmetric: persistent demand weakness and slower housekeeping normalization create more downside than the incremental benefit available in Upside. Scenario differences remain limited to visible operating drivers. | C83: The range is asymmetric: persistent demand weakness and slower housekeeping normalization create more downside than the incremental benefit available in Upside. Scenario differences remain limited to visible operating drivers. | D83: The range is asymmetric: persistent demand weakness and slower housekeeping normalization create more downside than the incremental benefit available in Upside. Scenario differences remain limited to visible operating drivers. | E83: The range is asymmetric: persistent demand weakness and slower housekeeping normalization create more downside than the incremental benefit available in Upside. Scenario differences remain limited to visible operating drivers. | F83: The range is asymmetric: persistent demand weakness and slower housekeeping normalization create more downside than the incremental benefit available in Upside. Scenario differences remain limited to visible operating drivers. | G83: The range is asymmetric: persistent demand weakness and slower housekeeping normalization create more downside than the incremental benefit available in Upside. Scenario differences remain limited to visible operating drivers. | H83: The range is asymmetric: persistent demand weakness and slower housekeeping normalization create more downside than the incremental benefit available in Upside. Scenario differences remain limited to visible operating drivers. | I83: Risk — Housekeeping productivity may normalize more slowly while the higher wage remains structural, increasing variable labor cost. | J83: Risk — Housekeeping productivity may normalize more slowly while the higher wage remains structural, increasing variable labor cost. | K83: Risk — Housekeeping productivity may normalize more slowly while the higher wage remains structural, increasing variable labor cost. | L83: Risk — Housekeeping productivity may normalize more slowly while the higher wage remains structural, increasing variable labor cost. | M83: Risk — Housekeeping productivity may normalize more slowly while the higher wage remains structural, increasing variable labor cost. | N83: Risk — Housekeeping productivity may normalize more slowly while the higher wage remains structural, increasing variable labor cost.
B84: The range is asymmetric: persistent demand weakness and slower housekeeping normalization create more downside than the incremental benefit available in Upside. Scenario differences remain limited to visible operating drivers. | C84: The range is asymmetric: persistent demand weakness and slower housekeeping normalization create more downside than the incremental benefit available in Upside. Scenario differences remain limited to visible operating drivers. | D84: The range is asymmetric: persistent demand weakness and slower housekeeping normalization create more downside than the incremental benefit available in Upside. Scenario differences remain limited to visible operating drivers. | E84: The range is asymmetric: persistent demand weakness and slower housekeeping normalization create more downside than the incremental benefit available in Upside. Scenario differences remain limited to visible operating drivers. | F84: The range is asymmetric: persistent demand weakness and slower housekeeping normalization create more downside than the incremental benefit available in Upside. Scenario differences remain limited to visible operating drivers. | G84: The range is asymmetric: persistent demand weakness and slower housekeeping normalization create more downside than the incremental benefit available in Upside. Scenario differences remain limited to visible operating drivers. | H84: The range is asymmetric: persistent demand weakness and slower housekeeping normalization create more downside than the incremental benefit available in Upside. Scenario differences remain limited to visible operating drivers. | I84: Risk — Housekeeping productivity may normalize more slowly while the higher wage remains structural, increasing variable labor cost. | J84: Risk — Housekeeping productivity may normalize more slowly while the higher wage remains structural, increasing variable labor cost. | K84: Risk — Housekeeping productivity may normalize more slowly while the higher wage remains structural, increasing variable labor cost. | L84: Risk — Housekeeping productivity may normalize more slowly while the higher wage remains structural, increasing variable labor cost. | M84: Risk — Housekeeping productivity may normalize more slowly while the higher wage remains structural, increasing variable labor cost. | N84: Risk — Housekeeping productivity may normalize more slowly while the higher wage remains structural, increasing variable labor cost.
B85: Forecast accuracy cannot yet be evaluated because no later actuals exist. RF1 should be judged as a transparent decision baseline and refreshed only when new evidence becomes available. | C85: Forecast accuracy cannot yet be evaluated because no later actuals exist. RF1 should be judged as a transparent decision baseline and refreshed only when new evidence becomes available. | D85: Forecast accuracy cannot yet be evaluated because no later actuals exist. RF1 should be judged as a transparent decision baseline and refreshed only when new evidence becomes available. | E85: Forecast accuracy cannot yet be evaluated because no later actuals exist. RF1 should be judged as a transparent decision baseline and refreshed only when new evidence becomes available. | F85: Forecast accuracy cannot yet be evaluated because no later actuals exist. RF1 should be judged as a transparent decision baseline and refreshed only when new evidence becomes available. | G85: Forecast accuracy cannot yet be evaluated because no later actuals exist. RF1 should be judged as a transparent decision baseline and refreshed only when new evidence becomes available. | H85: Forecast accuracy cannot yet be evaluated because no later actuals exist. RF1 should be judged as a transparent decision baseline and refreshed only when new evidence becomes available. | I85: Opportunity — Corporate support and targeted September marketing can improve occupancy if pickup converts without sacrificing realized ADR. | J85: Opportunity — Corporate support and targeted September marketing can improve occupancy if pickup converts without sacrificing realized ADR. | K85: Opportunity — Corporate support and targeted September marketing can improve occupancy if pickup converts without sacrificing realized ADR. | L85: Opportunity — Corporate support and targeted September marketing can improve occupancy if pickup converts without sacrificing realized ADR. | M85: Opportunity — Corporate support and targeted September marketing can improve occupancy if pickup converts without sacrificing realized ADR. | N85: Opportunity — Corporate support and targeted September marketing can improve occupancy if pickup converts without sacrificing realized ADR.
B86: Forecast accuracy cannot yet be evaluated because no later actuals exist. RF1 should be judged as a transparent decision baseline and refreshed only when new evidence becomes available. | C86: Forecast accuracy cannot yet be evaluated because no later actuals exist. RF1 should be judged as a transparent decision baseline and refreshed only when new evidence becomes available. | D86: Forecast accuracy cannot yet be evaluated because no later actuals exist. RF1 should be judged as a transparent decision baseline and refreshed only when new evidence becomes available. | E86: Forecast accuracy cannot yet be evaluated because no later actuals exist. RF1 should be judged as a transparent decision baseline and refreshed only when new evidence becomes available. | F86: Forecast accuracy cannot yet be evaluated because no later actuals exist. RF1 should be judged as a transparent decision baseline and refreshed only when new evidence becomes available. | G86: Forecast accuracy cannot yet be evaluated because no later actuals exist. RF1 should be judged as a transparent decision baseline and refreshed only when new evidence becomes available. | H86: Forecast accuracy cannot yet be evaluated because no later actuals exist. RF1 should be judged as a transparent decision baseline and refreshed only when new evidence becomes available. | I86: Opportunity — Corporate support and targeted September marketing can improve occupancy if pickup converts without sacrificing realized ADR. | J86: Opportunity — Corporate support and targeted September marketing can improve occupancy if pickup converts without sacrificing realized ADR. | K86: Opportunity — Corporate support and targeted September marketing can improve occupancy if pickup converts without sacrificing realized ADR. | L86: Opportunity — Corporate support and targeted September marketing can improve occupancy if pickup converts without sacrificing realized ADR. | M86: Opportunity — Corporate support and targeted September marketing can improve occupancy if pickup converts without sacrificing realized ADR. | N86: Opportunity — Corporate support and targeted September marketing can improve occupancy if pickup converts without sacrificing realized ADR.
B87: Forecast accuracy cannot yet be evaluated because no later actuals exist. RF1 should be judged as a transparent decision baseline and refreshed only when new evidence becomes available. | C87: Forecast accuracy cannot yet be evaluated because no later actuals exist. RF1 should be judged as a transparent decision baseline and refreshed only when new evidence becomes available. | D87: Forecast accuracy cannot yet be evaluated because no later actuals exist. RF1 should be judged as a transparent decision baseline and refreshed only when new evidence becomes available. | E87: Forecast accuracy cannot yet be evaluated because no later actuals exist. RF1 should be judged as a transparent decision baseline and refreshed only when new evidence becomes available. | F87: Forecast accuracy cannot yet be evaluated because no later actuals exist. RF1 should be judged as a transparent decision baseline and refreshed only when new evidence becomes available. | G87: Forecast accuracy cannot yet be evaluated because no later actuals exist. RF1 should be judged as a transparent decision baseline and refreshed only when new evidence becomes available. | H87: Forecast accuracy cannot yet be evaluated because no later actuals exist. RF1 should be judged as a transparent decision baseline and refreshed only when new evidence becomes available. | I87: Opportunity — Corporate support and targeted September marketing can improve occupancy if pickup converts without sacrificing realized ADR. | J87: Opportunity — Corporate support and targeted September marketing can improve occupancy if pickup converts without sacrificing realized ADR. | K87: Opportunity — Corporate support and targeted September marketing can improve occupancy if pickup converts without sacrificing realized ADR. | L87: Opportunity — Corporate support and targeted September marketing can improve occupancy if pickup converts without sacrificing realized ADR. | M87: Opportunity — Corporate support and targeted September marketing can improve occupancy if pickup converts without sacrificing realized ADR. | N87: Opportunity — Corporate support and targeted September marketing can improve occupancy if pickup converts without sacrificing realized ADR.
B89: NEXT MANAGEMENT ACTIONS | C89: NEXT MANAGEMENT ACTIONS | D89: NEXT MANAGEMENT ACTIONS | E89: NEXT MANAGEMENT ACTIONS | F89: NEXT MANAGEMENT ACTIONS | G89: NEXT MANAGEMENT ACTIONS | H89: NEXT MANAGEMENT ACTIONS | I89: NEXT MANAGEMENT ACTIONS | J89: NEXT MANAGEMENT ACTIONS | K89: NEXT MANAGEMENT ACTIONS | L89: NEXT MANAGEMENT ACTIONS | M89: NEXT MANAGEMENT ACTIONS | N89: NEXT MANAGEMENT ACTIONS
B90: # | C90: Decision / follow-up | J90: Owner | L90: Timing | N90: Evidence expected
B91: 1 | C91: Track occupied room nights by segment against Base, Upside, and Downside; escalate sustained variance. | J91: GM / Commercial | L91: Weekly in H2 | N91: Pickup by segment
B92: 2 | C92: Review housekeeping hours per occupied room and loaded wage against the normalization path. | J92: Operations | L92: Weekly Jul–Sep | N92: Hours, rooms, payroll
B93: 3 | C93: Confirm execution and invoice timing for the deferred marketing activity included in September. | J93: Marketing / Finance | L93: By September close | N93: Completed service and invoice
B94: 4 | C94: Resolve the cause and recurrence risk of the unconfirmed May overhead item before the next RF update. | J94: Finance | L94: Before next RF | N94: Vendor / ledger support
B96: Synthetic portfolio case. Property operating contribution is a non-GAAP management measure defined in the project specification. See Checks before relying on the workbook. | C96: Synthetic portfolio case. Property operating contribution is a non-GAAP management measure defined in the project specification. See Checks before relying on the workbook. | D96: Synthetic portfolio case. Property operating contribution is a non-GAAP management measure defined in the project specification. See Checks before relying on the workbook. | E96: Synthetic portfolio case. Property operating contribution is a non-GAAP management measure defined in the project specification. See Checks before relying on the workbook. | F96: Synthetic portfolio case. Property operating contribution is a non-GAAP management measure defined in the project specification. See Checks before relying on the workbook. | G96: Synthetic portfolio case. Property operating contribution is a non-GAAP management measure defined in the project specification. See Checks before relying on the workbook. | H96: Synthetic portfolio case. Property operating contribution is a non-GAAP management measure defined in the project specification. See Checks before relying on the workbook. | I96: Synthetic portfolio case. Property operating contribution is a non-GAAP management measure defined in the project specification. See Checks before relying on the workbook. | J96: Synthetic portfolio case. Property operating contribution is a non-GAAP management measure defined in the project specification. See Checks before relying on the workbook. | K96: Synthetic portfolio case. Property operating contribution is a non-GAAP management measure defined in the project specification. See Checks before relying on the workbook. | L96: Synthetic portfolio case. Property operating contribution is a non-GAAP management measure defined in the project specification. See Checks before relying on the workbook. | M96: Synthetic portfolio case. Property operating contribution is a non-GAAP management measure defined in the project specification. See Checks before relying on the workbook. | N96: Synthetic portfolio case. Property operating contribution is a non-GAAP management measure defined in the project specification. See Checks before relying on the workbook.

Sheet Checks
C2: Portfolio Release v1.0 validation checks
C3: Checks read source, budget, variance, forecast, and review results. No other worksheet depends on this sheet.
C4: Master Portfolio Release status | D4: =IF(AND(COUNTIF(F8:F223,"PASS")=179,COUNTIF(F8:F223,"FAIL")=0),"PASS","FAIL") -> PASS
C7: Source integrity | D7: Measured issues / difference | E7: Tolerance | F7: Status | G7: Basis | J7: Expected budget period | K7: Source occurrence count | L7: Status
C8: Expected source tables are populated | D8: =IF(AND(COUNTA(Data!$C$8:$G$151)>0,COUNTA(Data!$C$158:$G$193)>0,COUNTA(Data!$C$200:$H$217)>0,COUNTA(Data!$C$224:$J$230)>0,COUNTA(Assumptions!$C$8:$R$19)>0),0,1) -> 0 | E8: 0 | F8: =IF(ABS(D8)<=E8,"PASS","FAIL") -> PASS | G8: Five static source ranges | J8: 46023 | K8: =COUNTIFS(Assumptions!$D$8:$D$19,J8) -> 1 | L8: =IF(K8=1,"PASS","FAIL") -> PASS
C9: Approved budget assumption row count | D9: =ABS(COUNTA(Assumptions!$C$8:$C$19)-12) -> 0 | E9: 0 | F9: =IF(ABS(D9)<=E9,"PASS","FAIL") -> PASS | G9: Expected 12 | J9: 46054 | K9: =COUNTIFS(Assumptions!$D$8:$D$19,J9) -> 1 | L9: =IF(K9=1,"PASS","FAIL") -> PASS
C10: Financial actual row count | D10: =ABS(COUNTA(Data!$C$8:$C$151)-144) -> 0 | E10: 0 | F10: =IF(ABS(D10)<=E10,"PASS","FAIL") -> PASS | G10: Expected 144 | J10: 46082 | K10: =COUNTIFS(Assumptions!$D$8:$D$19,J10) -> 1 | L10: =IF(K10=1,"PASS","FAIL") -> PASS
C11: Operating actual row count | D11: =ABS(COUNTA(Data!$C$158:$C$193)-36) -> 0 | E11: 0 | F11: =IF(ABS(D11)<=E11,"PASS","FAIL") -> PASS | G11: Expected 36 | J11: 46113 | K11: =COUNTIFS(Assumptions!$D$8:$D$19,J11) -> 1 | L11: =IF(K11=1,"PASS","FAIL") -> PASS
C12: Labor actual row count | D12: =ABS(COUNTA(Data!$C$200:$C$217)-18) -> 0 | E12: 0 | F12: =IF(ABS(D12)<=E12,"PASS","FAIL") -> PASS | G12: Expected 18 | J12: 46143 | K12: =COUNTIFS(Assumptions!$D$8:$D$19,J12) -> 1 | L12: =IF(K12=1,"PASS","FAIL") -> PASS
C13: Case update row count | D13: =ABS(COUNTA(Data!$C$224:$C$230)-7) -> 0 | E13: 0 | F13: =IF(ABS(D13)<=E13,"PASS","FAIL") -> PASS | G13: Expected 7 | J13: 46174 | K13: =COUNTIFS(Assumptions!$D$8:$D$19,J13) -> 1 | L13: =IF(K13=1,"PASS","FAIL") -> PASS
C14: Required source fields | D14: =IF(AND(Data!C7="case_version",Data!D7="period",Data!E7="account_code",Data!F7="account_name",Data!G7="amount_usd",Data!C157="case_version",Data!D157="period",Data!E157="segment",Data!F157="occupied_room_nights",Data!G157="room_revenue",Data!C199="case_version",Data!D199="period",Data!E199="housekeeping_hours",Data!F199="housekeeping_payroll",Data!G199="fixed_staff_fte",Data!H199="fixed_staff_payroll",Data!C223="update_id",Data!D223="as_of_date",Data!E223="effective_start",Data!F223="effective_end",Data!G223="category",Data!H223="observation",Data!I223="evidence_status",Data!J223="forecast_relevance",Assumptions!C7="case_version",Assumptions!D7="period",Assumptions!E7="rooms_available",Assumptions!F7="total_occupied_room_nights",Assumptions!G7="corporate_share",Assumptions!H7="retail_adr",Assumptions!I7="corporate_adr",Assumptions!J7="housekeeping_hours_per_occupied_room",Assumptions!K7="housekeeping_loaded_wage_per_hour",Assumptions!L7="guest_service_cost_per_occupied_room",Assumptions!M7="distribution_fee_rate",Assumptions!N7="fixed_staff_fte",Assumptions!O7="fixed_staff_loaded_cost_per_fte",Assumptions!P7="rent",Assumptions!Q7="property_overhead",Assumptions!R7="marketing"),0,1) -> 0 | E14: 0 | F14: =IF(ABS(D14)<=E14,"PASS","FAIL") -> PASS | G14: Exact required headers | J14: 46204 | K14: =COUNTIFS(Assumptions!$D$8:$D$19,J14) -> 1 | L14: =IF(K14=1,"PASS","FAIL") -> PASS
C15: Case version | D15: =COUNTIFS(Assumptions!$C$8:$C$19,"<>v1.0")+COUNTIFS(Data!$C$8:$C$151,"<>v1.0")+COUNTIFS(Data!$C$158:$C$193,"<>v1.0")+COUNTIFS(Data!$C$200:$C$217,"<>v1.0") -> 0 | E15: 0 | F15: =IF(ABS(D15)<=E15,"PASS","FAIL") -> PASS | G15: All versioned rows must equal v1.0 | J15: 46235 | K15: =COUNTIFS(Assumptions!$D$8:$D$19,J15) -> 1 | L15: =IF(K15=1,"PASS","FAIL") -> PASS
C16: Missing required source values | D16: =COUNTBLANK(Assumptions!$C$8:$R$19)+COUNTBLANK(Data!$C$8:$G$151)+COUNTBLANK(Data!$C$158:$G$193)+COUNTBLANK(Data!$C$200:$H$217)+COUNTBLANK(Data!$C$224:$J$230) -> 0 | E16: 0 | F16: =IF(ABS(D16)<=E16,"PASS","FAIL") -> PASS | G16: No blanks in frozen source tables | J16: 46266 | K16: =COUNTIFS(Assumptions!$D$8:$D$19,J16) -> 1 | L16: =IF(K16=1,"PASS","FAIL") -> PASS
C17: Twelve unique budget months | D17: =ABS(COUNTIFS($K$8:$K$19,1)-12) -> 0 | E17: 0 | F17: =IF(ABS(D17)<=E17,"PASS","FAIL") -> PASS | G17: Each expected month occurs once | J17: 46296 | K17: =COUNTIFS(Assumptions!$D$8:$D$19,J17) -> 1 | L17: =IF(K17=1,"PASS","FAIL") -> PASS
C18: Budget month span | D18: =IF(AND(MIN(Assumptions!$D$8:$D$19)=DATE(2026,1,1),MAX(Assumptions!$D$8:$D$19)=DATE(2026,12,1)),0,1) -> 0 | E18: 0 | F18: =IF(ABS(D18)<=E18,"PASS","FAIL") -> PASS | G18: January through December 2026 | J18: 46327 | K18: =COUNTIFS(Assumptions!$D$8:$D$19,J18) -> 1 | L18: =IF(K18=1,"PASS","FAIL") -> PASS
C19: Rooms available | D19: =COUNTIFS(Assumptions!$E$8:$E$19,"<>100") -> 0 | E19: 0 | F19: =IF(ABS(D19)<=E19,"PASS","FAIL") -> PASS | G19: 100 rooms each month | J19: 46357 | K19: =COUNTIFS(Assumptions!$D$8:$D$19,J19) -> 1 | L19: =IF(K19=1,"PASS","FAIL") -> PASS
C20: Approved distribution fee rate | D20: =COUNTIFS(Assumptions!$M$8:$M$19,"<>0.04") -> 0 | E20: 0 | F20: =IF(ABS(D20)<=E20,"PASS","FAIL") -> PASS | G20: 4.0% each month
C21: Duplicate budget periods | D21: =COUNTIFS($K$8:$K$19,">1") -> 0 | E21: 0 | F21: =IF(ABS(D21)<=E21,"PASS","FAIL") -> PASS | G21: No expected month may occur more than once
C22: Missing budget periods | D22: =COUNTIFS($K$8:$K$19,0) -> 0 | E22: 0 | F22: =IF(ABS(D22)<=E22,"PASS","FAIL") -> PASS | G22: No expected month may be absent
C24: Operating model | D24: Measured issues / difference | E24: Tolerance | F24: Status | G24: Basis | J24: Month | K24: Retail | L24: Corporate | M24: Labor | N24: Room Revenue | O24: HK Payroll | P24: Guest Services | Q24: Distribution | R24: Fixed Staff | S24: Rent | T24: Overhead | U24: Marketing
C25: Occupied room nights within capacity | D25: =IF(Budget!D11>Budget!D10,1,0)+IF(Budget!E11>Budget!E10,1,0)+IF(Budget!F11>Budget!F10,1,0)+IF(Budget!G11>Budget!G10,1,0)+IF(Budget!H11>Budget!H10,1,0)+IF(Budget!I11>Budget!I10,1,0)+IF(Budget!J11>Budget!J10,1,0)+IF(Budget!K11>Budget!K10,1,0)+IF(Budget!L11>Budget!L10,1,0)+IF(Budget!M11>Budget!M10,1,0)+IF(Budget!N11>Budget!N10,1,0)+IF(Budget!O11>Budget!O10,1,0) -> 0 | E25: 0 | F25: =IF(ABS(D25)<=E25,"PASS","FAIL") -> PASS | G25: Monthly issue count | J25: 46023 | K25: =COUNTIFS(Data!$D$158:$D$193,$J25,Data!$E$158:$E$193,"Retail/Leisure") -> 1 | L25: =COUNTIFS(Data!$D$158:$D$193,$J25,Data!$E$158:$E$193,"Negotiated Corporate") -> 1 | M25: =COUNTIFS(Data!$D$200:$D$217,$J25) -> 1 | N25: =COUNTIFS(Data!$D$8:$D$151,$J25,Data!$F$8:$F$151,"Room Revenue") -> 1 | O25: =COUNTIFS(Data!$D$8:$D$151,$J25,Data!$F$8:$F$151,"Housekeeping Payroll") -> 1 | P25: =COUNTIFS(Data!$D$8:$D$151,$J25,Data!$F$8:$F$151,"Guest Services") -> 1 | Q25: =COUNTIFS(Data!$D$8:$D$151,$J25,Data!$F$8:$F$151,"Distribution and Payment") -> 1 | R25: =COUNTIFS(Data!$D$8:$D$151,$J25,Data!$F$8:$F$151,"Fixed Staff Payroll") -> 1 | S25: =COUNTIFS(Data!$D$8:$D$151,$J25,Data!$F$8:$F$151,"Rent") -> 1 | T25: =COUNTIFS(Data!$D$8:$D$151,$J25,Data!$F$8:$F$151,"Property Overhead") -> 1 | U25: =COUNTIFS(Data!$D$8:$D$151,$J25,Data!$F$8:$F$151,"Marketing") -> 1
C26: Occupancy between 0% and 100% | D26: =COUNTIFS(Budget!$D$12:$O$12,"<0")+COUNTIFS(Budget!$D$12:$O$12,">1") -> 0 | E26: 0 | F26: =IF(ABS(D26)<=E26,"PASS","FAIL") -> PASS | G26: Monthly issue count | J26: 46054 | K26: =COUNTIFS(Data!$D$158:$D$193,$J26,Data!$E$158:$E$193,"Retail/Leisure") -> 1 | L26: =COUNTIFS(Data!$D$158:$D$193,$J26,Data!$E$158:$E$193,"Negotiated Corporate") -> 1 | M26: =COUNTIFS(Data!$D$200:$D$217,$J26) -> 1 | N26: =COUNTIFS(Data!$D$8:$D$151,$J26,Data!$F$8:$F$151,"Room Revenue") -> 1 | O26: =COUNTIFS(Data!$D$8:$D$151,$J26,Data!$F$8:$F$151,"Housekeeping Payroll") -> 1 | P26: =COUNTIFS(Data!$D$8:$D$151,$J26,Data!$F$8:$F$151,"Guest Services") -> 1 | Q26: =COUNTIFS(Data!$D$8:$D$151,$J26,Data!$F$8:$F$151,"Distribution and Payment") -> 1 | R26: =COUNTIFS(Data!$D$8:$D$151,$J26,Data!$F$8:$F$151,"Fixed Staff Payroll") -> 1 | S26: =COUNTIFS(Data!$D$8:$D$151,$J26,Data!$F$8:$F$151,"Rent") -> 1 | T26: =COUNTIFS(Data!$D$8:$D$151,$J26,Data!$F$8:$F$151,"Property Overhead") -> 1 | U26: =COUNTIFS(Data!$D$8:$D$151,$J26,Data!$F$8:$F$151,"Marketing") -> 1
C27: Corporate share between 0% and 100% | D27: =COUNTIFS(Budget!$D$13:$O$13,"<0")+COUNTIFS(Budget!$D$13:$O$13,">1") -> 0 | E27: 0 | F27: =IF(ABS(D27)<=E27,"PASS","FAIL") -> PASS | G27: Monthly issue count | J27: 46082 | K27: =COUNTIFS(Data!$D$158:$D$193,$J27,Data!$E$158:$E$193,"Retail/Leisure") -> 1 | L27: =COUNTIFS(Data!$D$158:$D$193,$J27,Data!$E$158:$E$193,"Negotiated Corporate") -> 1 | M27: =COUNTIFS(Data!$D$200:$D$217,$J27) -> 1 | N27: =COUNTIFS(Data!$D$8:$D$151,$J27,Data!$F$8:$F$151,"Room Revenue") -> 1 | O27: =COUNTIFS(Data!$D$8:$D$151,$J27,Data!$F$8:$F$151,"Housekeeping Payroll") -> 1 | P27: =COUNTIFS(Data!$D$8:$D$151,$J27,Data!$F$8:$F$151,"Guest Services") -> 1 | Q27: =COUNTIFS(Data!$D$8:$D$151,$J27,Data!$F$8:$F$151,"Distribution and Payment") -> 1 | R27: =COUNTIFS(Data!$D$8:$D$151,$J27,Data!$F$8:$F$151,"Fixed Staff Payroll") -> 1 | S27: =COUNTIFS(Data!$D$8:$D$151,$J27,Data!$F$8:$F$151,"Rent") -> 1 | T27: =COUNTIFS(Data!$D$8:$D$151,$J27,Data!$F$8:$F$151,"Property Overhead") -> 1 | U27: =COUNTIFS(Data!$D$8:$D$151,$J27,Data!$F$8:$F$151,"Marketing") -> 1
C28: Segment room nights reconcile | D28: =MAX(ABS(Budget!D14+Budget!D15-Budget!D11),ABS(Budget!E14+Budget!E15-Budget!E11),ABS(Budget!F14+Budget!F15-Budget!F11),ABS(Budget!G14+Budget!G15-Budget!G11),ABS(Budget!H14+Budget!H15-Budget!H11),ABS(Budget!I14+Budget!I15-Budget!I11),ABS(Budget!J14+Budget!J15-Budget!J11),ABS(Budget!K14+Budget!K15-Budget!K11),ABS(Budget!L14+Budget!L15-Budget!L11),ABS(Budget!M14+Budget!M15-Budget!M11),ABS(Budget!N14+Budget!N15-Budget!N11),ABS(Budget!O14+Budget!O15-Budget!O11)) -> 0 | E28: 1e-06 | F28: =IF(ABS(D28)<=E28,"PASS","FAIL") -> PASS | G28: Maximum absolute difference | J28: 46113 | K28: =COUNTIFS(Data!$D$158:$D$193,$J28,Data!$E$158:$E$193,"Retail/Leisure") -> 1 | L28: =COUNTIFS(Data!$D$158:$D$193,$J28,Data!$E$158:$E$193,"Negotiated Corporate") -> 1 | M28: =COUNTIFS(Data!$D$200:$D$217,$J28) -> 1 | N28: =COUNTIFS(Data!$D$8:$D$151,$J28,Data!$F$8:$F$151,"Room Revenue") -> 1 | O28: =COUNTIFS(Data!$D$8:$D$151,$J28,Data!$F$8:$F$151,"Housekeeping Payroll") -> 1 | P28: =COUNTIFS(Data!$D$8:$D$151,$J28,Data!$F$8:$F$151,"Guest Services") -> 1 | Q28: =COUNTIFS(Data!$D$8:$D$151,$J28,Data!$F$8:$F$151,"Distribution and Payment") -> 1 | R28: =COUNTIFS(Data!$D$8:$D$151,$J28,Data!$F$8:$F$151,"Fixed Staff Payroll") -> 1 | S28: =COUNTIFS(Data!$D$8:$D$151,$J28,Data!$F$8:$F$151,"Rent") -> 1 | T28: =COUNTIFS(Data!$D$8:$D$151,$J28,Data!$F$8:$F$151,"Property Overhead") -> 1 | U28: =COUNTIFS(Data!$D$8:$D$151,$J28,Data!$F$8:$F$151,"Marketing") -> 1
C29: No negative room nights | D29: =COUNTIFS(Budget!$D$11:$O$11,"<0")+COUNTIFS(Budget!$D$14:$O$14,"<0")+COUNTIFS(Budget!$D$15:$O$15,"<0") -> 0 | E29: 0 | F29: =IF(ABS(D29)<=E29,"PASS","FAIL") -> PASS | G29: Monthly issue count | J29: 46143 | K29: =COUNTIFS(Data!$D$158:$D$193,$J29,Data!$E$158:$E$193,"Retail/Leisure") -> 1 | L29: =COUNTIFS(Data!$D$158:$D$193,$J29,Data!$E$158:$E$193,"Negotiated Corporate") -> 1 | M29: =COUNTIFS(Data!$D$200:$D$217,$J29) -> 1 | N29: =COUNTIFS(Data!$D$8:$D$151,$J29,Data!$F$8:$F$151,"Room Revenue") -> 1 | O29: =COUNTIFS(Data!$D$8:$D$151,$J29,Data!$F$8:$F$151,"Housekeeping Payroll") -> 1 | P29: =COUNTIFS(Data!$D$8:$D$151,$J29,Data!$F$8:$F$151,"Guest Services") -> 1 | Q29: =COUNTIFS(Data!$D$8:$D$151,$J29,Data!$F$8:$F$151,"Distribution and Payment") -> 1 | R29: =COUNTIFS(Data!$D$8:$D$151,$J29,Data!$F$8:$F$151,"Fixed Staff Payroll") -> 1 | S29: =COUNTIFS(Data!$D$8:$D$151,$J29,Data!$F$8:$F$151,"Rent") -> 1 | T29: =COUNTIFS(Data!$D$8:$D$151,$J29,Data!$F$8:$F$151,"Property Overhead") -> 1 | U29: =COUNTIFS(Data!$D$8:$D$151,$J29,Data!$F$8:$F$151,"Marketing") -> 1
C30: Segment revenue reconciles | D30: =MAX(ABS(Budget!D21+Budget!D22-Budget!D23),ABS(Budget!E21+Budget!E22-Budget!E23),ABS(Budget!F21+Budget!F22-Budget!F23),ABS(Budget!G21+Budget!G22-Budget!G23),ABS(Budget!H21+Budget!H22-Budget!H23),ABS(Budget!I21+Budget!I22-Budget!I23),ABS(Budget!J21+Budget!J22-Budget!J23),ABS(Budget!K21+Budget!K22-Budget!K23),ABS(Budget!L21+Budget!L22-Budget!L23),ABS(Budget!M21+Budget!M22-Budget!M23),ABS(Budget!N21+Budget!N22-Budget!N23),ABS(Budget!O21+Budget!O22-Budget!O23)) -> 0 | E30: 0.01 | F30: =IF(ABS(D30)<=E30,"PASS","FAIL") -> PASS | G30: Maximum absolute difference ($) | J30: 46174 | K30: =COUNTIFS(Data!$D$158:$D$193,$J30,Data!$E$158:$E$193,"Retail/Leisure") -> 1 | L30: =COUNTIFS(Data!$D$158:$D$193,$J30,Data!$E$158:$E$193,"Negotiated Corporate") -> 1 | M30: =COUNTIFS(Data!$D$200:$D$217,$J30) -> 1 | N30: =COUNTIFS(Data!$D$8:$D$151,$J30,Data!$F$8:$F$151,"Room Revenue") -> 1 | O30: =COUNTIFS(Data!$D$8:$D$151,$J30,Data!$F$8:$F$151,"Housekeeping Payroll") -> 1 | P30: =COUNTIFS(Data!$D$8:$D$151,$J30,Data!$F$8:$F$151,"Guest Services") -> 1 | Q30: =COUNTIFS(Data!$D$8:$D$151,$J30,Data!$F$8:$F$151,"Distribution and Payment") -> 1 | R30: =COUNTIFS(Data!$D$8:$D$151,$J30,Data!$F$8:$F$151,"Fixed Staff Payroll") -> 1 | S30: =COUNTIFS(Data!$D$8:$D$151,$J30,Data!$F$8:$F$151,"Rent") -> 1 | T30: =COUNTIFS(Data!$D$8:$D$151,$J30,Data!$F$8:$F$151,"Property Overhead") -> 1 | U30: =COUNTIFS(Data!$D$8:$D$151,$J30,Data!$F$8:$F$151,"Marketing") -> 1
C32: Cost model | D32: Measured issues / difference | E32: Tolerance | F32: Status | G32: Basis
C33: Housekeeping payroll | D33: =MAX(ABS(Budget!D32-Budget!D31*Budget!D30),ABS(Budget!E32-Budget!E31*Budget!E30),ABS(Budget!F32-Budget!F31*Budget!F30),ABS(Budget!G32-Budget!G31*Budget!G30),ABS(Budget!H32-Budget!H31*Budget!H30),ABS(Budget!I32-Budget!I31*Budget!I30),ABS(Budget!J32-Budget!J31*Budget!J30),ABS(Budget!K32-Budget!K31*Budget!K30),ABS(Budget!L32-Budget!L31*Budget!L30),ABS(Budget!M32-Budget!M31*Budget!M30),ABS(Budget!N32-Budget!N31*Budget!N30),ABS(Budget!O32-Budget!O31*Budget!O30)) -> 0 | E33: 0.01 | F33: =IF(ABS(D33)<=E33,"PASS","FAIL") -> PASS | G33: Hours × loaded wage
C34: Guest-service expense | D34: =MAX(ABS(Budget!D34-Budget!D11*Budget!D33),ABS(Budget!E34-Budget!E11*Budget!E33),ABS(Budget!F34-Budget!F11*Budget!F33),ABS(Budget!G34-Budget!G11*Budget!G33),ABS(Budget!H34-Budget!H11*Budget!H33),ABS(Budget!I34-Budget!I11*Budget!I33),ABS(Budget!J34-Budget!J11*Budget!J33),ABS(Budget!K34-Budget!K11*Budget!K33),ABS(Budget!L34-Budget!L11*Budget!L33),ABS(Budget!M34-Budget!M11*Budget!M33),ABS(Budget!N34-Budget!N11*Budget!N33),ABS(Budget!O34-Budget!O11*Budget!O33)) -> 0 | E34: 0.01 | F34: =IF(ABS(D34)<=E34,"PASS","FAIL") -> PASS | G34: Occupied nights × unit cost
C35: Distribution expense | D35: =MAX(ABS(Budget!D36-Budget!D23*Budget!D35),ABS(Budget!E36-Budget!E23*Budget!E35),ABS(Budget!F36-Budget!F23*Budget!F35),ABS(Budget!G36-Budget!G23*Budget!G35),ABS(Budget!H36-Budget!H23*Budget!H35),ABS(Budget!I36-Budget!I23*Budget!I35),ABS(Budget!J36-Budget!J23*Budget!J35),ABS(Budget!K36-Budget!K23*Budget!K35),ABS(Budget!L36-Budget!L23*Budget!L35),ABS(Budget!M36-Budget!M23*Budget!M35),ABS(Budget!N36-Budget!N23*Budget!N35),ABS(Budget!O36-Budget!O23*Budget!O35)) -> 0 | E35: 0.01 | F35: =IF(ABS(D35)<=E35,"PASS","FAIL") -> PASS | G35: Revenue × approved fee rate
C36: Fixed staff payroll | D36: =MAX(ABS(Budget!D42-Budget!D40*Budget!D41),ABS(Budget!E42-Budget!E40*Budget!E41),ABS(Budget!F42-Budget!F40*Budget!F41),ABS(Budget!G42-Budget!G40*Budget!G41),ABS(Budget!H42-Budget!H40*Budget!H41),ABS(Budget!I42-Budget!I40*Budget!I41),ABS(Budget!J42-Budget!J40*Budget!J41),ABS(Budget!K42-Budget!K40*Budget!K41),ABS(Budget!L42-Budget!L40*Budget!L41),ABS(Budget!M42-Budget!M40*Budget!M41),ABS(Budget!N42-Budget!N40*Budget!N41),ABS(Budget!O42-Budget!O40*Budget!O41)) -> 0 | E36: 0.01 | F36: =IF(ABS(D36)<=E36,"PASS","FAIL") -> PASS | G36: FTE × loaded cost per FTE
C37: Total operating costs | D37: =MAX(ABS(Budget!D49-SUM(Budget!D32,Budget!D34,Budget!D36,Budget!D42:'Budget'!D45)),ABS(Budget!E49-SUM(Budget!E32,Budget!E34,Budget!E36,Budget!E42:'Budget'!E45)),ABS(Budget!F49-SUM(Budget!F32,Budget!F34,Budget!F36,Budget!F42:'Budget'!F45)),ABS(Budget!G49-SUM(Budget!G32,Budget!G34,Budget!G36,Budget!G42:'Budget'!G45)),ABS(Budget!H49-SUM(Budget!H32,Budget!H34,Budget!H36,Budget!H42:'Budget'!H45)),ABS(Budget!I49-SUM(Budget!I32,Budget!I34,Budget!I36,Budget!I42:'Budget'!I45)),ABS(Budget!J49-SUM(Budget!J32,Budget!J34,Budget!J36,Budget!J42:'Budget'!J45)),ABS(Budget!K49-SUM(Budget!K32,Budget!K34,Budget!K36,Budget!K42:'Budget'!K45)),ABS(Budget!L49-SUM(Budget!L32,Budget!L34,Budget!L36,Budget!L42:'Budget'!L45)),ABS(Budget!M49-SUM(Budget!M32,Budget!M34,Budget!M36,Budget!M42:'Budget'!M45)),ABS(Budget!N49-SUM(Budget!N32,Budget!N34,Budget!N36,Budget!N42:'Budget'!N45)),ABS(Budget!O49-SUM(Budget!O32,Budget!O34,Budget!O36,Budget!O42:'Budget'!O45))) -> 0 | E37: 0.01 | F37: =IF(ABS(D37)<=E37,"PASS","FAIL") -> PASS | G37: Required cost components
C38: Property operating contribution | D38: =MAX(ABS(Budget!D50-(Budget!D23-Budget!D49)),ABS(Budget!E50-(Budget!E23-Budget!E49)),ABS(Budget!F50-(Budget!F23-Budget!F49)),ABS(Budget!G50-(Budget!G23-Budget!G49)),ABS(Budget!H50-(Budget!H23-Budget!H49)),ABS(Budget!I50-(Budget!I23-Budget!I49)),ABS(Budget!J50-(Budget!J23-Budget!J49)),ABS(Budget!K50-(Budget!K23-Budget!K49)),ABS(Budget!L50-(Budget!L23-Budget!L49)),ABS(Budget!M50-(Budget!M23-Budget!M49)),ABS(Budget!N50-(Budget!N23-Budget!N49)),ABS(Budget!O50-(Budget!O23-Budget!O49))) -> 0 | E38: 0.01 | F38: =IF(ABS(D38)<=E38,"PASS","FAIL") -> PASS | G38: Revenue less total operating costs
C40: Annual aggregation | D40: Measured issues / difference | E40: Tolerance | F40: Status | G40: Basis
C41: Monthly additive lines reconcile to FY2026 | D41: =MAX(ABS(SUM(Budget!D9:O9)-Budget!P9),ABS(SUM(Budget!D10:O10)-Budget!P10),ABS(SUM(Budget!D11:O11)-Budget!P11),ABS(SUM(Budget!D14:O14)-Budget!P14),ABS(SUM(Budget!D15:O15)-Budget!P15),ABS(SUM(Budget!D21:O21)-Budget!P21),ABS(SUM(Budget!D22:O22)-Budget!P22),ABS(SUM(Budget!D23:O23)-Budget!P23),ABS(SUM(Budget!D31:O31)-Budget!P31),ABS(SUM(Budget!D32:O32)-Budget!P32),ABS(SUM(Budget!D34:O34)-Budget!P34),ABS(SUM(Budget!D36:O36)-Budget!P36),ABS(SUM(Budget!D42:O42)-Budget!P42),ABS(SUM(Budget!D43:O43)-Budget!P43),ABS(SUM(Budget!D44:O44)-Budget!P44),ABS(SUM(Budget!D45:O45)-Budget!P45),ABS(SUM(Budget!D49:O49)-Budget!P49),ABS(SUM(Budget!D50:O50)-Budget!P50)) -> 0 | E41: 0.01 | F41: =IF(ABS(D41)<=E41,"PASS","FAIL") -> PASS | G41: Maximum absolute difference
C42: Annual occupancy uses annual totals | D42: =ABS(Budget!P12-Budget!P11/Budget!P10) -> 0 | E42: 1e-07 | F42: =IF(ABS(D42)<=E42,"PASS","FAIL") -> PASS | G42: Annual occupied nights ÷ annual available nights
C43: Annual ADR and RevPAR use annual totals | D43: =MAX(ABS(Budget!P24-Budget!P23/Budget!P11),ABS(Budget!P25-Budget!P23/Budget!P10)) -> 0 | E43: 1e-07 | F43: =IF(ABS(D43)<=E43,"PASS","FAIL") -> PASS | G43: Weighted annual metrics
C44: Annual productivity and unit costs are weighted | D44: =MAX(ABS(Budget!P29-Budget!P31/Budget!P11),ABS(Budget!P30-Budget!P32/Budget!P31),ABS(Budget!P33-Budget!P34/Budget!P11),ABS(Budget!P35-Budget!P36/Budget!P23)) -> 0 | E44: 1e-07 | F44: =IF(ABS(D44)<=E44,"PASS","FAIL") -> PASS | G44: Annual numerators ÷ annual denominators
C45: Annual contribution margin uses annual totals | D45: =ABS(Budget!P51-Budget!P50/Budget!P23) -> 0 | E45: 1e-07 | F45: =IF(ABS(D45)<=E45,"PASS","FAIL") -> PASS | G45: Annual contribution ÷ annual revenue
C47: Workbook integrity | D47: Measured issues / difference | E47: Tolerance | F47: Status | G47: Basis
C48: Required worksheets exist | D48: =IF(AND(Start!$C$2<>"",Data!$C$2<>"",Assumptions!$C$2<>"",Budget!$C$2<>"",Forecast!$C$2<>"",Variance!$C$2<>"",Review!$C$2<>"",Checks!$C$2<>""),0,1) -> 0 | E48: 0 | F48: =IF(ABS(D48)<=E48,"PASS","FAIL") -> PASS | G48: Eight required visible worksheets
C49: Formula errors | D49: 0 | E49: 0 | F49: =IF(ABS(D49)<=E49,"PASS","FAIL") -> PASS | G49: Verified after final recalculation
C50: External workbook links | D50: 0 | E50: 0 | F50: =IF(ABS(D50)<=E50,"PASS","FAIL") -> PASS | G50: Verified by final package audit
C51: Hidden worksheets | D51: 0 | E51: 0 | F51: =IF(ABS(D51)<=E51,"PASS","FAIL") -> PASS | G51: Verified by final package audit
C52: Macros | D52: 0 | E52: 0 | F52: =IF(ABS(D52)<=E52,"PASS","FAIL") -> PASS | G52: Verified by final package audit
C53: Circular iteration | D53: 0 | E53: 0 | F53: =IF(ABS(D53)<=E53,"PASS","FAIL") -> PASS | G53: Verified by final package audit
C54: Volatile formulas | D54: 0 | E54: 0 | F54: =IF(ABS(D54)<=E54,"PASS","FAIL") -> PASS | G54: Verified by final formula audit
C55: Formulas outside Checks referencing Checks | D55: 0 | E55: 0 | F55: =IF(ABS(D55)<=E55,"PASS","FAIL") -> PASS | G55: Verified by final formula audit
C56: Budget references to actuals or later-phase tabs | D56: 0 | E56: 0 | F56: =IF(ABS(D56)<=E56,"PASS","FAIL") -> PASS | G56: Verified by final formula audit
C58: Phase 2 controls retained above. Phase 3 controls follow.
C59: Period and source scope | D59: Measured issues / difference | E59: Tolerance | F59: Status | G59: Basis
C60: Current actual scope is January–June 2026 | D60: =ABS(COUNTIFS(Data!$D$158:$D$193,">="&DATE(2026,1,1),Data!$D$158:$D$193,"<="&DATE(2026,6,1))-12) -> 0 | E60: 0 | F60: =IF(ABS(D60)<=E60,"PASS","FAIL") -> PASS | G60: Twelve segment-month records across six months
C61: Prior-year scope is January–June 2025 | D61: =ABS(COUNTIFS(Data!$D$158:$D$193,">="&DATE(2025,1,1),Data!$D$158:$D$193,"<="&DATE(2025,6,1))-12) -> 0 | E61: 0 | F61: =IF(ABS(D61)<=E61,"PASS","FAIL") -> PASS | G61: Twelve prior-year segment-month records
C62: No July–December 2026 actual is included | D62: =COUNTIFS(Data!$D$158:$D$193,">="&DATE(2026,7,1),Data!$D$158:$D$193,"<="&DATE(2026,12,1))+COUNTIFS(Data!$D$200:$D$217,">="&DATE(2026,7,1),Data!$D$200:$D$217,"<="&DATE(2026,12,1))+COUNTIFS(Data!$D$8:$D$151,">="&DATE(2026,7,1),Data!$D$8:$D$151,"<="&DATE(2026,12,1)) -> 0 | E62: 0 | F62: =IF(ABS(D62)<=E62,"PASS","FAIL") -> PASS | G62: No source actual after June 2026
C63: Required segment-month records are present | D63: =COUNTIFS(K25:L30,0) -> 0 | E63: 0 | F63: =IF(ABS(D63)<=E63,"PASS","FAIL") -> PASS | G63: Each segment occurs once per current month
C64: Required segment-month records are unique | D64: =COUNTIFS(K25:L30,">1") -> 0 | E64: 0 | F64: =IF(ABS(D64)<=E64,"PASS","FAIL") -> PASS | G64: No duplicate current segment-month key
C65: Required financial account-month records are present | D65: =COUNTIFS(N25:U30,0) -> 0 | E65: 0 | F65: =IF(ABS(D65)<=E65,"PASS","FAIL") -> PASS | G65: Each required account occurs once per current month
C66: Required financial account-month records are unique | D66: =COUNTIFS(N25:U30,">1") -> 0 | E66: 0 | F66: =IF(ABS(D66)<=E66,"PASS","FAIL") -> PASS | G66: No duplicate current financial account-month key
C67: Required labor records are present | D67: =COUNTIFS(M25:M30,0) -> 0 | E67: 0 | F67: =IF(ABS(D67)<=E67,"PASS","FAIL") -> PASS | G67: One labor record per current month
C68: Required labor records are unique | D68: =COUNTIFS(M25:M30,">1") -> 0 | E68: 0 | F68: =IF(ABS(D68)<=E68,"PASS","FAIL") -> PASS | G68: No duplicate current labor month
C69: Analysis cutoff is displayed correctly | D69: =ABS(Variance!D9-DATE(2026,7,8)) -> 0 | E69: 0 | F69: =IF(ABS(D69)<=E69,"PASS","FAIL") -> PASS | G69: July 8, 2026
C71: Actual reconstruction | D71: Measured issues / difference | E71: Tolerance | F71: Status | G71: Basis
C72: Segment occupied nights sum to total occupied nights | D72: =MAX(ABS(Variance!D95-Variance!D97-Variance!D98),ABS(Variance!E95-Variance!E97-Variance!E98),ABS(Variance!F95-Variance!F97-Variance!F98),ABS(Variance!G95-Variance!G97-Variance!G98),ABS(Variance!H95-Variance!H97-Variance!H98),ABS(Variance!I95-Variance!I97-Variance!I98)) -> 0 | E72: =0.000001 -> 1e-06 | F72: =IF(ABS(D72)<=E72,"PASS","FAIL") -> PASS | G72: Recorded segment nights only
C73: Segment revenue sums to total room revenue | D73: =MAX(ABS(Variance!D106-Variance!D104-Variance!D105),ABS(Variance!E106-Variance!E104-Variance!E105),ABS(Variance!F106-Variance!F104-Variance!F105),ABS(Variance!G106-Variance!G104-Variance!G105),ABS(Variance!H106-Variance!H104-Variance!H105),ABS(Variance!I106-Variance!I104-Variance!I105)) -> 0 | E73: 0.01 | F73: =IF(ABS(D73)<=E73,"PASS","FAIL") -> PASS | G73: Recorded segment revenue only
C74: Operating revenue reconciles to financial actuals | D74: =MAX(ABS(Variance!D106-SUMIFS(Data!$G$8:$G$151,Data!$D$8:$D$151,Variance!D$92,Data!$F$8:$F$151,"Room Revenue")),ABS(Variance!E106-SUMIFS(Data!$G$8:$G$151,Data!$D$8:$D$151,Variance!E$92,Data!$F$8:$F$151,"Room Revenue")),ABS(Variance!F106-SUMIFS(Data!$G$8:$G$151,Data!$D$8:$D$151,Variance!F$92,Data!$F$8:$F$151,"Room Revenue")),ABS(Variance!G106-SUMIFS(Data!$G$8:$G$151,Data!$D$8:$D$151,Variance!G$92,Data!$F$8:$F$151,"Room Revenue")),ABS(Variance!H106-SUMIFS(Data!$G$8:$G$151,Data!$D$8:$D$151,Variance!H$92,Data!$F$8:$F$151,"Room Revenue")),ABS(Variance!I106-SUMIFS(Data!$G$8:$G$151,Data!$D$8:$D$151,Variance!I$92,Data!$F$8:$F$151,"Room Revenue"))) -> 0 | E74: 0.01 | F74: =IF(ABS(D74)<=E74,"PASS","FAIL") -> PASS | G74: Operating source versus financial source
C75: Housekeeping payroll reconciles labor and financial sources | D75: =MAX(ABS(Variance!D110-SUMIFS(Data!$G$8:$G$151,Data!$D$8:$D$151,Variance!D$92,Data!$F$8:$F$151,"Housekeeping Payroll")),ABS(Variance!E110-SUMIFS(Data!$G$8:$G$151,Data!$D$8:$D$151,Variance!E$92,Data!$F$8:$F$151,"Housekeeping Payroll")),ABS(Variance!F110-SUMIFS(Data!$G$8:$G$151,Data!$D$8:$D$151,Variance!F$92,Data!$F$8:$F$151,"Housekeeping Payroll")),ABS(Variance!G110-SUMIFS(Data!$G$8:$G$151,Data!$D$8:$D$151,Variance!G$92,Data!$F$8:$F$151,"Housekeeping Payroll")),ABS(Variance!H110-SUMIFS(Data!$G$8:$G$151,Data!$D$8:$D$151,Variance!H$92,Data!$F$8:$F$151,"Housekeeping Payroll")),ABS(Variance!I110-SUMIFS(Data!$G$8:$G$151,Data!$D$8:$D$151,Variance!I$92,Data!$F$8:$F$151,"Housekeeping Payroll"))) -> 0 | E75: 0.01 | F75: =IF(ABS(D75)<=E75,"PASS","FAIL") -> PASS | G75: Labor source versus financial source
C76: Fixed-staff payroll reconciles labor and financial sources | D76: =MAX(ABS(Variance!D117-SUMIFS(Data!$G$8:$G$151,Data!$D$8:$D$151,Variance!D$92,Data!$F$8:$F$151,"Fixed Staff Payroll")),ABS(Variance!E117-SUMIFS(Data!$G$8:$G$151,Data!$D$8:$D$151,Variance!E$92,Data!$F$8:$F$151,"Fixed Staff Payroll")),ABS(Variance!F117-SUMIFS(Data!$G$8:$G$151,Data!$D$8:$D$151,Variance!F$92,Data!$F$8:$F$151,"Fixed Staff Payroll")),ABS(Variance!G117-SUMIFS(Data!$G$8:$G$151,Data!$D$8:$D$151,Variance!G$92,Data!$F$8:$F$151,"Fixed Staff Payroll")),ABS(Variance!H117-SUMIFS(Data!$G$8:$G$151,Data!$D$8:$D$151,Variance!H$92,Data!$F$8:$F$151,"Fixed Staff Payroll")),ABS(Variance!I117-SUMIFS(Data!$G$8:$G$151,Data!$D$8:$D$151,Variance!I$92,Data!$F$8:$F$151,"Fixed Staff Payroll"))) -> 0 | E76: 0.01 | F76: =IF(ABS(D76)<=E76,"PASS","FAIL") -> PASS | G76: Labor source versus financial source
C77: Distribution expense equals 4% of actual revenue | D77: =MAX(ABS(Variance!D114-4%*Variance!D106),ABS(Variance!E114-4%*Variance!E106),ABS(Variance!F114-4%*Variance!F106),ABS(Variance!G114-4%*Variance!G106),ABS(Variance!H114-4%*Variance!H106),ABS(Variance!I114-4%*Variance!I106)) -> 1.8189894e-12 | E77: 0.01 | F77: =IF(ABS(D77)<=E77,"PASS","FAIL") -> PASS | G77: Recorded distribution expense versus fixed policy
C78: Actual operating costs reconcile to components | D78: =MAX(ABS(Variance!D121-SUM(Variance!D110,Variance!D112,Variance!D114,Variance!D117,Variance!D118,Variance!D119,Variance!D120)),ABS(Variance!E121-SUM(Variance!E110,Variance!E112,Variance!E114,Variance!E117,Variance!E118,Variance!E119,Variance!E120)),ABS(Variance!F121-SUM(Variance!F110,Variance!F112,Variance!F114,Variance!F117,Variance!F118,Variance!F119,Variance!F120)),ABS(Variance!G121-SUM(Variance!G110,Variance!G112,Variance!G114,Variance!G117,Variance!G118,Variance!G119,Variance!G120)),ABS(Variance!H121-SUM(Variance!H110,Variance!H112,Variance!H114,Variance!H117,Variance!H118,Variance!H119,Variance!H120)),ABS(Variance!I121-SUM(Variance!I110,Variance!I112,Variance!I114,Variance!I117,Variance!I118,Variance!I119,Variance!I120))) -> 0 | E78: 0.01 | F78: =IF(ABS(D78)<=E78,"PASS","FAIL") -> PASS | G78: All seven recorded cost lines
C79: Actual contribution equals revenue less costs | D79: =MAX(ABS(Variance!D122-(Variance!D106-Variance!D121)),ABS(Variance!E122-(Variance!E106-Variance!E121)),ABS(Variance!F122-(Variance!F106-Variance!F121)),ABS(Variance!G122-(Variance!G106-Variance!G121)),ABS(Variance!H122-(Variance!H106-Variance!H121)),ABS(Variance!I122-(Variance!I106-Variance!I121))) -> 0 | E79: 0.01 | F79: =IF(ABS(D79)<=E79,"PASS","FAIL") -> PASS | G79: Recorded revenue less actual costs
C80: Actual derived KPIs use recorded numerators and denominators | D80: =MAX(ABS(Variance!J96-Variance!J95/Variance!J94),ABS(Variance!J102-Variance!J106/Variance!J95),ABS(Variance!J109-Variance!J110/Variance!J107),ABS(Variance!J111-Variance!J112/Variance!J95)) -> 0 | E80: =0.000001 -> 1e-06 | F80: =IF(ABS(D80)<=E80,"PASS","FAIL") -> PASS | G80: YTD ratios recomputed from recorded facts
C82: Budget comparison | D82: Measured issues / difference | E82: Tolerance | F82: Status | G82: Basis
C83: January–June budget values tie to Budget | D83: =MAX(ABS(Variance!D62-Budget!D11),ABS(Variance!D73-Budget!D23),ABS(Variance!D77-Budget!D32),ABS(Variance!D79-Budget!D34),ABS(Variance!D81-Budget!D36),ABS(Variance!D84-Budget!D42),ABS(Variance!D85-Budget!D43),ABS(Variance!D86-Budget!D44),ABS(Variance!D87-Budget!D45),ABS(Variance!D89-Budget!D50),ABS(Variance!E62-Budget!E11),ABS(Variance!E73-Budget!E23),ABS(Variance!E77-Budget!E32),ABS(Variance!E79-Budget!E34),ABS(Variance!E81-Budget!E36),ABS(Variance!E84-Budget!E42),ABS(Variance!E85-Budget!E43),ABS(Variance!E86-Budget!E44),ABS(Variance!E87-Budget!E45),ABS(Variance!E89-Budget!E50),ABS(Variance!F62-Budget!F11),ABS(Variance!F73-Budget!F23),ABS(Variance!F77-Budget!F32),ABS(Variance!F79-Budget!F34),ABS(Variance!F81-Budget!F36),ABS(Variance!F84-Budget!F42),ABS(Variance!F85-Budget!F43),ABS(Variance!F86-Budget!F44),ABS(Variance!F87-Budget!F45),ABS(Variance!F89-Budget!F50),ABS(Variance!G62-Budget!G11),ABS(Variance!G73-Budget!G23),ABS(Variance!G77-Budget!G32),ABS(Variance!G79-Budget!G34),ABS(Variance!G81-Budget!G36),ABS(Variance!G84-Budget!G42),ABS(Variance!G85-Budget!G43),ABS(Variance!G86-Budget!G44),ABS(Variance!G87-Budget!G45),ABS(Variance!G89-Budget!G50),ABS(Variance!H62-Budget!H11),ABS(Variance!H73-Budget!H23),ABS(Variance!H77-Budget!H32),ABS(Variance!H79-Budget!H34),ABS(Variance!H81-Budget!H36),ABS(Variance!H84-Budget!H42),ABS(Variance!H85-Budget!H43),ABS(Variance!H86-Budget!H44),ABS(Variance!H87-Budget!H45),ABS(Variance!H89-Budget!H50),ABS(Variance!I62-Budget!I11),ABS(Variance!I73-Budget!I23),ABS(Variance!I77-Budget!I32),ABS(Variance!I79-Budget!I34),ABS(Variance!I81-Budget!I36),ABS(Variance!I84-Budget!I42),ABS(Variance!I85-Budget!I43),ABS(Variance!I86-Budget!I44),ABS(Variance!I87-Budget!I45),ABS(Variance!I89-Budget!I50)) -> 0 | E83: 0.01 | F83: =IF(ABS(D83)<=E83,"PASS","FAIL") -> PASS | G83: Matched monthly links to approved Budget
C84: No approved-budget figure is independently hardcoded on Variance | D84: 0 | E84: 0 | F84: =IF(ABS(D84)<=E84,"PASS","FAIL") -> PASS | G84: Verified by final formula audit
C85: Actual-minus-budget amounts calculate correctly | D85: =MAX(ABS(Variance!J139-(Variance!J106-Variance!J73)),ABS(Variance!J155-(Variance!J122-Variance!J89)),ABS(Variance!J156*0+Variance!J154-(Variance!J121-Variance!J88))) -> 0 | E85: 0.01 | F85: =IF(ABS(D85)<=E85,"PASS","FAIL") -> PASS | G85: Revenue, contribution, and cost examples
C86: Percentage-point calculations are correct | D86: =MAX(ABS(Variance!F27-(Variance!D27-Variance!E27)*100),ABS(Variance!F30-(Variance!D30-Variance!E30)*100),ABS(Variance!F48-(Variance!D48-Variance!E48)*100)) -> 0 | E86: =0.000001 -> 1e-06 | F86: =IF(ABS(D86)<=E86,"PASS","FAIL") -> PASS | G86: Occupancy, corporate share, and contribution margin
C87: YTD additive totals reconcile to monthly amounts | D87: =MAX(ABS(Variance!J106-SUM(Variance!D106:I106)),ABS(Variance!J121-SUM(Variance!D121:I121)),ABS(Variance!J73-SUM(Variance!D73:I73)),ABS(Variance!J88-SUM(Variance!D88:I88))) -> 0 | E87: 0.01 | F87: =IF(ABS(D87)<=E87,"PASS","FAIL") -> PASS | G87: Actual and budget YTD amounts
C88: YTD ratios use aggregate totals | D88: =MAX(ABS(Variance!J96-Variance!J95/Variance!J94),ABS(Variance!J99-Variance!J98/Variance!J95),ABS(Variance!J123-Variance!J122/Variance!J106),ABS(Variance!J63-Variance!J62/Variance!J61)) -> 0 | E88: =0.000001 -> 1e-06 | F88: =IF(ABS(D88)<=E88,"PASS","FAIL") -> PASS | G88: Aggregate numerators and denominators
C90: Bridge integrity | D90: Measured issues / difference | E90: Tolerance | F90: Status | G90: Basis
C91: Monthly revenue bridge residuals equal zero | D91: =MAX(ABS(Variance!D174),ABS(Variance!E174),ABS(Variance!F174),ABS(Variance!G174),ABS(Variance!H174),ABS(Variance!I174)) -> 3.5470293e-11 | E91: 0.01 | F91: =IF(ABS(D91)<=E91,"PASS","FAIL") -> PASS | G91: Monthly volume, mix, and rate effects
C92: YTD revenue bridge residual equals zero | D92: =ABS(Variance!J174) -> 1.3096724e-10 | E92: 0.01 | F92: =IF(ABS(D92)<=E92,"PASS","FAIL") -> PASS | G92: Sum of monthly effects
C93: Monthly housekeeping bridge residuals equal zero | D93: =MAX(ABS(Variance!D194),ABS(Variance!E194),ABS(Variance!F194),ABS(Variance!G194),ABS(Variance!H194),ABS(Variance!I194)) -> 1.5347723e-12 | E93: 0.01 | F93: =IF(ABS(D93)<=E93,"PASS","FAIL") -> PASS | G93: Monthly volume, efficiency, and wage effects
C94: YTD housekeeping bridge residual equals zero | D94: =ABS(Variance!J194) -> 0 | E94: 0.01 | F94: =IF(ABS(D94)<=E94,"PASS","FAIL") -> PASS | G94: Sum of monthly effects
C95: Monthly guest-service bridge residuals equal zero | D95: =MAX(ABS(Variance!D209),ABS(Variance!E209),ABS(Variance!F209),ABS(Variance!G209),ABS(Variance!H209),ABS(Variance!I209)) -> 2.8421709e-12 | E95: 0.01 | F95: =IF(ABS(D95)<=E95,"PASS","FAIL") -> PASS | G95: Monthly volume and unit-cost effects
C96: YTD guest-service bridge residual equals zero | D96: =ABS(Variance!J209) -> 3.6379788e-11 | E96: 0.01 | F96: =IF(ABS(D96)<=E96,"PASS","FAIL") -> PASS | G96: Sum of monthly effects
C97: Monthly fixed-staff bridge residuals equal zero | D97: =MAX(ABS(Variance!D224),ABS(Variance!E224),ABS(Variance!F224),ABS(Variance!G224),ABS(Variance!H224),ABS(Variance!I224)) -> 0 | E97: 0.01 | F97: =IF(ABS(D97)<=E97,"PASS","FAIL") -> PASS | G97: Monthly FTE and rate effects
C98: YTD fixed-staff bridge residual equals zero | D98: =ABS(Variance!J224) -> 0 | E98: 0.01 | F98: =IF(ABS(D98)<=E98,"PASS","FAIL") -> PASS | G98: Sum of monthly effects
C99: Distribution-fee linkage reconciles | D99: =MAX(ABS(Variance!D235),ABS(Variance!E235),ABS(Variance!F235),ABS(Variance!G235),ABS(Variance!H235),ABS(Variance!I235),ABS(Variance!J235)) -> 1.2505552e-12 | E99: 0.01 | F99: =IF(ABS(D99)<=E99,"PASS","FAIL") -> PASS | G99: Distribution cost change equals 4% of revenue variance
C100: Contribution bridge reconciles to actual contribution | D100: =ABS(Variance!D257) -> 0 | E100: 0.01 | F100: =IF(ABS(D100)<=E100,"PASS","FAIL") -> PASS | G100: Budget contribution plus all driver impacts
C101: Cost-change and contribution-impact signs are inverted | D101: =MAX(ABS(Variance!D244+Variance!J189),ABS(Variance!D245+Variance!J190),ABS(Variance!D246+Variance!J191),ABS(Variance!D247+Variance!J205),ABS(Variance!D248+Variance!J206),ABS(Variance!D249+Variance!J233),ABS(Variance!D250+Variance!J220),ABS(Variance!D251+Variance!J221),ABS(Variance!D252+Variance!J229),ABS(Variance!D253+Variance!J230),ABS(Variance!D254+Variance!J231)) -> 0 | E101: 0.01 | F101: =IF(ABS(D101)<=E101,"PASS","FAIL") -> PASS | G101: Expense effects reversed in contribution bridge
C103: Workbook architecture | D103: Measured issues / difference | E103: Tolerance | F103: Status | G103: Basis
C104: Exactly eight visible sheets remain in locked order | D104: 0 | E104: 0 | F104: =IF(ABS(D104)<=E104,"PASS","FAIL") -> PASS | G104: Verified by final package audit
C105: External workbook links | D105: 0 | E105: 0 | F105: =IF(ABS(D105)<=E105,"PASS","FAIL") -> PASS | G105: Verified by final package audit
C106: Hidden worksheets | D106: 0 | E106: 0 | F106: =IF(ABS(D106)<=E106,"PASS","FAIL") -> PASS | G106: Verified by final package audit
C107: Macros | D107: 0 | E107: 0 | F107: =IF(ABS(D107)<=E107,"PASS","FAIL") -> PASS | G107: Verified by final package audit
C108: Circular calculation | D108: 0 | E108: 0 | F108: =IF(ABS(D108)<=E108,"PASS","FAIL") -> PASS | G108: Verified by final package audit
C109: Volatile formulas | D109: 0 | E109: 0 | F109: =IF(ABS(D109)<=E109,"PASS","FAIL") -> PASS | G109: Verified by final formula audit
C110: Formulas outside Checks referencing Checks | D110: 0 | E110: 0 | F110: =IF(ABS(D110)<=E110,"PASS","FAIL") -> PASS | G110: Verified by final formula audit
C111: Budget remains independent of new analysis | D111: 0 | E111: 0 | F111: =IF(ABS(D111)<=E111,"PASS","FAIL") -> PASS | G111: Verified by final formula audit
C112: Forecast contains no forecast output | D112: 0 | E112: 0 | F112: =IF(ABS(D112)<=E112,"PASS","FAIL") -> PASS | G112: Verified by final workbook audit
...
